Homeworks/Homework 5/B63561/TARGET_I2C.v
module TARGET_I2C(
   // Inputs
   SDA_OUT, SDA_OE, SCL, RD_DATA, I2C_ADDR, CLK,
   // Outputs
   RESET, SDA_IN, reg_addr, WR_DATA
   );

  // Entradas y salidas
  output reg SDA_IN;
  output reg [15:0] WR_DATA; 
  output     [4:0] reg_addr;
  input RESET, SDA_OUT, SDA_OE, SCL, CLK;
  input [15:0] RD_DATA;
  input [6:0] I2C_ADDR;

  localparam INICIO       = 3'b001;
  localparam RECIBIR_BITS = 3'b010;
  localparam ENVIAR_BITS  = 3'b100;
  localparam STOP         = 3'b111;

  // Variables intermedias
  reg [2:0] estado, prox_estado;
  reg [4:0] cuenta_bits, prox_cuenta_bits;
  wire escritura, lectura;
  wire [1:0] start, op;
  wire [4:0] phy_addr;
  reg [31:0] transaccion;
  reg [6:0] I2C_ADDR_RECIBIDO, NXT_I2C_ADDR_RECIBIDO;
  reg SDA_OUT_reg, SDA_OUT_delay, SCL_anterior, flag, NXT_flag, NXT_SDA_IN;
  reg ACK1, NXT_ACK1, ACK2, NXT_ACK2;
  reg RNW_reg;
  reg NXT_posedge_SCL_1, posedge_SCL_1;
  reg BYTE1, NXT_BYTE1;

  assign escritura = (op[1:0] == 2'b01);
  assign lectura   =   (op == 2'b10);
  assign start     = transaccion[31:30];
  assign op        = transaccion[29:28];
  assign phy_addr  = transaccion[27:24];
  assign reg_addr  = transaccion[24:20];

  assign posedge_SCL = !SCL_anterior && SCL;

  // Flip flops
  always @(posedge SCL) begin
    if (!RESET) begin
      cuenta_bits    <= 0;
      SDA_OUT_reg    <= 1;
      SDA_OUT_delay  <= 1;
    end else begin
      SDA_OUT_reg <= SDA_OUT;
      SDA_OUT_delay <= SDA_OUT_reg;
    end
  end

  always @(posedge CLK) begin
    if (!RESET) begin
      estado  <= INICIO;
      flag    <= 0;
      ACK1    <= 0;
      ACK2    <= 0;
      BYTE1 <= 0;
    end else begin
      estado       <= prox_estado;
      SCL_anterior  <= SCL;
      cuenta_bits   <= prox_cuenta_bits;
      I2C_ADDR_RECIBIDO <= NXT_I2C_ADDR_RECIBIDO;
      flag <= NXT_flag;
      SDA_IN <= NXT_SDA_IN;
      ACK1          <= NXT_ACK1;
      ACK2          <= NXT_ACK2;
      BYTE1         <= NXT_BYTE1;
      posedge_SCL_1 <= NXT_posedge_SCL_1;
    end
  end

  // Logica combinacional

  always @(*) begin
    prox_estado = estado;
    prox_cuenta_bits = cuenta_bits;
    NXT_I2C_ADDR_RECIBIDO = I2C_ADDR_RECIBIDO;
    NXT_flag = flag;
    NXT_SDA_IN = SDA_IN;
    NXT_ACK1 = ACK1;
    NXT_posedge_SCL_1 = posedge_SCL_1;
    NXT_ACK2 = ACK2;
    NXT_BYTE1 = BYTE1;

    case (estado)
	    INICIO: 
        begin
          NXT_SDA_IN = 1;
		      prox_cuenta_bits = 0;
          NXT_I2C_ADDR_RECIBIDO = 0;
          WR_DATA = 0;
          if (SDA_OE) 
            begin
		          prox_estado = RECIBIR_BITS;
		        end
	      end

	    RECIBIR_BITS: 
        begin
          if (posedge_SCL) 
            begin

             NXT_flag = 1;

             if (flag) 
              begin
                if (SDA_IN && !ACK1 && !ACK2) 
                  begin 
                    if (cuenta_bits < 8) 
                      begin
                      prox_cuenta_bits = cuenta_bits+1;
                      if (cuenta_bits < 7) begin NXT_I2C_ADDR_RECIBIDO[6-cuenta_bits] = SDA_OUT; end
                      end

                    if (cuenta_bits > 7) 
                      begin
                        if (I2C_ADDR_RECIBIDO == I2C_ADDR)
                        begin 
                          if (!SDA_OE) 
                            begin
                              if (RNW_reg==1) begin 
                                prox_estado = ENVIAR_BITS; 
                                NXT_SDA_IN = 0;
                              end
                              else NXT_SDA_IN = 0;
                            end
                          prox_cuenta_bits = 0;
                        end
                        else prox_estado = INICIO;
                      end

                    if (cuenta_bits == 7) 
                      begin 
                        RNW_reg = SDA_OUT; 
                      end
                  end
                  
                
                if (!SDA_IN || ACK1)
                  begin 
                    NXT_posedge_SCL_1 = 1;
                    if (posedge_SCL_1) begin 
                    if (SDA_OUT == 1 || SDA_OUT == 0) begin
                    if (cuenta_bits < 8 ) 
                      begin
                        NXT_ACK1 = 1;
                        NXT_SDA_IN = 1;
                        prox_cuenta_bits = cuenta_bits+1;
                        WR_DATA[15-cuenta_bits] = SDA_OUT;
                      end

                    if (cuenta_bits==8) 
                      begin
                        if (!SDA_OE) NXT_SDA_IN = 0;
                      end 
                  end
                  end
                  end

                  if (!SDA_IN || ACK2) 
                  begin 
                    if (SDA_OUT == 1 || SDA_OUT == 0) begin
                    if (cuenta_bits > 7) 
                      begin
                        NXT_ACK2 = 1;
                        NXT_SDA_IN = 1;
                        prox_cuenta_bits = cuenta_bits+1;
                        if (cuenta_bits < 16) WR_DATA[15-cuenta_bits] = SDA_OUT;
                        if (cuenta_bits==15) NXT_SDA_IN = 0;
                      end
                    end
                   
                  end
              end
            end
            if (cuenta_bits == 16 && !SDA_OE) prox_estado = INICIO; 
            if (cuenta_bits > 7 && I2C_ADDR_RECIBIDO != I2C_ADDR) prox_estado = INICIO; 
        end

	    ENVIAR_BITS:
        begin 
                                                  // Enviando Primer Byte
              if (!SDA_IN || ACK1 )  
                begin
                  if (cuenta_bits < 9)
                  begin
                    NXT_ACK1 = 1;
                    if (posedge_SCL) 
                    begin
                      prox_cuenta_bits = cuenta_bits+1;
                      NXT_SDA_IN = RD_DATA[15-cuenta_bits];
                    end
                  end
                end
                                                      // Enviando Segundo Byte
              //if (!SDA_IN || ACK2)
              if (SDA_OUT || ACK2)
                begin
                  if (cuenta_bits > 8)
                    begin
                      NXT_ACK2 = 1;
                      if (posedge_SCL) 
                      begin
                        prox_cuenta_bits = cuenta_bits+1;
                        if (cuenta_bits < 16) NXT_SDA_IN = RD_DATA[15-cuenta_bits];
                      end
                    end
                end
              if (!SDA_IN) 
                begin 
                  if (cuenta_bits > 16) 
                    begin 
                      prox_estado = INICIO;
                    end
                end 
	    end

      
      default: begin end

    endcase;
  end
endmodule

Homeworks/Homework 5/B63561/CPU_I2C.v
module CPU_I2C(
   // Outputs
   SDA_OUT, SDA_OE, SCL, RD_DATA,

   // Inputs
   CLK, RESET, START_STB, SDA_IN, transaccion, RNW, I2C_ADDR, WR_DATA
   );

  // Entradas
  input CLK, RESET, START_STB, SDA_IN, RNW;
  input [31:0] transaccion;
  input [6:0] I2C_ADDR;
  input [15:0] WR_DATA;

  // Salidas
  output reg SDA_OUT, SDA_OE;
  output  SCL;
  output reg [15:0] RD_DATA;

  localparam INICIO    = 3'b001;
  localparam START     = 3'b000;
  localparam ESCRITURA = 3'b010;
  localparam LECTURA   = 3'b100;
  localparam STOP      = 3'b111;   
  localparam DIV_FREQ  = 2; // 25% del CLK

  // Variables intermedias
  reg [2:0] estado, prox_estado;
  reg [4:0] cuenta_bits, prox_cuenta_bits;
  reg [4:0] cuenta_bits_STOP, prox_cuenta_bits_STOP;
  reg [DIV_FREQ-1:0] div_freq;
  reg START_STB_d, START_STB_reg;
  wire iniciar, escritura, lectura;
  wire posedge_SCL;
  reg SCL_anterior, prox_SDA_OUT, SCL_reg, NXT_SDA_OE;
  reg SDA_OUT_anterior;
  reg ACK1, NXT_ACK1, ACK2, NXT_ACK2;
  reg START_CONDITION_ACTIVADA;
  reg BYTE1, NXT_BYTE1;
  reg NXT_posedge_SCL_1, posedge_SCL_1;
  reg NXT_posedge_SCL_2, posedge_SCL_2;

  // Condiciones de inicio y parada
  wire START_CONDITION;
  wire STOP_CONDITION;

  assign iniciar   = (transaccion[31:30] == 2'b01);
  assign escritura = (transaccion[29:28] == 2'b01);
  assign lectura = (transaccion[29:28] == 2'b10);

  // SCL es fraccion del CLK
  assign SCL = SCL_reg;

  assign posedge_SCL = !SCL_anterior && SCL;
  assign negedge_SDA_OUT = SDA_OUT_anterior && !SDA_OUT;
  assign posedge_SDA_OUT = !SDA_OUT_anterior && SDA_OUT;

  assign START_CONDITION = SCL && negedge_SDA_OUT;
  assign STOP_CONDITION  = SCL && posedge_SDA_OUT;

  // Flip flops
  always @(posedge CLK) begin
    if (!RESET) begin
      estado        <= INICIO;
      cuenta_bits   <= 0;
      cuenta_bits_STOP <= 0;
      div_freq      <= 0;
      SCL_anterior  <= 1;
      SDA_OUT_anterior <= 1;
      SDA_OUT       <= 1;
      SDA_OE        <= 0;
      START_STB_reg <= 0;
      START_STB_d   <= 0;
      ACK1 <= 0;
      ACK2 <= 0;
      BYTE1 <= 0;
    end else begin
      estado        <= prox_estado;
      cuenta_bits   <= prox_cuenta_bits;
      cuenta_bits_STOP <= prox_cuenta_bits_STOP;
      SDA_OE        <= NXT_SDA_OE;
      div_freq      <= div_freq+1;
      SCL_anterior  <= SCL;
      SDA_OUT_anterior <= SDA_OUT;
      SDA_OUT       <= prox_SDA_OUT;
      START_STB_reg <= START_STB;
      START_STB_d   <= START_STB_reg;
      ACK1          <= NXT_ACK1;
      posedge_SCL_1 <= NXT_posedge_SCL_1;
      posedge_SCL_2 <= NXT_posedge_SCL_2;
      ACK2          <= NXT_ACK2;
      BYTE1         <= NXT_BYTE1;
    end
  end

  //Logica combinacional

  always @(*) begin
    
    if (START_CONDITION || START_CONDITION_ACTIVADA)
      begin 
        START_CONDITION_ACTIVADA = 1;
        SCL_reg = div_freq[DIV_FREQ-1];
      end 
        else begin SCL_reg = 1'b1; end

    
    prox_estado = estado;
    prox_cuenta_bits = cuenta_bits;
    prox_cuenta_bits_STOP = cuenta_bits_STOP;
    prox_SDA_OUT = SDA_OUT;
    NXT_SDA_OE = SDA_OE;
    NXT_ACK1 = ACK1;
    NXT_posedge_SCL_1 = posedge_SCL_1;
    NXT_posedge_SCL_2 = posedge_SCL_2;
    NXT_ACK2 = ACK2;
    NXT_BYTE1 = BYTE1;


    case (estado)
	    INICIO: begin
		    NXT_SDA_OE = 1'b0;
        SDA_OUT = 1'b1;
		    prox_cuenta_bits = 0;
        NXT_posedge_SCL_1 = 0;
        RD_DATA = 0;
        
        if (START_STB) 
          begin
            prox_estado = START;
          end
        
	    end

      START: 
        begin
          prox_SDA_OUT = 0;
          if (RNW) prox_estado = LECTURA; 
          if (!RNW)  prox_estado = ESCRITURA;
        end

	    ESCRITURA: 
        begin
              if (!BYTE1) 
                begin 
                  NXT_SDA_OE = 1'b1;
                  if (posedge_SCL)
                    begin
                      prox_cuenta_bits = cuenta_bits+1;
                      prox_SDA_OUT = I2C_ADDR[6-cuenta_bits];
                      if (cuenta_bits == 7) 
                        begin  
                          prox_SDA_OUT = 0; 
                          prox_cuenta_bits = cuenta_bits+1;
                        end
                      if (cuenta_bits == 8) 
                        begin 
                          NXT_SDA_OE = 0; 
                          prox_SDA_OUT = 0; 
                          prox_cuenta_bits = 0;
                          NXT_BYTE1 = 1;
                        end
                      end
                end

              if (SDA_IN && BYTE1 && posedge_SCL) NXT_posedge_SCL_1 = 1;              // Pasa 1er posedge_SCL
              if (SDA_IN && BYTE1 && posedge_SCL_1 && !ACK1) prox_estado = STOP;      // No se recibio ACK1

              //if (SDA_IN && BYTE1 && posedge_SCL) NXT_posedge_SCL_1 = 1;              // Pasa 1er posedge_SCL
              //if (SDA_IN && BYTE1 && posedge_SCL_1 && !ACK1) NXT_posedge_SCL_2 = 1;   // No se recibio ACK1
              //if (SDA_IN && BYTE1 && posedge_SCL_2 && !ACK1) prox_estado = STOP; 

                                                                                      // Enviando Primer Byte
              if (!SDA_IN || ACK1 )  
                begin
                  if (cuenta_bits < 9)
                  begin
                    NXT_SDA_OE = 1'b1;
                    NXT_ACK1 = 1;
                    if (posedge_SCL) 
                    begin
                      prox_cuenta_bits = cuenta_bits+1;
                      prox_SDA_OUT = WR_DATA[15-cuenta_bits];
                      if (cuenta_bits == 8) NXT_SDA_OE = 0;
                    end
                  end
                end
                                                      // Enviando Segundo Byte
              if (!SDA_IN || ACK2)  
                begin
                  if (cuenta_bits > 8)
                    begin
                      NXT_SDA_OE = 1'b1;
                      NXT_ACK2 = 1;
                      if (posedge_SCL) 
                      begin
                        prox_cuenta_bits = cuenta_bits+1;
                        if (cuenta_bits < 16) prox_SDA_OUT = WR_DATA[15-cuenta_bits];
                      end
                    end
                end
              if (!SDA_IN) 
                begin 
                  if (cuenta_bits > 16) 
                    begin 
                      //prox_estado = STOP;
                      prox_SDA_OUT = 1;
                      SCL_reg = 1'b1;
                    end
                  if (STOP_CONDITION) prox_estado = STOP;
                end 
        end

	    LECTURA: 
        begin
          begin
              if (!BYTE1) 
                begin 
                  NXT_SDA_OE = 1'b1;
                  if (posedge_SCL)
                    begin
                      prox_cuenta_bits = cuenta_bits+1;
                      prox_SDA_OUT = I2C_ADDR[6-cuenta_bits];
                      if (cuenta_bits == 7) 
                        begin  
                          prox_SDA_OUT = 1; 
                          prox_cuenta_bits = cuenta_bits+1;
                        end
                      if (cuenta_bits == 8) 
                        begin 
                          NXT_SDA_OE = 0; 
                          prox_SDA_OUT = 0;
                          prox_cuenta_bits = 0;
                          NXT_BYTE1 = 1;
                        end
                      end
                end

              if (SDA_IN && BYTE1 && posedge_SCL) NXT_posedge_SCL_1 = 1;              // Pasa 1er posedge_SCL
              if (SDA_IN && BYTE1 && posedge_SCL_1 && !ACK1) prox_estado = STOP;      // No se recibio ACK1
              //if (SDA_IN && BYTE1 && posedge_SCL && !ACK1) prox_estado = STOP;      // No se recibio ACK1


                                                      // Recibo Primer Byte
              if (!SDA_IN || ACK1 )  
                begin
                  prox_SDA_OUT = 1;
                  if (posedge_SCL) NXT_ACK1 = 1;
                  if (ACK1 && cuenta_bits < 9)
                  begin
                    if (cuenta_bits == 8)
                      begin
                        NXT_SDA_OE = 1'b1;
                        prox_SDA_OUT = 0; 
                      end
                    if (posedge_SCL) 
                    begin
                      prox_cuenta_bits = cuenta_bits+1;
                      RD_DATA[15-cuenta_bits] = SDA_IN;
                    end
                  end

                end
                                                      // Recibo Segundo Byte
              if (!SDA_OUT || ACK2)  
                begin
                  if (cuenta_bits > 8)
                    begin
                      NXT_SDA_OE = 1'b0;
                      NXT_ACK2 = 1;
                      if (cuenta_bits < 15) prox_SDA_OUT = 1;
                      if (cuenta_bits > 16) prox_SDA_OUT = 0;
                      if (posedge_SCL) 
                        begin
                          //if (cuenta_bits > 15) prox_SDA_OUT = 0;
                          prox_cuenta_bits = cuenta_bits+1;
                          RD_DATA[15-cuenta_bits] = SDA_IN;
                        end
                    end
                end
              if (cuenta_bits > 16) 
                begin 
                  prox_estado = STOP;
                  SCL_reg = 1'b1;
                end
            end
        end

      STOP: 
        begin
          prox_cuenta_bits_STOP = cuenta_bits_STOP + 1;
          SCL_reg = 1'b1;
          START_CONDITION_ACTIVADA = 0;
          prox_SDA_OUT = 0;
          if (cuenta_bits_STOP == 3) begin 
            //prox_estado = INICIO; 
            prox_SDA_OUT = 1;
            prox_cuenta_bits_STOP = 0;
          end
          if (STOP_CONDITION) prox_estado = INICIO; 
        end 


      default: begin end
    endcase;
  end
endmodule

Homeworks/Homework 5/B63561/testbench_I2C.v
`include "CPU_I2C.v"
`include "TARGET_I2C.v"

// Testbench Code Goes here
module I2C_tb;

// Regs
reg         CLK, RESET_CPU, RESET_TARGET, START_STB, RNW;
reg  [31:0] transaccion;
reg [6:0]  I2C_ADDR_TARGET;
reg [6:0]  I2C_ADDR_CPU;
reg  [15:0] I2C_data_read, WR_DATA, RD_DATA;

// Wires
wire [15:0] I2C_data_write;
wire [15:0] reg_addr;
wire        SCL, SDA_IN, SDA_OUT, SDA_OE; 

initial begin
	$dumpfile("I2C.vcd");
	$dumpvars(-1, U0);
	$dumpvars(-1, U1);
end


initial begin
  CLK = 0;
  RESET_CPU = 1;
  RESET_TARGET  = 1;
  START_STB = 0;

  /*+++++++++++++++++++++++++++++++ PRUEBA #1 ESCRITURA +++++++++++++++++++++++++++++++*/
  
  #20  RESET_CPU = 0;
       RESET_TARGET  = 0;
  #120 RESET_CPU = 1;
  #180 RESET_TARGET  = 1; 
      START_STB = 1;
	  I2C_ADDR_CPU = 7'b0111101; // Calling TARGET #61
	  I2C_ADDR_TARGET = 7'b0111101;
	  WR_DATA = 16'h07CC;
      transaccion = 32'h5BA73549;
	  RNW = 0;
  #40 START_STB = 0;

  

	/*++++++++++++++++++++++++ PRUEBA #2 ESCRITURA Y RECEPTOR IGNORA ++++++++++++++++++*/

  #5500

  #80  RESET_CPU = 0;
       RESET_TARGET  = 0;
  #120 RESET_CPU = 1;
  #180 RESET_TARGET  = 1; 
      START_STB = 1;
	  I2C_ADDR_CPU = 7'b0000001; // Calling TARGET #01
	  I2C_ADDR_TARGET = 7'b0111101;
	  WR_DATA = 16'h07CC;
      transaccion = 32'h5BA73549;
	  RNW = 0;
  #40 START_STB = 0;
  
  #3000

  /*+++++++++++++++++++++++++++++++ PRUEBA #3 LECTURA +++++++++++++++++++++++++++++++*/
  
  #20  RESET_CPU = 0;
       RESET_TARGET  = 0;
  #120 RESET_CPU = 1;
  #180 RESET_TARGET  = 1; 
      START_STB = 1;
	  I2C_ADDR_CPU = 7'b0111101; // Calling TARGET #61
	  I2C_ADDR_TARGET = 7'b0111101;
	  RD_DATA = 16'h07E8;
      transaccion = 32'h5BA73549;
	  RNW = 1;
  #40 START_STB = 0;

  #5000

    /*+++++++++++++++++++ PRUEBA #4 LECTURA Y RECEPTOR IGNORA ++++++++++++++++++++++++*/
  
  #20  RESET_CPU = 0;
       RESET_TARGET  = 0;
  #120 RESET_CPU = 1;
  #180 RESET_TARGET  = 1; 
      START_STB = 1;
	  I2C_ADDR_CPU = 7'b0000001; // Calling TARGET #61
	  I2C_ADDR_TARGET = 7'b0111101;
	  RD_DATA = 16'h07E8;
      transaccion = 32'h5BA73549;
	  RNW = 1;
  #40 START_STB = 0;


  #16000 $finish;
end

always begin
 #20 CLK = !CLK;
end


CPU_I2C U0 (
/*AUTOINST*/
		   // Outputs
		   .SDA_OUT		(SDA_OUT),
		   .SDA_OE		(SDA_OE),
		   .SCL			(SCL),
		   // Inputs
		   .CLK			(CLK),
		   .RESET		(RESET_CPU),
		   .START_STB		(START_STB),
		   .SDA_IN		(SDA_IN),
		   .transaccion	(transaccion[31:0]),
		   .RNW         (RNW), 
		   .I2C_ADDR 	(I2C_ADDR_CPU),
		   .WR_DATA 	(WR_DATA)
		   );


TARGET_I2C U1 (
/*AUTOINST*/
		  // Outputs
		  .reg_addr		(reg_addr[4:0]),
		  .SDA_IN		(SDA_IN),
		  // Inputs
		  .SCL			(SCL),
		  .CLK			(CLK),
		  .RESET		(RESET_TARGET),
		  .SDA_OUT		(SDA_OUT),
		  .SDA_OE		(SDA_OE),
		  .RD_DATA   	(RD_DATA),
		  .I2C_ADDR  	(I2C_ADDR_TARGET)
		  );


endmodule

Homeworks/Homework 5/B63561/I2C.vcd
$date
	Wed Jun 19 21:20:53 2024
$end
$version
	Icarus Verilog
$end
$timescale
	1s
$end
$scope module I2C_tb $end
$scope module U0 $end
$var wire 1 ! CLK $end
$var wire 7 " I2C_ADDR [6:0] $end
$var wire 1 # RESET $end
$var wire 1 $ RNW $end
$var wire 1 % START_CONDITION $end
$var wire 1 & START_STB $end
$var wire 1 ' STOP_CONDITION $end
$var wire 16 ( WR_DATA [15:0] $end
$var wire 1 ) negedge_SDA_OUT $end
$var wire 1 * posedge_SCL $end
$var wire 1 + posedge_SDA_OUT $end
$var wire 32 , transaccion [31:0] $end
$var wire 1 - lectura $end
$var wire 1 . iniciar $end
$var wire 1 / escritura $end
$var wire 1 0 SDA_IN $end
$var wire 1 1 SCL $end
$var parameter 32 2 DIV_FREQ $end
$var parameter 3 3 ESCRITURA $end
$var parameter 3 4 INICIO $end
$var parameter 3 5 LECTURA $end
$var parameter 3 6 START $end
$var parameter 3 7 STOP $end
$var reg 1 8 ACK1 $end
$var reg 1 9 ACK2 $end
$var reg 1 : BYTE1 $end
$var reg 1 ; NXT_ACK1 $end
$var reg 1 < NXT_ACK2 $end
$var reg 1 = NXT_BYTE1 $end
$var reg 1 > NXT_SDA_OE $end
$var reg 1 ? NXT_posedge_SCL_1 $end
$var reg 1 @ NXT_posedge_SCL_2 $end
$var reg 16 A RD_DATA [15:0] $end
$var reg 1 B SCL_anterior $end
$var reg 1 1 SCL_reg $end
$var reg 1 C SDA_OE $end
$var reg 1 D SDA_OUT $end
$var reg 1 E SDA_OUT_anterior $end
$var reg 1 F START_CONDITION_ACTIVADA $end
$var reg 1 G START_STB_d $end
$var reg 1 H START_STB_reg $end
$var reg 5 I cuenta_bits [4:0] $end
$var reg 5 J cuenta_bits_STOP [4:0] $end
$var reg 2 K div_freq [1:0] $end
$var reg 3 L estado [2:0] $end
$var reg 1 M posedge_SCL_1 $end
$var reg 1 N posedge_SCL_2 $end
$var reg 1 O prox_SDA_OUT $end
$var reg 5 P prox_cuenta_bits [4:0] $end
$var reg 5 Q prox_cuenta_bits_STOP [4:0] $end
$var reg 3 R prox_estado [2:0] $end
$upscope $end
$upscope $end
$scope module I2C_tb $end
$scope module U1 $end
$var wire 1 ! CLK $end
$var wire 7 S I2C_ADDR [6:0] $end
$var wire 16 T RD_DATA [15:0] $end
$var wire 1 U RESET $end
$var wire 1 1 SCL $end
$var wire 1 C SDA_OE $end
$var wire 1 D SDA_OUT $end
$var wire 1 V posedge_SCL $end
$var wire 2 W start [1:0] $end
$var wire 5 X reg_addr [4:0] $end
$var wire 5 Y phy_addr [4:0] $end
$var wire 2 Z op [1:0] $end
$var wire 1 [ lectura $end
$var wire 1 \ escritura $end
$var parameter 3 ] ENVIAR_BITS $end
$var parameter 3 ^ INICIO $end
$var parameter 3 _ RECIBIR_BITS $end
$var parameter 3 ` STOP $end
$var reg 1 a ACK1 $end
$var reg 1 b ACK2 $end
$var reg 1 c BYTE1 $end
$var reg 7 d I2C_ADDR_RECIBIDO [6:0] $end
$var reg 1 e NXT_ACK1 $end
$var reg 1 f NXT_ACK2 $end
$var reg 1 g NXT_BYTE1 $end
$var reg 7 h NXT_I2C_ADDR_RECIBIDO [6:0] $end
$var reg 1 i NXT_SDA_IN $end
$var reg 1 j NXT_flag $end
$var reg 1 k NXT_posedge_SCL_1 $end
$var reg 1 l RNW_reg $end
$var reg 1 m SCL_anterior $end
$var reg 1 0 SDA_IN $end
$var reg 1 n SDA_OUT_delay $end
$var reg 1 o SDA_OUT_reg $end
$var reg 16 p WR_DATA [15:0] $end
$var reg 5 q cuenta_bits [4:0] $end
$var reg 3 r estado [2:0] $end
$var reg 1 s flag $end
$var reg 1 t posedge_SCL_1 $end
$var reg 5 u prox_cuenta_bits [4:0] $end
$var reg 3 v prox_estado [2:0] $end
$var reg 32 w transaccion [31:0] $end
$upscope $end
$upscope $end
$enddefinitions $end
$comment Show the parameter values. $end
$dumpall
b111 `
b10 _
b1 ^
b100 ]
b111 7
b0 6
b100 5
b1 4
b10 3
b10 2
$end
#0
$dumpvars
bx w
bx v
bx u
xt
xs
bx r
bx q
bx p
xo
xn
xm
xl
xk
xj
xi
bx h
xg
xf
xe
bx d
xc
xb
xa
x\
x[
bx Z
b0xxxx Y
bx X
bx W
xV
1U
bx T
bx S
bx R
bx Q
bx P
xO
xN
xM
bx L
bx K
bx J
bx I
xH
xG
xF
xE
xD
xC
xB
bx A
x@
x?
x>
x=
x<
x;
x:
x9
x8
11
x0
x/
x.
x-
bx ,
x+
x*
x)
bx (
x'
0&
x%
x$
1#
bx "
0!
$end
#20
0'
0%
0+
0)
0*
b0 A
0?
0=
0<
0;
0>
1O
b0 Q
b0 P
b1 R
b0 p
b0 h
b0 u
1i
0g
0f
0e
0j
b1 v
0:
09
08
0G
0H
0C
1D
1E
1B
b0 K
b0 J
b0 I
b1 L
0c
0b
0a
0s
b1 r
1!
0U
0#
#40
0!
#60
1!
#80
0!
#100
1!
#120
0!
#140
0M
b1 K
1!
1#
#160
0!
#180
b10 K
1!
#200
0!
#220
b11 K
1!
#240
0!
#260
b0 K
1!
#280
0!
#300
b1 K
1!
#320
1.
1/
0-
1i
b0 h
b0 u
b0 R
0!
0$
b1011011101001110011010101001001 ,
b11111001100 (
b111101 S
b111101 "
1&
1U
#340
b10 R
0O
0V
1H
b10 K
b0 L
10
b0 d
b0 q
1m
1!
#360
0O
b10 R
0!
0&
#380
1F
1%
1)
1>
1G
0H
0D
b11 K
b10 L
1!
#400
0!
#420
0%
0)
01
b10 v
0G
0E
b0 K
1C
1!
#440
0!
#460
0m
b10 r
0B
b1 K
1!
#480
0!
#500
0o
1j
b1 P
1V
1*
11
b10 K
1!
#520
0!
#540
0V
0*
0O
b1 P
1s
1m
1B
b11 K
b1 I
1!
#560
0!
#580
01
b0 K
1!
#600
0!
#620
0m
0B
b1 K
1!
#640
0!
#660
0n
b1 u
1O
b10 P
1V
1*
11
b10 K
1!
#680
0!
#700
1'
0V
b0 h
b1 u
1+
0*
b10 P
b1 q
1m
1D
1B
b11 K
b10 I
1!
#720
0!
#740
0'
0+
01
1E
b0 K
1!
#760
0!
#780
0m
0B
b1 K
1!
#800
0!
#820
1o
b100000 h
b10 u
b11 P
1V
1*
11
b10 K
1!
#840
0!
#860
0V
0*
b11 P
b100000 d
b10 q
1m
1B
b11 K
b11 I
1!
#880
0!
#900
01
b0 K
1!
#920
0!
#940
0m
0B
b1 K
1!
#960
0!
#980
1n
b110000 h
b11 u
b100 P
1V
1*
11
b10 K
1!
#1000
0!
#1020
0V
0*
b100 P
b110000 d
b11 q
1m
1B
b11 K
b100 I
1!
#1040
0!
#1060
01
b0 K
1!
#1080
0!
#1100
0m
0B
b1 K
1!
#1120
0!
#1140
b111000 h
b100 u
b101 P
1V
1*
11
b10 K
1!
#1160
0!
#1180
0V
0*
1O
b101 P
b111000 d
b100 q
1m
1B
b11 K
b101 I
1!
#1200
0!
#1220
01
b0 K
1!
#1240
0!
#1260
0m
0B
b1 K
1!
#1280
0!
#1300
b111100 h
b101 u
0O
b110 P
1V
1*
11
b10 K
1!
#1320
0!
#1340
1%
0V
1)
b101 u
0*
0O
b110 P
b111100 d
b101 q
1m
0D
1B
b11 K
b110 I
1!
#1360
0!
#1380
0%
0)
01
0E
b0 K
1!
#1400
0!
#1420
0m
0B
b1 K
1!
#1440
0!
#1460
0o
b110 u
1O
b111 P
1V
1*
11
b10 K
1!
#1480
0!
#1500
1'
0V
b111100 h
b110 u
1+
0*
1O
b111 P
b110 q
1m
1D
1B
b11 K
b111 I
1!
#1520
0!
#1540
0'
0+
01
1E
b0 K
1!
#1560
0!
#1580
0m
0B
b1 K
1!
#1600
0!
#1620
0n
1o
b111101 h
b111 u
0O
b1000 P
1V
1*
11
b10 K
1!
#1640
0!
#1660
1%
0V
1)
0l
b111 u
0*
0=
1>
0O
b1000 P
b111101 d
b111 q
1m
0D
1B
b11 K
b1000 I
1!
#1680
0!
#1700
0%
0)
01
0E
b0 K
1!
#1720
0!
#1740
0m
0B
b1 K
1!
#1760
0!
#1780
1n
0o
b1000 u
1=
0>
0O
b0 P
1V
1*
11
b10 K
1!
#1800
0!
#1820
0V
0*
b1000 u
1i
0?
b1000 q
1m
1:
1B
b11 K
0C
b0 I
1!
#1840
0!
#1860
01
b0 K
1!
#1880
0!
#1900
0m
0B
b1 K
1!
#1920
0!
#1940
0n
b0 u
0i
1?
1V
1*
11
b10 K
1!
#1960
0!
#1980
0V
0*
b0 P
1;
1>
00
b0 q
1m
1M
1B
b11 K
1!
#2000
0!
#2020
01
18
b0 K
1C
1!
#2040
0!
#2060
0m
0B
b1 K
1!
#2080
0!
#2100
1k
b1 P
1V
1*
11
b10 K
1!
#2120
0!
#2140
0V
0*
b1 P
1t
1m
1B
b11 K
b1 I
1!
#2160
0!
#2180
01
b0 K
1!
#2200
0!
#2220
0m
0B
b1 K
1!
#2240
0!
#2260
b1 u
1i
1e
b10 P
1V
1*
11
b10 K
1!
#2280
0!
#2300
0V
0*
b10 P
1a
10
b1 q
1m
1B
b11 K
b10 I
1!
#2320
0!
#2340
01
b0 K
1!
#2360
0!
#2380
0m
0B
b1 K
1!
#2400
0!
#2420
b10 u
b11 P
1V
1*
11
b10 K
1!
#2440
0!
#2460
0V
0*
b11 P
b10 q
1m
1B
b11 K
b11 I
1!
#2480
0!
#2500
01
b0 K
1!
#2520
0!
#2540
0m
0B
b1 K
1!
#2560
0!
#2580
b11 u
b100 P
1V
1*
11
b10 K
1!
#2600
0!
#2620
0V
0*
b100 P
b11 q
1m
1B
b11 K
b100 I
1!
#2640
0!
#2660
01
b0 K
1!
#2680
0!
#2700
0m
0B
b1 K
1!
#2720
0!
#2740
b100 u
b101 P
1V
1*
11
b10 K
1!
#2760
0!
#2780
0V
0*
0O
b101 P
b100 q
1m
1B
b11 K
b101 I
1!
#2800
0!
#2820
01
b0 K
1!
#2840
0!
#2860
0m
0B
b1 K
1!
#2880
0!
#2900
b101 u
1O
b110 P
1V
1*
11
b10 K
1!
#2920
0!
#2940
1'
0V
b10000000000 p
b101 u
1+
0*
b110 P
b101 q
1m
1D
1B
b11 K
b110 I
1!
#2960
0!
#2980
0'
0+
01
1E
b0 K
1!
#3000
0!
#3020
0m
0B
b1 K
1!
#3040
0!
#3060
1o
b110 u
b111 P
1V
1*
11
b10 K
1!
#3080
0!
#3100
0V
0*
b111 P
b110 q
1m
1B
b11 K
b111 I
1!
#3120
0!
#3140
01
b0 K
1!
#3160
0!
#3180
0m
0B
b1 K
1!
#3200
0!
#3220
1n
b11000000000 p
b111 u
b1000 P
1V
1*
11
b10 K
1!
#3240
0!
#3260
0V
0*
1>
b1000 P
b111 q
1m
1B
b11 K
b1000 I
1!
#3280
0!
#3300
01
b0 K
1!
#3320
0!
#3340
0m
0B
b1 K
1!
#3360
0!
#3380
b11100000000 p
b1000 u
0>
b1001 P
1V
1*
11
b10 K
1!
