Homeworks/Homework 1/tester.v
module tester (
  clock, 
  reset, 
  sensor_a,
  sensor_b,
  pin_validation,
  pin,
  alarma_pin_incorrecto,
  alarma_bloqueo,
  senal_abrir_compuerta,
  senal_cerrar_compuerta);

  output clock, reset, sensor_a, sensor_b, pin_validation;
  output reg [7:0] pin;
  input alarma_pin_incorrecto, alarma_bloqueo, senal_abrir_compuerta, senal_cerrar_compuerta;

  reg clock, reset, sensor_a, sensor_b, pin_validation;
  wire alarma_pin_incorrecto, alarma_bloqueo, senal_abrir_compuerta, senal_cerrar_compuerta;

// Periodo T = 10s
  initial begin

    // Todas las senales, salidas y variables internas a su estado inicial
    clock = 0;
    reset = 0;
    sensor_a = 0;
    sensor_b = 0;
    pin = 8'b00000000;
    pin_validation = 0;

    // Boton reset
    #5 reset = 1;
    #5 reset = 0;

    // Nota: Las pruebas se pueden comentar e ir probando una por una.

    // Prueba 1: Funcionamiento normal basico

    #10 sensor_a = 1;                                             // Llega vehiculo, sensor A se activa. Estado a.
    #20 {pin,pin_validation} = {8'b00111101,1'b1};                // Ingreso de pin correcto. Estado b -> c. 
    #10 pin_validation = 1'b0;                                    // Para que no vuelva a leer el pin
    #5 sensor_a = 0;                                              // Sensor A se desactiva
    #30 sensor_b = 1;                                             // Sensor B se activa. Estado -> f.
    #30 sensor_b = 0;                                             // Sensor B inactivo en este punto indica que 
                                                                  // se regresa a estado a.

    // Prueba 2: Ingreso de pin incorrecto menos de 3 veces

    #10 sensor_a = 1;                                             // Llega vehiculo, sensor A se activa. Estado a.
                                                                  // Estado b:
    #20 {pin,pin_validation} = {8'b00111111,1'b1};                // Ingreso de pin incorrecto (primera) + señal para leer pin
    #10 pin_validation = 1'b0;                                    // Para que no vuelva a leer el pin
    #20 {pin,pin_validation} = {8'b01111101,1'b1};                // Ingreso de pin correcto (segunda) + señal para leer pin
    #10 pin_validation = 1'b0;                                    // Para que no vuelva a leer el pin
    #20 {pin,pin_validation} = {8'b00111101,1'b1};                // Ingreso de pin correcto + señal para leer pin
    #10 pin_validation = 1'b0;                                    // Para que no vuelva a leer el pin
    #5 sensor_a = 0;                                              // Sensor A se desactiva
    #30 sensor_b = 1;                                             // Sensor B se activa
    #30 sensor_b = 0;                                             // Sensor B inactivo en este punto indica que 
                                                                  // se regresa a estado a.

    // Prueba 3: Ingreso de pin incorrecto 3 veces o más

    #10 sensor_a = 1;                                             // Llega vehiculo, sensor A se activa. Estado a.
                                                                  // Estado b:
    #20 {pin,pin_validation} = {8'b00111111,1'b1};                // Ingreso de pin incorrecto (primera) + señal para leer pin
    #10 pin_validation = 1'b0;                                    // Para que no vuelva a leer el pin
    #20 {pin,pin_validation} = {8'b01111101,1'b1};                // Ingreso de pin correcto (segunda) + señal para leer pin
    #10 pin_validation = 1'b0;                                    // Para que no vuelva a leer el pin
    #20 {pin,pin_validation} = {8'b11111101,1'b1};                // Ingreso de pin correcto (tercera) + señal para leer pin
    #10 pin_validation = 1'b0;                                    // Para que no vuelva a leer el pin
                                                                  // Se ingresa a estado d:
    #20 {pin,pin_validation} = {8'b01111111,1'b1};                // Ingreso de pin correcto (cuarta) + señal para leer pin
    #10 pin_validation = 1'b0;                                    // Para que no vuelva a leer el pin
    #20 {pin,pin_validation} = {8'b00111101,1'b1};                // Ingreso de pin correcto + señal para leer pin
    #10 pin_validation = 1'b0;                                    // Para que no vuelva a leer el pin
                                                                  // Se ingresa a estado c:
    #5 sensor_a = 0;                                              // Sensor A se desactiva
    #30 sensor_b = 1;                                             // Sensor B se activa
    #30 sensor_b = 0;                                             // Sensor B inactivo en este punto indica que 
                                                                  // se regresa a estado a.

    // Prueba 4: Alarma de bloqueo.

    #10 sensor_a = 1;                                             // Llega vehiculo, sensor A se activa. Estado a.
                                                                  // Estado b:
    #20 {pin,pin_validation} = {8'b00111101,1'b1};                // Ingreso de pin correcto + señal para leer pin
    #10 pin_validation = 1'b0;                                    // Para que no vuelva a leer el pin
                                                                  // Se ingresa a estado c:
    #5 sensor_a = 0;                                              // Sensor A se desactiva de forma rutinaria
    #5 sensor_a = 1;                                              // Sensor A se activa de pronto
    #35 sensor_b = 1;                                             // Sensor B se activa
                                                                  // Ambos sensores encendidos al mismo tiempo:
                                                                  // Se ingresa al estado e:
    #20 {pin,pin_validation} = {8'b00111111,1'b1};                // Ingreso de pin incorrecto + señal para leer pin
    #10 pin_validation = 1'b0;                                    // Para que no vuelva a leer el pin

    #20 {pin,pin_validation,sensor_a} = {8'b00111101,1'b1,1'b0};  // Ingreso de pin correcto + señal para leer pin 
                                                                  // + desactivacion sensor A
    #10 pin_validation = 1'b0;                                    // Para que no vuelva a leer el pin
                                                                  // Continua el funcionamiento normal basico:
    #30 sensor_b = 0;                                             // Sensor B inactivo en este punto indica que
                                                                  // se regresa a estado a.

    #50 $finish;
  end

  always begin
    #5 clock = !clock;                                            // Cada 5s cambia de estado (alto o bajo) el clock
  end

endmodule

Homeworks/Homework 1/controlador.v
// Maquina de estados para el controlador del estacionamiento
// Autor: Alonso José Jiménez Anchía

// **Declaracion del modulo**

// Argumentos del modulo son todos los puertos
// de entrada y de salida
module controlador (
    clock,
    reset,
    sensor_a,
    sensor_b,
    pin_validation,
    pin,
    alarma_pin_incorrecto,
    alarma_bloqueo,
    senal_abrir_compuerta,
    senal_cerrar_compuerta,
    );

// **Entradas**
input clock, reset, sensor_a, sensor_b, pin_validation;
input [7:0] pin;

// **Salidas**
output reg alarma_pin_incorrecto, alarma_bloqueo;
output reg senal_abrir_compuerta, senal_cerrar_compuerta;

// **Variables Internas**

// Estados de 3 bits tal que 2^3=8 estados posibles en total
reg [2:0] state;

// Para guardar un estado anterior
reg [2:0] old_state;

// Para guardar siguiente estado anterior
reg [2:0] next_old_state;

// Contador de 5 bits => Cuenta hasta 2^5=32
reg [4:0] i;

// Proximo estado tambien es una variable de 3 bits
reg [2:0] nxt_state;

// Siguiente valor de contador tambien de 5 bits
reg [4:0] nxt_i;  

// Siguientes valores de salidas son reg de 1 bit
reg [1:0] next_alarma_pin_incorrecto;
reg [1:0] next_alarma_bloqueo;
reg [1:0] next_senal_abrir_compuerta;
reg [1:0] next_senal_cerrar_compuerta;


// Cable auxiliar para saber cuando sensor a y sensor b están, ambos
// en estado alto y así tener la condición para ingresar al estado e.
wire Y;

//Ambas variables almacenadas en registros hechos con FF de flanco positivo.
// Un FF por bit de cada variable.
always @(posedge clock) begin
  if (reset) begin
    state  <= 3'b000;
    i <= 5'b00000;
    alarma_pin_incorrecto <= 0;
    alarma_bloqueo <= 0;
    senal_abrir_compuerta <= 0;
    senal_cerrar_compuerta <= 0;
    old_state <= 0;
  end else begin
    state  <= nxt_state;
    i <= nxt_i;
    alarma_pin_incorrecto <= next_alarma_pin_incorrecto;
    alarma_bloqueo <= next_alarma_bloqueo;
    senal_abrir_compuerta <= next_senal_abrir_compuerta;
    senal_cerrar_compuerta <= next_senal_cerrar_compuerta;
    old_state <= next_old_state;
  end
end  //Fin de los flip flops

// **Logica combinacional**

always @(*) begin

// Valores por defecto

  nxt_state = state;                                              // Para completar el comportamiento del FF se necesita
                                                                  // que por defecto el nxt_state sostenga el valor del 
                                                                  // estado anterior
  nxt_i = i;                                                      // Igual al caso de state y nxt_state, para garantizar el 
                                                                  // comportamiento del FF. 

// Comportamiento de la maquina de estados
// Define las transiciones de proximo estado segun el diagrama ASM
// visto en clase y el comportamiento de "valid" y "count0" en el 
// ultimo estado, segun la especificacion.

  case(state)
    3'b000: begin                                                  // Estado a, #0
                 if (Y) begin                                      // Se revisa si sensorA=SensorB=activados
                    next_alarma_bloqueo = 1;                            // Se activa alarma de bloqueo
                    next_senal_abrir_compuerta = 0;                     // Senal abrir compuerta se bloquea
                    next_senal_cerrar_compuerta = 0;                    // Senal cerrar compuerta se bloquea
                    next_old_state = state;                             // Se guarda estado actual
                    nxt_state = 3'b100;                            // Siguiente estado e, estado bloqueante.
                 end

                  next_senal_cerrar_compuerta = 0;                      // Senal cerrar compuerta en estado bajo
                  next_alarma_pin_incorrecto=0;                         // Alarma pin incorrecto desactivada
                  next_alarma_bloqueo=0;                                // Alarma bloqueo desactivada
                  next_senal_abrir_compuerta=0;                         // Senal abrir compuerta desactivada
                  next_senal_cerrar_compuerta=0;                        // Senal cerrar compuerta desactivada
                  if (sensor_a && ~sensor_b) nxt_state = 3'b001;
    end
                                                                   // Solo salimos de este estado cuando sensor_a=1'b1

    3'b001: begin                                                  // Estado b, #1

                 if (Y) begin                                      // Se revisa si sensorA=SensorB=activados
                    next_alarma_bloqueo = 1;                       // Se activa alarma de bloqueo
                    next_senal_abrir_compuerta = 0;                // Senal abrir compuerta se bloquea
                    next_senal_cerrar_compuerta = 0;               // Senal cerrar compuerta se bloquea
                    next_old_state = state;                        // Se guarda estado actual
                    nxt_state = 3'b100;                            // Siguiente estado e, estado bloqueante.
                 end

                 if (pin == 8'b00111101 && pin_validation) begin
                  nxt_state = 3'b010;                              // Estado siguiente -> c
                  nxt_i = 0;                                       // Siguiente flanco i = 0        
                 end
                 if (pin != 8'b00111101 && pin_validation) begin   // Si pin incorrecto + validacion: 
                  nxt_i = i + 1;                                   // i++ en sig. flanco
                 end
                 if (i>=3) begin                                   // Si contador lleva 3 o más pines incorrectos
                    next_alarma_pin_incorrecto = 1;                // Se activa API: Alarma por pin incorrecto.
                    nxt_state <= 3'b011;                           // Estado siguiente -> d.
                 end
               end

    3'b010: begin                                                  // Estado c, #2
                 if (Y) begin                                      // Se revisa si sensorA=SensorB=activados
                    next_alarma_bloqueo = 1;                            // Se activa alarma de bloqueo
                    next_senal_abrir_compuerta = 0;                     // Senal abrir compuerta se bloquea
                    next_senal_cerrar_compuerta = 0;                    // Senal cerrar compuerta se bloquea
                    next_old_state = state;                             // Se guarda estado actual
                    nxt_state = 3'b100;                            // Siguiente estado e, estado bloqueante.
                 end
                 else begin
                    next_senal_abrir_compuerta = 1;                     // Senal para abrir compuerta se activa
                    if (sensor_b && ~sensor_a) begin               // Si sensor A = ON & sensor B = OFF
                    next_alarma_bloqueo = 0;                            // Se desactiva alarma de bloqueo
                    nxt_state = 3'b101;                            // Estado siguiente -> f
                    end
                 end
               end

    3'b011: begin                                                  // Estado d, #3
                 if (Y) begin                                      // Se revisa si sensorA=SensorB=activados
                    next_alarma_bloqueo = 1;                       // Se activa alarma de bloqueo
                    next_senal_abrir_compuerta = 0;                // Senal abrir compuerta se bloquea
                    next_senal_cerrar_compuerta = 0;               // Senal cerrar compuerta se bloquea
                    next_old_state = state;                        // Se guarda estado actual
                    nxt_state = 3'b100;                            // Siguiente estado e, estado bloqueante.
                 end
                 else begin
                    next_alarma_pin_incorrecto = 1;                 // Alarma por pin incorrecto se activa
                    if (pin == 8'b00111101 && pin_validation) begin // Si pin es correcto:
                        nxt_i = 5'b00000;                           // Se reinicia contador
                        nxt_state = 3'b010;                         // Estado siguiente -> c
                    end
                    if (pin != 8'b00111101 && pin_validation) begin
                      nxt_i = i + 1;                                // i++
                    end
                 end
               end  
    3'b100: begin                                                   // Estado e, #4
                next_alarma_bloqueo = 1;                            // Se activa alarma de bloqueo
                next_senal_abrir_compuerta = 0;                     // Senal abrir compuerta se bloquea
                if (pin == 8'b00111101 && pin_validation) begin     // Si pin es correcto:
                    nxt_state = old_state;                          // Estado siguiente -> f
                 end

              end

    3'b101: begin                                                   // Estado f, #5
                  if (Y) begin                                      // Se revisa si sensorA=SensorB=activados
                      next_alarma_bloqueo = 1;                      // Se activa alarma de bloqueo
                      next_senal_abrir_compuerta = 0;               // Senal abrir compuerta se bloquea
                      next_senal_cerrar_compuerta = 0;              // Senal cerrar compuerta se bloquea
                      next_old_state = state;                       // Se guarda estado actual
                      nxt_state = 3'b100;                           // Siguiente estado e, estado bloqueante.
                 end
                 else begin
                      next_alarma_bloqueo = 0;                      // Se desactiva alarma de bloqueo
                      next_senal_abrir_compuerta = 0;               // Senal para abrir compuerta se desactiva
                      next_senal_cerrar_compuerta = 1;              // Senal para cerrar compuerta se activa
                      if (~sensor_b) begin                          // Cuando sensor B se inactive:
                                        nxt_state = 3'b000;         // Estado siguiente -> a
                                    end
                 end

              end                                              

    default:   nxt_state = 3'b000;                                  // Si la maquina entrara en un estado 
                                                                    // inesperado, regrese al inicio.
  endcase

end                                                                 // Este end corresponde al always @(*)
                                                                    // de la logica combinacional

                                                                    // Variable Y en estado alto permite ingreso al estado e.
assign Y = sensor_a & sensor_b;                                     // En cualquier momento, si sensor_a=sensor_b=1 entonces Y=1

endmodule

Homeworks/Homework 1/testbench.v
// Para poder instanciar los modulos controlador y tester:
`include "tester.v"
`include "controlador.v"

// Testbench Code Goes here
module controlador_tb;

  // Modulo del testbench necesita cables para conectar los modulos controlador con tester
  wire clock, reset, sensor_a, sensor_b, pin_validation;
  wire [7:0] pin;
  wire alarma_pin_incorrecto, alarma_bloqueo, senal_abrir_compuerta, senal_cerrar_compuerta;

  initial begin
    // Los resultados del testbench se guardan en resultados.vcd
	  $dumpfile("resultados.vcd");
    // Todas las variables y señales del modulo U0 serán registradas en el archivo resultados.vcd
	  $dumpvars(-1, U0);
    // Para mostrar los valores de variables o expresiones durante la simulación.
	  $monitor ("sensor_a=%b,sensor_b=%b,pin_validation=%b,pin=%b,alarma_pin_incorrecto=%b,alarma_bloqueo=%b,senal_abrir_compuerta=%b,senal_cerrar_compuerta=%b",
    sensor_a,sensor_b,pin_validation,pin,alarma_pin_incorrecto,
    alarma_bloqueo,senal_abrir_compuerta,senal_cerrar_compuerta);
  end

  controlador U0 (

    // Se conectan los cables del modulo controlador con los mismos cables pero del testbench
    .clock (clock),
    .reset (reset),
    .sensor_a (sensor_a),
    .sensor_b (sensor_b),
    .pin_validation (pin_validation), 
    .pin (pin),
    .alarma_pin_incorrecto (alarma_pin_incorrecto), 
    .alarma_bloqueo (alarma_bloqueo), 
    .senal_abrir_compuerta (senal_abrir_compuerta), 
    .senal_cerrar_compuerta (senal_cerrar_compuerta)
  );

  tester P0 (
    // Se conectan los cables del modulo tester con los mismos cables pero del testbench
    .clock (clock),
    .reset (reset),
    .sensor_a (sensor_a),
    .sensor_b (sensor_b),
    .pin_validation (pin_validation),
    .pin (pin),
    .alarma_pin_incorrecto (alarma_pin_incorrecto), 
    .alarma_bloqueo (alarma_bloqueo), 
    .senal_abrir_compuerta (senal_abrir_compuerta), 
    .senal_cerrar_compuerta (senal_cerrar_compuerta)
  );

endmodule

Homeworks/Homework 1/resultados.vcd
$date
	Sat May  4 08:22:37 2024
$end
$version
	Icarus Verilog
$end
$timescale
	1s
$end
$scope module controlador_tb $end
$scope module U0 $end
$var wire 1 ! Y $end
$var wire 1 " clock $end
$var wire 8 # pin [7:0] $end
$var wire 1 $ pin_validation $end
$var wire 1 % reset $end
$var wire 1 & sensor_a $end
$var wire 1 ' sensor_b $end
$var reg 1 ( alarma_bloqueo $end
$var reg 1 ) alarma_pin_incorrecto $end
$var reg 5 * i [4:0] $end
$var reg 2 + next_alarma_bloqueo [1:0] $end
$var reg 2 , next_alarma_pin_incorrecto [1:0] $end
$var reg 3 - next_old_state [2:0] $end
$var reg 2 . next_senal_abrir_compuerta [1:0] $end
$var reg 2 / next_senal_cerrar_compuerta [1:0] $end
$var reg 5 0 nxt_i [4:0] $end
$var reg 3 1 nxt_state [2:0] $end
$var reg 3 2 old_state [2:0] $end
$var reg 1 3 senal_abrir_compuerta $end
$var reg 1 4 senal_cerrar_compuerta $end
$var reg 3 5 state [2:0] $end
$upscope $end
$upscope $end
$enddefinitions $end
$comment Show the parameter values. $end
$dumpall
$end
#0
$dumpvars
bx 5
x4
x3
bx 2
b0 1
bx 0
bx /
bx .
bx -
bx ,
bx +
bx *
x)
x(
0'
0&
0%
0$
b0 #
0"
0!
$end
#5
b0 .
b0 +
b0 ,
b0 /
b0 0
b0 2
04
03
0(
0)
b0 *
b0 5
1"
1%
#10
0"
0%
#15
bx 2
1"
#20
b1 1
0"
1&
#25
b1 5
1"
#30
0"
#35
1"
#40
b10 1
0"
b111101 #
1$
#45
b1 .
b10 5
1"
#50
0"
0$
#55
13
1"
0&
#60
0"
#65
1"
#70
0"
#75
1"
#80
0"
#85
b1 /
b0 .
b101 5
b101 1
1"
1'
#90
0"
#95
14
03
1"
#100
0"
#105
1"
#110
0"
#115
b0 /
b0 5
b0 1
1"
0'
#120
0"
#125
04
b1 5
b1 1
1"
1&
#130
0"
#135
1"
#140
0"
#145
b1 *
b10 0
1"
b111111 #
1$
#150
0"
#155
b1 0
1"
0$
#160
0"
#165
1"
#170
0"
#175
b10 *
b11 0
1"
b1111101 #
1$
#180
0"
#185
b10 0
1"
0$
#190
0"
#195
1"
#200
0"
#205
b1 .
b0 *
b10 5
b0 0
b10 1
1"
b111101 #
1$
#210
0"
#215
13
1"
0$
#220
0"
0&
#225
1"
#230
0"
#235
1"
#240
0"
#245
1"
#250
b101 1
0"
1'
#255
b1 /
b0 .
b101 5
1"
#260
0"
#265
14
03
1"
#270
0"
#275
1"
#280
b0 1
0"
0'
#285
b0 /
b0 5
1"
#290
b1 1
0"
1&
#295
04
b1 5
1"
#300
0"
#305
1"
#310
b1 0
0"
b111111 #
1$
#315
b10 0
b1 *
1"
#320
b1 0
0"
0$
#325
1"
#330
0"
#335
1"
#340
b10 0
0"
b1111101 #
1$
#345
b11 0
b10 *
1"
#350
b10 0
0"
0$
#355
1"
#360
0"
#365
1"
#370
b11 0
0"
b11111101 #
1$
#375
b11 1
b1 ,
b100 0
b11 *
1"
#380
b11 0
b11 1
0"
0$
#385
1)
b11 5
1"
#390
0"
#395
1"
#400
b100 0
0"
b1111111 #
1$
#405
b101 0
b100 *
1"
#410
b100 0
0"
0$
#415
1"
#420
0"
#425
1"
#430
b10 1
b0 0
0"
b111101 #
1$
#435
b1 .
b0 *
b10 5
1"
#440
0"
0$
#445
13
1"
0&
#450
0"
#455
1"
#460
0"
#465
1"
#470
0"
#475
b1 /
b0 .
b101 5
b101 1
1"
1'
#480
0"
#485
14
03
1"
#490
0"
#495
1"
#500
0"
#505
b0 ,
b0 /
b0 5
b0 1
1"
0'
#510
0"
#515
04
0)
b1 5
b1 1
1"
1&
#520
0"
#525
1"
#530
0"
#535
b1 .
b10 5
b10 1
1"
1$
#540
0"
#545
13
1"
0$
#550
0"
0&
#555
1"
1&
#560
0"
#565
1"
#570
0"
#575
1"
#580
0"
#585
1"
#590
b100 1
b10 -
b0 .
b1 +
1!
0"
1'
#595
b10 2
03
1(
b100 5
1"
#600
0"
#605
1"
#610
0"
b111111 #
1$
#615
1"
#620
0"
0$
#625
1"
#630
0"
#635
1"
#640
0!
b10 1
0"
b111101 #
1$
0&
#645
b101 1
b0 +
b1 .
b10 5
1"
#650
b101 1
0"
0$
#655
b1 /
b0 .
13
0(
b101 5
1"
#660
0"
#665
14
03
1"
#670
0"
#675
1"
#680
b0 1
0"
0'
#685
b0 /
b0 5
1"
#690
0"
#695
04
1"
