Homeworks/Homework 4/target_spi.v
module target_spi(
   // Inputs
   MOSI, SCK, SS, CKP, CPH, RESET,
   // Outputs
   MISO
   );

  // Entradas
  input MOSI, SCK, SS, CKP, CPH, RESET;

  // Salidas
  output reg MISO;

  // Parametros
  localparam IDLE = 3'b001;
  localparam ESCRITURA_LECTURA = 3'b010;

  // Variables intermedias
  reg [2:0]  estado, prox_estado;
  reg [4:0] cuenta_bits, prox_cuenta_bits;
  reg NXT_MISO;
  reg [15:0] dato_recibido, prox_dato_recibido;
  reg [15:0] dato_enviado, prox_dato_enviado;
  reg [7:0] quinto_digito;                                // 5th digit of my carnet
  reg [7:0] sexto_digito;                                 // 6th digit of my carnet
  reg SS_d, MISO_d;
  wire posedge_SS;

  // DETECCION DEL FLANCO POSITIVO DE SS
  assign posedge_SS = SS && !SS_d;

  // Fip flops
  always @(posedge SCK) begin
    if (RESET || posedge_SS) begin
      estado        <= IDLE;
      cuenta_bits   <= 0;
      MISO <= 0;
      dato_recibido <= 0;
      dato_enviado <= 16'b0000011000000001;
      SS_d   <= 0;
    end else begin
      estado        <= prox_estado;
      cuenta_bits   <= prox_cuenta_bits;
      MISO          <= NXT_MISO;
      dato_recibido <= prox_dato_recibido;
      dato_enviado  <= prox_dato_enviado;
      SS_d   <= SS;

    end
  end //Fin de los FFs

  //Logica combinacional

  always @(*) begin
    prox_estado = estado;
    prox_cuenta_bits = cuenta_bits;
    NXT_MISO = MISO;

    case (estado)
	    IDLE: 
          begin
            prox_cuenta_bits = 0;
            if (~SS)   prox_estado = ESCRITURA_LECTURA;
          end

      ESCRITURA_LECTURA: 
          begin
              prox_cuenta_bits = cuenta_bits+1;
              NXT_MISO = dato_enviado[15-cuenta_bits];                          // Sending data
              dato_recibido[15-cuenta_bits] = MOSI;                             // Receiving data

            if (cuenta_bits == 15) prox_estado = IDLE;  
          end
      default: begin
                prox_estado = IDLE;
	             end
    endcase;
  end
endmodule

Homeworks/Homework 4/CPU_spi.v
module CPU_spi(/*AUTOARG*/
   // Outputs
   MOSI, SCK, CS,
   // Inputs
   CLK, RESET, CKP, CPH, MISO, START_STB, transaccion
   );

  // Entradas
  input CLK, RESET, CKP, CPH, MISO, START_STB;
  input [15:0] transaccion;

  // Salidas
  output reg MOSI, CS;
  output SCK;


  // Parametros
  localparam IDLE = 3'b001;
  localparam ESCRITURA_LECTURA = 3'b010;
  localparam DIV_FREQ = 2;


  // Variables intermedias
  reg [2:0]  estado, prox_estado;
  reg [4:0] cuenta_bits_d, cuenta_bits, prox_cuenta_bits;
  reg NXT_CS, NXT_MOSI;
  reg [DIV_FREQ-1:0] div_freq;
  reg SCK_anterior;
  reg [15:0] dato_recibido, prox_dato_recibido;
  reg [15:0] dato_enviado, prox_dato_enviado;

  // WIRES
  wire posedge_SCK;
  wire trans_finalizada;
  
  // ASSIGNS
  assign trans_finalizada = (cuenta_bits_d == 31);

  // MDC a fraccion del CLK
  assign SCK = div_freq[DIV_FREQ-1];
  assign posedge_SCK = !SCK_anterior && SCK;

  // Flip flops
  always @(posedge CLK) begin
    if (RESET) begin
      estado        <= IDLE;
      cuenta_bits   <= 0;
      div_freq      <= 0;
      SCK_anterior <= 0;
      CS <= 1;
      MOSI <= 0;
      dato_recibido <= 0;
      dato_enviado <=0;
    end else begin
      estado        <= prox_estado;
      cuenta_bits   <= prox_cuenta_bits;
      div_freq      <= div_freq+1;
      SCK_anterior <= SCK;
      CS <= NXT_CS;
      MOSI <= NXT_MOSI;
      dato_recibido <= prox_dato_recibido;
      dato_enviado <= prox_dato_enviado;

    end
  end //Fin de los FFs

  //Logica combinacional
  always @(*) begin

    // Valores por defecto
    prox_estado = estado;
    prox_cuenta_bits   = cuenta_bits;
    NXT_CS = CS;
    NXT_MOSI = MOSI;
    prox_dato_recibido = dato_recibido;
    prox_dato_enviado = dato_enviado;
    
 
    case (estado)
      IDLE:
        begin
          NXT_CS = 1; 
          prox_cuenta_bits = 0;
          NXT_MOSI = 0;
          if (START_STB) begin
            prox_estado = ESCRITURA_LECTURA; 
          end
          /*
          nxt_mdio_oe = start_stb;
	        if (start_stb && write) begin
              prox_estado = ESCRITURA;
          end else if (start_stb && ~write) begin
            prox_estado = LECTURA;
	        end */
	      end

      ESCRITURA_LECTURA: 
        begin
          NXT_CS = 0;  
          if (posedge_SCK)
                      begin
                      prox_cuenta_bits = cuenta_bits + 1;
                      NXT_MOSI = transaccion[15-cuenta_bits];                          // Sending data
                      dato_recibido[15-cuenta_bits] = MISO;                            // Receiving data
                      end
          if (cuenta_bits == 15) prox_estado = IDLE;
          
          /*
          if (trans_finalizada) prox_estado = INICIO;
          nxt_mdio_oe = 1;
          prox_cuenta_bits = cuenta_bits+1;*/
        end

      default:  
        begin
          prox_estado = IDLE;
          prox_dato_recibido = 0;
      end
    endcase;
  end

/*
//Generación del reloj de salida MDC  
reg clk_div2; 
wire clk_div4;
reg [1:0] count_clock; */
/*
always @(posedge CLK) begin
  if (RESET) begin
    clk_div2    <= 0;
    count_clock <= 0;
  end else begin
    clk_div2    <= ~clk_div2;
    count_clock <= count_clock+1;
  end
end*/

//assign clk_div4 = count_clock[1];
//assign mdc = clk_div2;

/*
// Incremento de cuenta_bits
always @(posedge mdc) begin
   if (reset || start_stb) begin
     cuenta_bits   <= 0;
     cuenta_bits_d <= 0;
     mdio_oe       <= 0;
   end else begin
     cuenta_bits   <= prox_cuenta_bits;
     cuenta_bits_d <= cuenta_bits;
     mdio_out      <= transaccion[31-cuenta_bits];
     //mdio_oe       <= nxt_mdio_oe;
   end
 end */

endmodule

Homeworks/Homework 4/testbench_spi.v
`include "CPU_spi.v"
`include "target_spi.v"
  

// Testbench Code Goes here
module spi_tb;

reg        CLK, RESET, START_STB;
reg  [15:0] transaccion;
//reg  [7:0] spi_data_read;
//wire [7:0] spi_data_write;
wire        SCK, MOSI, MISO, CS;

initial begin
	$dumpfile("spi.vcd");
	$dumpvars(-1, CPU);
	$dumpvars(-1, T1);
	//$dumpvars(-1, T2);
end


initial begin
  CLK = 0;
  RESET = 0;

  #20 RESET = 1;
  #120 RESET = 0;
      START_STB = 0;
      transaccion = 16'b0000001100000101;
  #80 START_STB = 1;
  #40 START_STB = 0;
  //#7800 transaccion = 8'b00000101;
        //mdio_data_read = 16'h2468;
  //#160  START_STB = 1;
  //#40   START_STB = 0;
  #8000 $finish;
end

always begin
 #20 CLK = !CLK;
end


CPU_spi CPU (/*AUTOINST*/

		   // Outputs
           .MOSI (MOSI), 
		   .CS (CS),
           .SCK (SCK),
		   // Inputs
		   .CLK	(CLK),
		   .RESET (RESET),
		   .CKP (CKP),
		   .CPH (CPH),
		   .MISO (MISO),
		   .START_STB (START_STB),
		   .transaccion (transaccion[15:0]));

target_spi T1 (/*AUTOINST*/ 

		  // Outputs
		  //.mdio_data_write	(mdio_data_write[15:0]),
		  //.reg_addr		(reg_addr[5:0]),
		  .MISO		(mdio_in),
		  // Inputs
		  .MOSI			(MOSI),
		  .SCK			(SCK),
		  .SS			(CS),
		  .CKP			(CKP),
		  .CPH			(CPH),
		  .RESET 		(RESET) 
		  );


endmodule

Homeworks/Homework 4/spi.vcd
$date
	Sat Jun  1 15:30:53 2024
$end
$version
	Icarus Verilog
$end
$timescale
	1s
$end
$scope module spi_tb $end
$scope module CPU $end
$var wire 1 ! CKP $end
$var wire 1 " CLK $end
$var wire 1 # CPH $end
$var wire 1 $ MISO $end
$var wire 1 % RESET $end
$var wire 1 & START_STB $end
$var wire 1 ' posedge_SCK $end
$var wire 16 ( transaccion [15:0] $end
$var wire 1 ) trans_finalizada $end
$var wire 1 * SCK $end
$var parameter 32 + DIV_FREQ $end
$var parameter 3 , ESCRITURA_LECTURA $end
$var parameter 3 - IDLE $end
$var reg 1 . CS $end
$var reg 1 / MOSI $end
$var reg 1 0 NXT_CS $end
$var reg 1 1 NXT_MOSI $end
$var reg 1 2 SCK_anterior $end
$var reg 5 3 cuenta_bits [4:0] $end
$var reg 5 4 cuenta_bits_d [4:0] $end
$var reg 16 5 dato_enviado [15:0] $end
$var reg 16 6 dato_recibido [15:0] $end
$var reg 2 7 div_freq [1:0] $end
$var reg 3 8 estado [2:0] $end
$var reg 5 9 prox_cuenta_bits [4:0] $end
$var reg 16 : prox_dato_enviado [15:0] $end
$var reg 16 ; prox_dato_recibido [15:0] $end
$var reg 3 < prox_estado [2:0] $end
$upscope $end
$upscope $end
$scope module spi_tb $end
$scope module T1 $end
$var wire 1 ! CKP $end
$var wire 1 # CPH $end
$var wire 1 / MOSI $end
$var wire 1 % RESET $end
$var wire 1 * SCK $end
$var wire 1 . SS $end
$var wire 1 = posedge_SS $end
$var parameter 3 > ESCRITURA_LECTURA $end
$var parameter 3 ? IDLE $end
$var reg 1 @ MISO $end
$var reg 1 A NXT_MISO $end
$var reg 1 B SS_d $end
$var reg 5 C cuenta_bits [4:0] $end
$var reg 16 D dato_enviado [15:0] $end
$var reg 16 E dato_recibido [15:0] $end
$var reg 3 F estado [2:0] $end
$var reg 5 G prox_cuenta_bits [4:0] $end
$var reg 16 H prox_dato_enviado [15:0] $end
$var reg 16 I prox_dato_recibido [15:0] $end
$var reg 3 J prox_estado [2:0] $end
$upscope $end
$upscope $end
$enddefinitions $end
$comment Show the parameter values. $end
$dumpall
b1 ?
b10 >
b1 -
b10 ,
b10 +
$end
#0
$dumpvars
bx J
bx I
bx H
bx G
bx F
bx E
bx D
bx C
xB
xA
x@
x=
bx <
bx ;
bx :
bx 9
bx 8
bx 7
bx 6
bx 5
bx 4
bx 3
x2
x1
x0
x/
x.
x*
x)
bx (
x'
x&
0%
z$
z#
0"
z!
$end
#20
b1 J
0'
0*
b0 :
b0 ;
01
10
b0 9
b1 <
b0 5
b0 6
0/
1.
02
b0 7
b0 3
b1 8
1"
1%
#40
0"
#60
1"
#80
0"
#100
1"
#120
0"
#140
b1 7
1"
b1100000101 (
0&
0%
#160
0"
#180
0=
b0 G
1B
b1 F
1'
1*
b10 7
1"
#200
0"
#220
bz000000000000000 ;
0'
bz000000000000000 6
b0 9
00
12
b11 7
b10 8
b10 <
1"
1&
#240
0"
#260
b10 J
b0 G
0*
0.
b0 7
00
1"
0&
#280
0"
#300
02
b1 7
1"
#320
0"
#340
b0xxxxxxxxxxxxxxx E
b1 G
0B
b0 C
b10 F
b1 9
1'
1*
b10 7
1"
#360
0"
#380
bz00000000000000 ;
0'
bz00000000000000 6
b1 9
12
b11 7
b1 3
1"
#400
0"
#420
0*
b0 7
1"
#440
0"
#460
02
b1 7
1"
#480
0"
#500
b10 G
bx0xxxxxxxxxxxxxx E
b1 C
b10 9
1'
1*
b10 7
1"
#520
0"
#540
bz0000000000000 ;
0'
bz0000000000000 6
b10 9
12
b11 7
b10 3
1"
#560
0"
#580
0*
b0 7
1"
#600
0"
#620
02
b1 7
1"
#640
0"
#660
b11 G
bx0xxxxxxxxxxxxx E
b10 C
b11 9
1'
1*
b10 7
1"
#680
0"
#700
bz000000000000 ;
0'
bz000000000000 6
b11 9
12
b11 7
b11 3
1"
#720
0"
#740
0*
b0 7
1"
#760
0"
#780
02
b1 7
1"
#800
0"
#820
b100 G
bx0xxxxxxxxxxxx E
b11 C
b100 9
1'
1*
b10 7
1"
#840
0"
#860
bz00000000000 ;
0'
bz00000000000 6
b100 9
12
b11 7
b100 3
1"
#880
0"
#900
0*
b0 7
1"
#920
0"
#940
02
b1 7
1"
#960
0"
#980
b101 G
bx0xxxxxxxxxxx E
b100 C
b101 9
1'
1*
b10 7
1"
#1000
0"
#1020
bz0000000000 ;
0'
bz0000000000 6
b101 9
12
b11 7
b101 3
1"
#1040
0"
#1060
0*
b0 7
1"
#1080
0"
#1100
02
b1 7
1"
#1120
0"
#1140
b110 G
bx0xxxxxxxxxx E
b101 C
b110 9
1'
1*
b10 7
1"
#1160
0"
#1180
bz000000000 ;
0'
bz000000000 6
01
b110 9
12
b11 7
b110 3
1"
#1200
0"
#1220
0*
b0 7
1"
#1240
0"
#1260
02
b1 7
1"
#1280
0"
#1300
b111 G
bx0xxxxxxxxx E
b110 C
11
b111 9
1'
1*
b10 7
1"
#1320
0"
#1340
bz00000000 ;
bx1xxxxxxxxx E
b111 G
0'
bz00000000 6
b111 9
1/
12
b11 7
b111 3
1"
#1360
0"
#1380
0*
b0 7
1"
#1400
0"
#1420
02
b1 7
1"
#1440
0"
#1460
b1000 G
bx1xxxxxxxx E
b111 C
b1000 9
1'
1*
b10 7
1"
#1480
0"
#1500
bz0000000 ;
0'
bz0000000 6
11
b1000 9
12
b11 7
b1000 3
1"
#1520
0"
#1540
0*
b0 7
1"
#1560
0"
#1580
02
b1 7
1"
#1600
0"
#1620
b1001 G
bx1xxxxxxx E
b1000 C
01
b1001 9
1'
1*
b10 7
1"
#1640
0"
#1660
bz000000 ;
bx0xxxxxxx E
b1001 G
0'
bz000000 6
b1001 9
0/
12
b11 7
b1001 3
1"
#1680
0"
#1700
0*
b0 7
1"
#1720
0"
#1740
02
b1 7
1"
#1760
0"
#1780
b1010 G
bx0xxxxxx E
b1001 C
b1010 9
1'
1*
b10 7
1"
#1800
0"
#1820
bz00000 ;
0'
bz00000 6
b1010 9
12
b11 7
b1010 3
1"
#1840
0"
#1860
0*
b0 7
1"
#1880
0"
#1900
02
b1 7
1"
#1920
0"
#1940
b1011 G
bx0xxxxx E
b1010 C
b1011 9
1'
1*
b10 7
1"
#1960
0"
#1980
bz0000 ;
0'
bz0000 6
b1011 9
12
b11 7
b1011 3
1"
#2000
0"
#2020
0*
b0 7
1"
#2040
0"
#2060
02
b1 7
1"
#2080
0"
#2100
b1100 G
bx0xxxx E
b1011 C
b1100 9
1'
1*
b10 7
1"
#2120
0"
#2140
bz000 ;
0'
bz000 6
b1100 9
12
b11 7
b1100 3
1"
#2160
0"
#2180
0*
b0 7
1"
#2200
0"
#2220
02
b1 7
1"
#2240
0"
#2260
b1101 G
bx0xxx E
b1100 C
b1101 9
1'
1*
b10 7
1"
#2280
0"
#2300
bz00 ;
0'
bz00 6
01
b1101 9
12
b11 7
b1101 3
1"
#2320
0"
#2340
0*
b0 7
1"
#2360
0"
#2380
02
b1 7
1"
#2400
0"
#2420
b1110 G
bx0xx E
b1101 C
11
b1110 9
1'
1*
b10 7
1"
#2440
0"
#2460
bz0 ;
bx1xx E
b1110 G
0'
bz0 6
11
b1110 9
1/
12
b11 7
b1110 3
1"
#2480
0"
#2500
0*
b0 7
1"
#2520
0"
#2540
02
b1 7
1"
#2560
0"
#2580
b1111 G
bx1x E
b1110 C
01
b1111 9
1'
1*
b10 7
1"
#2600
0"
#2620
bz ;
bx0x E
b1111 G
0'
b1 <
bz 6
01
b1111 9
0/
12
b11 7
b1111 3
1"
#2640
0"
#2660
0*
b0 9
10
b0 7
b1 8
1"
#2680
0"
#2700
1=
b1111 G
1.
02
b1 7
b0 3
1"
#2720
0"
#2740
0A
b0 G
b1 J
b11000000001 D
b0 E
0@
b0 C
b1 F
1'
1*
b10 7
1"
#2760
0"
#2780
0'
12
b11 7
1"
#2800
0"
#2820
0*
b0 7
1"
#2840
0"
#2860
02
b1 7
1"
#2880
0"
#2900
1'
1*
b10 7
1"
#2920
0"
#2940
0'
12
b11 7
1"
#2960
0"
#2980
0*
b0 7
1"
#3000
0"
#3020
02
b1 7
1"
#3040
0"
#3060
1'
1*
b10 7
1"
#3080
0"
#3100
0'
12
b11 7
1"
#3120
0"
#3140
0*
b0 7
1"
#3160
0"
#3180
02
b1 7
1"
#3200
0"
#3220
1'
1*
b10 7
1"
#3240
0"
#3260
0'
12
b11 7
1"
#3280
0"
#3300
0*
b0 7
1"
#3320
0"
#3340
02
b1 7
1"
#3360
0"
#3380
1'
1*
b10 7
1"
#3400
0"
#3420
0'
12
b11 7
1"
#3440
0"
#3460
0*
b0 7
1"
#3480
0"
#3500
02
b1 7
1"
#3520
0"
#3540
1'
1*
b10 7
1"
#3560
0"
#3580
0'
12
b11 7
1"
#3600
0"
#3620
0*
b0 7
1"
#3640
0"
#3660
02
b1 7
1"
#3680
0"
#3700
1'
1*
b10 7
1"
#3720
0"
#3740
0'
12
b11 7
1"
#3760
0"
#3780
0*
b0 7
1"
#3800
0"
#3820
02
b1 7
1"
#3840
0"
#3860
1'
1*
b10 7
1"
#3880
0"
#3900
0'
12
b11 7
1"
#3920
0"
#3940
0*
b0 7
1"
#3960
0"
#3980
02
b1 7
1"
#4000
0"
#4020
1'
1*
b10 7
1"
#4040
0"
#4060
0'
12
b11 7
1"
#4080
0"
#4100
0*
b0 7
1"
#4120
0"
#4140
02
b1 7
1"
#4160
0"
#4180
1'
1*
b10 7
1"
#4200
0"
#4220
0'
12
b11 7
1"
#4240
0"
#4260
0*
b0 7
1"
#4280
0"
#4300
02
b1 7
1"
#4320
0"
#4340
1'
1*
b10 7
1"
#4360
0"
#4380
0'
12
b11 7
1"
#4400
0"
#4420
0*
b0 7
1"
#4440
0"
#4460
02
b1 7
1"
#4480
0"
#4500
1'
1*
b10 7
1"
#4520
0"
#4540
0'
12
b11 7
1"
#4560
0"
#4580
0*
b0 7
1"
#4600
0"
#4620
02
b1 7
1"
#4640
0"
#4660
1'
1*
b10 7
1"
#4680
0"
#4700
0'
12
b11 7
1"
#4720
0"
#4740
0*
b0 7
1"
#4760
0"
#4780
02
b1 7
1"
#4800
0"
#4820
1'
1*
b10 7
1"
#4840
0"
#4860
0'
12
b11 7
1"
#4880
0"
#4900
0*
b0 7
1"
#4920
0"
#4940
02
b1 7
1"
#4960
0"
#4980
1'
1*
b10 7
1"
#5000
0"
#5020
0'
12
b11 7
1"
#5040
0"
#5060
0*
b0 7
1"
#5080
0"
#5100
02
b1 7
1"
#5120
0"
#5140
1'
1*
b10 7
1"
#5160
0"
#5180
0'
12
b11 7
1"
#5200
0"
#5220
0*
b0 7
1"
#5240
0"
#5260
02
b1 7
1"
#5280
0"
#5300
1'
1*
b10 7
1"
#5320
0"
#5340
0'
12
b11 7
1"
#5360
0"
#5380
0*
b0 7
1"
#5400
0"
#5420
02
b1 7
1"
#5440
0"
#5460
1'
1*
b10 7
1"
#5480
0"
#5500
0'
12
b11 7
1"
#5520
0"
#5540
0*
b0 7
1"
#5560
0"
#5580
02
b1 7
1"
#5600
0"
#5620
1'
1*
b10 7
1"
#5640
0"
#5660
0'
12
b11 7
1"
#5680
0"
#5700
0*
b0 7
1"
#5720
0"
#5740
02
b1 7
1"
#5760
0"
#5780
1'
1*
b10 7
1"
#5800
0"
#5820
0'
12
b11 7
1"
#5840
0"
#5860
0*
b0 7
1"
#5880
0"
#5900
02
b1 7
1"
#5920
0"
#5940
1'
1*
b10 7
1"
#5960
0"
#5980
0'
12
b11 7
1"
#6000
0"
#6020
0*
b0 7
1"
#6040
0"
#6060
02
b1 7
1"
#6080
0"
#6100
1'
1*
b10 7
1"
#6120
0"
#6140
0'
12
b11 7
1"
#6160
0"
#6180
0*
b0 7
1"
#6200
0"
#6220
02
b1 7
1"
#6240
0"
#6260
1'
1*
b10 7
1"
#6280
0"
#6300
0'
12
b11 7
1"
#6320
0"
#6340
0*
b0 7
1"
#6360
0"
#6380
02
b1 7
1"
#6400
0"
#6420
1'
1*
b10 7
1"
#6440
0"
#6460
0'
12
b11 7
1"
#6480
0"
#6500
0*
b0 7
1"
#6520
0"
#6540
02
b1 7
1"
#6560
0"
#6580
1'
1*
b10 7
1"
#6600
0"
#6620
0'
12
b11 7
1"
#6640
0"
#6660
0*
b0 7
1"
#6680
0"
#6700
02
b1 7
1"
#6720
0"
#6740
1'
1*
b10 7
1"
#6760
0"
#6780
0'
12
b11 7
1"
#6800
0"
#6820
0*
b0 7
1"
#6840
0"
#6860
02
b1 7
1"
#6880
0"
#6900
1'
1*
b10 7
1"
#6920
0"
#6940
0'
12
b11 7
1"
#6960
0"
#6980
0*
b0 7
1"
#7000
0"
#7020
02
b1 7
1"
#7040
0"
#7060
1'
1*
b10 7
1"
#7080
0"
#7100
0'
12
b11 7
1"
#7120
0"
#7140
0*
b0 7
1"
#7160
0"
#7180
02
b1 7
1"
#7200
0"
#7220
1'
1*
b10 7
1"
#7240
0"
#7260
0'
12
b11 7
1"
#7280
0"
#7300
0*
b0 7
1"
#7320
0"
#7340
02
b1 7
1"
#7360
0"
#7380
1'
1*
b10 7
1"
#7400
0"
#7420
0'
12
b11 7
1"
#7440
0"
#7460
0*
b0 7
1"
#7480
0"
#7500
02
b1 7
1"
#7520
0"
#7540
1'
1*
b10 7
1"
#7560
0"
#7580
0'
12
b11 7
1"
#7600
0"
#7620
0*
b0 7
1"
#7640
0"
#7660
02
b1 7
1"
#7680
0"
#7700
1'
1*
b10 7
1"
#7720
0"
#7740
0'
12
b11 7
1"
#7760
0"
#7780
0*
b0 7
1"
#7800
0"
#7820
02
b1 7
1"
#7840
0"
#7860
1'
1*
b10 7
1"
#7880
0"
#7900
0'
12
b11 7
1"
#7920
0"
#7940
0*
b0 7
1"
#7960
0"
#7980
02
b1 7
1"
#8000
0"
#8020
1'
1*
b10 7
1"
#8040
0"
#8060
0'
12
b11 7
1"
#8080
0"
#8100
0*
b0 7
1"
#8120
0"
#8140
02
b1 7
1"
#8160
0"
#8180
1'
1*
b10 7
1"
#8200
0"
#8220
0'
12
b11 7
1"
#8240
0"
#8260
0*
b0 7
1"
