Homeworks/Homework 5/I2C (copy)/TARGET_I2C.v
module TARGET_I2C(
   // Inputs
   SDA_OUT, SDA_OE, SCL, RD_DATA, I2C_ADDR, CLK,
   // Outputs
   RESET, SDA_IN, reg_addr, WR_DATA
   );

  //Entradas y salidas
  output reg SDA_IN;
  output reg [15:0] WR_DATA; 
  output     [4:0] reg_addr;
  input RESET, SDA_OUT, SDA_OE, SCL, CLK;
  input [15:0] RD_DATA;
  input [6:0] I2C_ADDR;

  localparam INICIO       = 3'b001;
  localparam RECIBIR_BITS = 3'b010;
  localparam ENVIAR_BITS  = 3'b100;

  //Variables intermedias
  reg [2:0] estado, prox_estado;
  reg [4:0] cuenta_bits, prox_cuenta_bits;
  wire escritura, lectura;
  wire [1:0] start, op;
  wire [4:0] phy_addr;
  reg [31:0] transaccion;
  reg [6:0] I2C_ADDR_RECIBIDO, NXT_I2C_ADDR_RECIBIDO;
  reg SDA_OUT_reg, SDA_OUT_delay, SCL_anterior, flag, NXT_flag, NXT_SDA_IN;
   reg ACK1, NXT_ACK1, ACK2, NXT_ACK2;

  assign escritura = (op[1:0] == 2'b01);
  assign lectura   =   (op == 2'b10);
  assign start     = transaccion[31:30];
  assign op        = transaccion[29:28];
  assign phy_addr  = transaccion[27:24];
  assign reg_addr  = transaccion[24:20];

  assign posedge_SCL = !SCL_anterior && SCL;

  //Fip flops
  always @(posedge SCL) begin
    if (!RESET) begin
      cuenta_bits    <= 0;
      SDA_OUT_reg    <= 1;
      SDA_OUT_delay  <= 1;
    end else begin
      //cuenta_bits  <= prox_cuenta_bits;
      //I2C_ADDR_RECIBIDO <= NXT_I2C_ADDR_RECIBIDO;
      SDA_OUT_reg <= SDA_OUT;
      SDA_OUT_delay <= SDA_OUT_reg;
    end
  end

  always @(posedge CLK) begin
    if (!RESET) begin
      estado  <= INICIO;
      flag    <= 0;
      ACK1    <= 0;
      ACK2    <= 0;
    end else begin
      estado       <= prox_estado;
      SCL_anterior  <= SCL;
      cuenta_bits   <= prox_cuenta_bits;
      I2C_ADDR_RECIBIDO <= NXT_I2C_ADDR_RECIBIDO;
      flag <= NXT_flag;
      SDA_IN <= NXT_SDA_IN;
      ACK1          <= NXT_ACK1;
      ACK2          <= NXT_ACK2;
    end
  end

  //Logica combinacional

  always @(*) begin
    prox_estado = estado;
    prox_cuenta_bits = cuenta_bits;
    NXT_I2C_ADDR_RECIBIDO = I2C_ADDR_RECIBIDO;
    NXT_flag = flag;
    NXT_SDA_IN = SDA_IN;
    NXT_ACK1 = ACK1;
    NXT_ACK2 = ACK2;


    case (estado)
	    INICIO: 
        begin
          NXT_SDA_IN = 0;
		      prox_cuenta_bits = 0;
		      if (~SDA_OE) begin
		        prox_estado = RECIBIR_BITS;
		      end
	      end

	    RECIBIR_BITS: 
        begin
          if (posedge_SCL) 
            begin
             NXT_flag = 1;
             if (flag) 
              begin
                if (!SDA_IN && !ACK1 && !ACK2) 
                  begin 
                    prox_cuenta_bits = cuenta_bits+1;
                    NXT_I2C_ADDR_RECIBIDO[6-cuenta_bits] = SDA_OUT;
                    if (I2C_ADDR_RECIBIDO == I2C_ADDR)
                      begin 
                        NXT_SDA_IN = 1;
                        prox_cuenta_bits = 0;
                      end
                  end
                if (SDA_IN || ACK1) 
                  begin 
                    if (cuenta_bits < 8) 
                      begin
                        NXT_ACK1 = 1;
                        NXT_SDA_IN = 0;
                        prox_cuenta_bits = cuenta_bits+1;
                        WR_DATA[15-cuenta_bits] = SDA_OUT;
                      end
                    if (cuenta_bits==8) begin 
                      NXT_SDA_IN = 1; 
                      //prox_cuenta_bits = cuenta_bits+1;
                      end
                  end

                  if (SDA_IN || ACK2) 
                  begin 
                    if (cuenta_bits > 7) 
                      begin
                        NXT_ACK2 = 1;
                        NXT_SDA_IN = 0;
                        prox_cuenta_bits = cuenta_bits+1;
                        if (cuenta_bits < 16) WR_DATA[15-cuenta_bits] = SDA_OUT;
                        if (cuenta_bits==15) NXT_SDA_IN = 1;
                        if (SDA_OE) prox_estado = INICIO; 
                      end
                   
                  end
              end
            end
        end

	    ENVIAR_BITS:
        begin
	        prox_cuenta_bits = cuenta_bits+1;
		      SDA_IN = RD_DATA[31-cuenta_bits];
		      if (cuenta_bits == 31) prox_estado = INICIO;
	    end
      
      default: begin end

    endcase;
  end
endmodule

Homeworks/Homework 5/I2C (copy)/CPU_I2C.v
module CPU_I2C(
   // Outputs
   SDA_OUT, SDA_OE, SCL, RD_DATA,

   // Inputs
   CLK, RESET, START_STB, SDA_IN, transaccion, RNW, I2C_ADDR, WR_DATA
   );

  // Entradas
  input CLK, RESET, START_STB, SDA_IN, RNW;
  input [31:0] transaccion;
  input [6:0] I2C_ADDR;
  input [15:0] WR_DATA;

  // Salidas
  output reg SDA_OUT, SDA_OE;
  output  SCL;
  output reg [15:0] RD_DATA;

  localparam INICIO    = 3'b001;
  localparam ESCRITURA = 3'b010;
  localparam LECTURA   = 3'b100;
  localparam STOP      = 3'b111;   
  localparam DIV_FREQ  = 2; // 25% del CLK

  // Variables intermedias
  reg [2:0] estado, prox_estado;
  reg [4:0] cuenta_bits, prox_cuenta_bits;
  reg [DIV_FREQ-1:0] div_freq;
  reg START_STB_d, START_STB_reg;
  wire iniciar, escritura, lectura;
  wire posedge_SCL;
  reg SCL_anterior, prox_SDA_OUT, SCL_reg, NXT_SDA_OE;
  reg SDA_OUT_anterior;
  reg ACK1, NXT_ACK1, ACK2, NXT_ACK2;
  reg START_CONDITION_ACTIVADA;
  wire START_CONDITION;

  assign iniciar   = (transaccion[31:30] == 2'b01);
  assign escritura = (transaccion[29:28] == 2'b01);
  assign lectura = (transaccion[29:28] == 2'b10);

  // SCL es fraccion del CLK
  assign SCL = SCL_reg;

  //assign START_CONDITION = SCL && negedge_SDA_OUT && INICIO;

  assign posedge_SCL = !SCL_anterior && SCL;
  assign negedge_SDA_OUT = SDA_OUT_anterior && !SDA_OUT;
  assign START_CONDITION = SCL && negedge_SDA_OUT;

  // Flip flops
  always @(posedge CLK) begin
    if (!RESET) begin
      estado        <= INICIO;
      cuenta_bits   <= 0;
      div_freq      <= 0;
      SCL_anterior  <= 1;
      SDA_OUT_anterior <= 1;
      SDA_OUT       <= 1;
      SDA_OE        <= 1;
      START_STB_reg <= 0;
      START_STB_d   <= 0;
      ACK1 <= 0;
      ACK2 <= 0;
    end else begin
      estado        <= prox_estado;
      cuenta_bits   <= prox_cuenta_bits;
      SDA_OE        <= NXT_SDA_OE;
      div_freq      <= div_freq+1;
      SCL_anterior  <= SCL;
      SDA_OUT_anterior <= SDA_OUT;
      SDA_OUT       <= prox_SDA_OUT;
      START_STB_reg <= START_STB;
      START_STB_d   <= START_STB_reg;
      ACK1          <= NXT_ACK1;
      ACK2          <= NXT_ACK2;
    end
  end

  //Logica combinacional

  always @(*) begin
    /*
    if (SDA_OE) begin 
            SCL_reg = 1'b1;
        end else begin
            SCL_reg = div_freq[DIV_FREQ-1];
    end
    */
    
    if (START_CONDITION || START_CONDITION_ACTIVADA)
      begin 
        START_CONDITION_ACTIVADA = 1;
        SCL_reg = div_freq[DIV_FREQ-1];
      end 
        else begin SCL_reg = 1'b1; end
    
    prox_estado = estado;
    prox_cuenta_bits = cuenta_bits;
    prox_SDA_OUT = SDA_OUT;
    NXT_SDA_OE = SDA_OE;
    NXT_ACK1 = ACK1;
    NXT_ACK2 = ACK2;


    case (estado)
	    INICIO: begin
		    NXT_SDA_OE = 1'b1;
        SDA_OUT = 1'b1;
		    prox_cuenta_bits = 0;
        if (START_STB && RNW)   prox_estado = LECTURA;
        if (START_STB && !RNW)  prox_estado = ESCRITURA;
	    end

	    ESCRITURA: 
        begin
		      NXT_SDA_OE = 1'b0; //CAMBIAR A 1
          SDA_OUT = 1'b0;
              if (!SDA_IN && !ACK1 && !ACK2) 
                begin 
                  if (posedge_SCL)
                  begin
                    prox_cuenta_bits = cuenta_bits+1;
                    prox_SDA_OUT = I2C_ADDR[6-cuenta_bits];
                    if (cuenta_bits == 7) 
                      begin  
                        prox_SDA_OUT = 0; 
                        prox_cuenta_bits = 0;
                      end
                  end
                end
                                                      // Enviando Primer Byte
              if (SDA_IN || ACK1 )  
                begin
                  if (cuenta_bits < 9)
                  begin
                    NXT_ACK1 = 1;
                    if (posedge_SCL) 
                    begin
                      prox_cuenta_bits = cuenta_bits+1;
                      prox_SDA_OUT = WR_DATA[15-cuenta_bits];
                    end
                  end
                end
                                                      // Enviando Segundo Byte
              if (SDA_IN || ACK2)  
                begin
                  if (cuenta_bits > 8)
                  begin
                    NXT_ACK2 = 1;
                    if (posedge_SCL) 
                    begin
                      prox_cuenta_bits = cuenta_bits+1;
                      if (cuenta_bits < 16) prox_SDA_OUT = WR_DATA[15-cuenta_bits];
                    end
                  end
                end
              if (SDA_IN) 
                begin 
                  if (cuenta_bits > 16) 
                    begin 
                      prox_estado = STOP;
                      //SCL_reg = 1'b1;
                    end
                end 
              //if (cuenta_bits == 15) begin prox_estado = INICIO; end
           //end
        end

	    LECTURA: 
        begin
          // if (negedge SDA_OE && SCL) 
          // Debo indicar en transaccion[8] = 1; para que el TARGET sepa que se trata de una lectura.
          SDA_OE = 1'b0;
          if (posedge_SCL) prox_SDA_OUT = transaccion[31-cuenta_bits];
          if (!SDA_OE) RD_DATA[31-cuenta_bits] = SDA_IN;
          if (posedge_SCL) prox_cuenta_bits = cuenta_bits+1;
          if (cuenta_bits == 31) prox_estado = STOP;
        end

      STOP: 
        begin
          SCL_reg = 1'b1;
          NXT_SDA_OE = 1'b1;
          if (SDA_OE) prox_estado = INICIO;
          // if(SCL && posedge_SDA_OE) prox_estado = INICIO;
        end


      default: begin end
    endcase;
  end
endmodule

Homeworks/Homework 5/I2C (copy)/testbench_I2C.v
`include "CPU_I2C.v"
`include "TARGET_I2C.v"

// Testbench Code Goes here
module I2C_tb;

// Regs
reg         CLK, RESET_CPU, RESET_TARGET, START_STB, RNW;
reg  [31:0] transaccion;
reg [6:0]  I2C_ADDR;
reg  [15:0] I2C_data_read, WR_DATA;

// Wires
wire [15:0] I2C_data_write;
wire [15:0] reg_addr;
wire        SCL, SDA_IN, SDA_OUT, SDA_OE; 

initial begin
	$dumpfile("I2C.vcd");
	$dumpvars(-1, U0);
	$dumpvars(-1, U1);
end


initial begin
  CLK = 0;
  RESET_CPU = 1;
  RESET_TARGET  = 1;
  START_STB = 0;

  /*+++++++++++++++++++++++++++++++ PRUEBA ESCRITURA +++++++++++++++++++++++++++++++*/
  #20  RESET_CPU = 0;
       RESET_TARGET  = 0;
  #120 RESET_CPU = 1;
  #180 RESET_TARGET  = 1; 
      START_STB = 1;
	  I2C_ADDR = 7'b0111101; // Calling TARGET #61
	  WR_DATA = 16'h07CC;
      transaccion = 32'h5BA73549;
	  RNW = 0;
  #40 START_STB = 0;

  /*+++++++++++++++++++++++++++++++ PRUEBA LECTURA +++++++++++++++++++++++++++++++*/
  /*
  #40   START_STB = 0;
  #7800 transaccion = 32'h65557777;
        I2C_data_read = 16'h2468;
  #160  START_STB = 1;
  #40   START_STB = 0;
  */
  #8000 $finish;
end

always begin
 #20 CLK = !CLK;
end


CPU_I2C U0 (
/*AUTOINST*/
		   // Outputs
		   .SDA_OUT		(SDA_OUT),
		   .SDA_OE		(SDA_OE),
		   .SCL			(SCL),
		   // Inputs
		   .CLK			(CLK),
		   .RESET		(RESET_CPU),
		   .START_STB		(START_STB),
		   .SDA_IN		(SDA_IN),
		   .transaccion	(transaccion[31:0]),
		   .RNW         (RNW), 
		   .I2C_ADDR 	(I2C_ADDR),
		   .WR_DATA 	(WR_DATA)
		   );


TARGET_I2C U1 (
/*AUTOINST*/
		  // Outputs
		  .reg_addr		(reg_addr[4:0]),
		  .SDA_IN		(SDA_IN),
		  // Inputs
		  .SCL			(SCL),
		  .CLK			(CLK),
		  .RESET		(RESET_TARGET),
		  .SDA_OUT		(SDA_OUT),
		  .SDA_OE		(SDA_OE),
		  .RD_DATA   	(I2C_data_read[15:0]),
		  .I2C_ADDR  	(I2C_ADDR)
		  );


endmodule

Homeworks/Homework 5/I2C (copy)/I2C.vcd
$date
	Mon Jun 17 13:40:59 2024
$end
$version
	Icarus Verilog
$end
$timescale
	1s
$end
$scope module I2C_tb $end
$scope module U0 $end
$var wire 1 ! CLK $end
$var wire 7 " I2C_ADDR [6:0] $end
$var wire 1 # RESET $end
$var wire 1 $ RNW $end
$var wire 1 % START_CONDITION $end
$var wire 1 & START_STB $end
$var wire 16 ' WR_DATA [15:0] $end
$var wire 1 ( negedge_SDA_OUT $end
$var wire 1 ) posedge_SCL $end
$var wire 32 * transaccion [31:0] $end
$var wire 1 + lectura $end
$var wire 1 , iniciar $end
$var wire 1 - escritura $end
$var wire 1 . SDA_IN $end
$var wire 1 / SCL $end
$var parameter 32 0 DIV_FREQ $end
$var parameter 3 1 ESCRITURA $end
$var parameter 3 2 INICIO $end
$var parameter 3 3 LECTURA $end
$var parameter 3 4 STOP $end
$var reg 1 5 ACK1 $end
$var reg 1 6 ACK2 $end
$var reg 1 7 NXT_ACK1 $end
$var reg 1 8 NXT_ACK2 $end
$var reg 1 9 NXT_SDA_OE $end
$var reg 16 : RD_DATA [15:0] $end
$var reg 1 ; SCL_anterior $end
$var reg 1 / SCL_reg $end
$var reg 1 < SDA_OE $end
$var reg 1 = SDA_OUT $end
$var reg 1 > SDA_OUT_anterior $end
$var reg 1 ? START_CONDITION_ACTIVADA $end
$var reg 1 @ START_STB_d $end
$var reg 1 A START_STB_reg $end
$var reg 5 B cuenta_bits [4:0] $end
$var reg 2 C div_freq [1:0] $end
$var reg 3 D estado [2:0] $end
$var reg 1 E prox_SDA_OUT $end
$var reg 5 F prox_cuenta_bits [4:0] $end
$var reg 3 G prox_estado [2:0] $end
$upscope $end
$upscope $end
$scope module I2C_tb $end
$scope module U1 $end
$var wire 1 ! CLK $end
$var wire 7 H I2C_ADDR [6:0] $end
$var wire 16 I RD_DATA [15:0] $end
$var wire 1 J RESET $end
$var wire 1 / SCL $end
$var wire 1 < SDA_OE $end
$var wire 1 = SDA_OUT $end
$var wire 1 K posedge_SCL $end
$var wire 2 L start [1:0] $end
$var wire 5 M reg_addr [4:0] $end
$var wire 5 N phy_addr [4:0] $end
$var wire 2 O op [1:0] $end
$var wire 1 P lectura $end
$var wire 1 Q escritura $end
$var parameter 3 R ENVIAR_BITS $end
$var parameter 3 S INICIO $end
$var parameter 3 T RECIBIR_BITS $end
$var reg 1 U ACK1 $end
$var reg 1 V ACK2 $end
$var reg 7 W I2C_ADDR_RECIBIDO [6:0] $end
$var reg 1 X NXT_ACK1 $end
$var reg 1 Y NXT_ACK2 $end
$var reg 7 Z NXT_I2C_ADDR_RECIBIDO [6:0] $end
$var reg 1 [ NXT_SDA_IN $end
$var reg 1 \ NXT_flag $end
$var reg 1 ] SCL_anterior $end
$var reg 1 . SDA_IN $end
$var reg 1 ^ SDA_OUT_delay $end
$var reg 1 _ SDA_OUT_reg $end
$var reg 16 ` WR_DATA [15:0] $end
$var reg 5 a cuenta_bits [4:0] $end
$var reg 3 b estado [2:0] $end
$var reg 1 c flag $end
$var reg 5 d prox_cuenta_bits [4:0] $end
$var reg 3 e prox_estado [2:0] $end
$var reg 32 f transaccion [31:0] $end
$upscope $end
$upscope $end
$enddefinitions $end
$comment Show the parameter values. $end
$dumpall
b10 T
b1 S
b100 R
b111 4
b100 3
b1 2
b10 1
b10 0
$end
#0
$dumpvars
bx f
bx e
bx d
xc
bx b
bx a
bx `
x_
x^
x]
x\
x[
bx Z
xY
xX
bx W
xV
xU
xQ
xP
bx O
b0xxxx N
bx M
bx L
xK
1J
bx I
bx H
bx G
bx F
xE
bx D
bx C
bx B
xA
x@
x?
x>
x=
x<
x;
bx :
x9
x8
x7
x6
x5
1/
x.
x-
x,
x+
bx *
x)
x(
bx '
0&
x%
x$
1#
bx "
0!
$end
#20
0%
0(
0)
08
07
19
1E
b0 F
b1 G
b0 d
0[
0Y
0X
0\
b1 e
06
05
0@
0A
1<
1=
1>
1;
b0 C
b0 B
b1 D
0V
0U
0c
b1 b
1!
0J
0#
#40
0!
#60
1!
#80
0!
#100
1!
#120
0!
#140
b1 C
1!
1#
#160
0!
#180
b10 C
1!
#200
0!
#220
b11 C
1!
#240
0!
#260
b0 C
1!
#280
0!
#300
b1 C
1!
#320
1,
1-
0+
0[
b0 d
b10 G
0!
0$
b1011011101001110011010101001001 *
b11111001100 '
b111101 "
b111101 H
1&
1J
#340
0E
1?
1%
1(
0=
09
0K
1A
b10 C
b10 D
0.
b0 a
1]
1!
#360
09
0!
0&
#380
0%
0(
b10 e
1@
0A
0>
b11 C
0<
1!
#400
0!
#420
0/
0@
b0 C
b10 b
1!
#440
0!
#460
0]
0;
b1 C
1!
#480
0!
#500
0_
1\
b1 F
1K
1)
1/
b10 C
1!
#520
0!
#540
0K
0)
0E
b1 F
1c
1]
1;
b11 C
b1 B
1!
#560
0!
#580
0/
b0 C
1!
#600
0!
#620
0]
0;
b1 C
1!
#640
0!
#660
0^
b0xxxxxx Z
b1 d
1E
b10 F
1K
1)
1/
b10 C
1!
#680
0!
#700
0E
0K
b0xxxxxx Z
b1 d
0)
b10 F
b0xxxxxx W
b1 a
1]
0=
1;
b11 C
b10 B
1!
#720
0!
#740
0/
b0 C
1!
#760
0!
#780
0]
0;
b1 C
1!
#800
0!
#820
b0xxxxx Z
b10 d
1E
b11 F
1K
1)
1/
b10 C
1!
#840
0!
#860
0E
0K
b0xxxxx Z
b10 d
0)
b11 F
b0xxxxx W
b10 a
1]
0=
1;
b11 C
b11 B
1!
#880
0!
#900
0/
b0 C
1!
#920
0!
#940
0]
0;
b1 C
1!
#960
0!
#980
b0xxxx Z
b11 d
1E
b100 F
1K
1)
1/
b10 C
1!
#1000
0!
#1020
0E
0K
b0xxxx Z
b11 d
0)
b100 F
b0xxxx W
b11 a
1]
0=
1;
b11 C
b100 B
1!
#1040
0!
#1060
0/
b0 C
1!
#1080
0!
#1100
0]
0;
b1 C
1!
#1120
0!
#1140
b0xxx Z
b100 d
1E
b101 F
1K
1)
1/
b10 C
1!
#1160
0!
#1180
0K
b0xxx Z
b100 d
0)
0E
b101 F
b0xxx W
b100 a
1]
0=
1;
b11 C
b101 B
1!
#1200
0!
#1220
0/
b0 C
1!
#1240
0!
#1260
0]
0;
b1 C
1!
#1280
0!
#1300
b0xx Z
b101 d
b110 F
1K
1)
1/
b10 C
1!
#1320
0!
#1340
0K
0)
0E
b110 F
b0xx W
b101 a
1]
1;
b11 C
b110 B
1!
#1360
0!
#1380
0/
b0 C
1!
#1400
0!
#1420
0]
0;
b1 C
1!
#1440
0!
#1460
b0x Z
b110 d
1E
b111 F
1K
1)
1/
b10 C
1!
#1480
0!
#1500
0K
b0x Z
b110 d
0)
0E
b111 F
b0x W
b110 a
1]
0=
1;
b11 C
b111 B
1!
#1520
0!
#1540
0/
b0 C
1!
#1560
0!
#1580
0]
0;
b1 C
1!
#1600
0!
#1620
b0 Z
b111 d
0E
b0 F
1K
1)
1/
b10 C
1!
#1640
0!
#1660
0K
0)
b0 F
b0 W
b111 a
1]
1;
b11 C
b0 B
1!
#1680
0!
#1700
0/
b0 C
1!
#1720
0!
#1740
0]
0;
b1 C
1!
#1760
0!
#1780
b1000 d
b1 F
1K
1)
1/
b10 C
1!
#1800
0!
#1820
0K
0)
0E
b1 F
b1000 a
1]
1;
b11 C
b1 B
1!
#1840
0!
#1860
0/
b0 C
1!
#1880
0!
#1900
0]
0;
b1 C
1!
#1920
0!
#1940
b1001 d
1E
b10 F
1K
1)
1/
b10 C
1!
#1960
0!
#1980
0E
0K
b1001 d
0)
b10 F
b1001 a
1]
0=
1;
b11 C
b10 B
1!
#2000
0!
#2020
0/
b0 C
1!
#2040
0!
#2060
0]
0;
b1 C
1!
#2080
0!
#2100
b1010 d
1E
b11 F
1K
1)
1/
b10 C
1!
#2120
0!
#2140
0E
0K
b1010 d
0)
b11 F
b1010 a
1]
0=
1;
b11 C
b11 B
1!
#2160
0!
#2180
0/
b0 C
1!
#2200
0!
#2220
0]
0;
b1 C
1!
#2240
0!
#2260
b1011 d
1E
b100 F
1K
1)
1/
b10 C
1!
#2280
0!
#2300
0E
0K
b1011 d
0)
b100 F
b1011 a
1]
0=
1;
b11 C
b100 B
1!
#2320
0!
#2340
0/
b0 C
1!
#2360
0!
#2380
0]
0;
b1 C
1!
#2400
0!
#2420
b1100 d
1E
b101 F
1K
1)
1/
b10 C
1!
#2440
0!
#2460
0K
b1100 d
0)
0E
b101 F
b1100 a
1]
0=
1;
b11 C
b101 B
1!
#2480
0!
#2500
0/
b0 C
1!
#2520
0!
#2540
0]
0;
b1 C
1!
#2560
0!
#2580
b1101 d
b110 F
1K
1)
1/
b10 C
1!
#2600
0!
#2620
0K
0)
0E
b110 F
b1101 a
1]
1;
b11 C
b110 B
1!
#2640
0!
#2660
0/
b0 C
1!
#2680
0!
#2700
0]
0;
b1 C
1!
#2720
0!
#2740
b1110 d
1E
b111 F
1K
1)
1/
b10 C
1!
#2760
0!
#2780
0K
b1110 d
0)
0E
b111 F
b1110 a
1]
0=
1;
b11 C
b111 B
1!
#2800
0!
#2820
0/
b0 C
1!
#2840
0!
#2860
0]
0;
b1 C
1!
#2880
0!
#2900
b1111 d
0E
b0 F
1K
1)
1/
b10 C
1!
#2920
0!
#2940
0K
0)
b0 F
b1111 a
1]
1;
b11 C
b0 B
1!
#2960
0!
#2980
0/
b0 C
1!
#3000
0!
#3020
0]
0;
b1 C
1!
#3040
0!
#3060
b10000 d
b1 F
1K
1)
1/
b10 C
1!
#3080
0!
#3100
0K
0)
0E
b1 F
b10000 a
1]
1;
b11 C
b1 B
1!
#3120
0!
#3140
0/
b0 C
1!
#3160
0!
#3180
0]
0;
b1 C
1!
#3200
0!
#3220
b10001 d
1E
b10 F
1K
1)
1/
b10 C
1!
#3240
0!
#3260
0E
0K
b10001 d
0)
b10 F
b10001 a
1]
0=
1;
b11 C
b10 B
1!
#3280
0!
#3300
0/
b0 C
1!
#3320
0!
#3340
0]
0;
b1 C
1!
#3360
0!
#3380
b10010 d
1E
b11 F
1K
1)
1/
b10 C
1!
#3400
0!
#3420
0E
0K
b10010 d
0)
b11 F
b10010 a
1]
0=
1;
b11 C
b11 B
1!
#3440
0!
#3460
0/
b0 C
1!
#3480
0!
#3500
0]
0;
b1 C
1!
#3520
0!
#3540
b10011 d
1E
b100 F
1K
1)
1/
b10 C
1!
#3560
0!
#3580
0E
0K
b10011 d
0)
b100 F
b10011 a
1]
0=
1;
b11 C
b100 B
1!
#3600
0!
#3620
0/
b0 C
1!
#3640
0!
#3660
0]
0;
b1 C
1!
#3680
0!
#3700
b10100 d
1E
b101 F
1K
1)
1/
b10 C
1!
#3720
0!
#3740
0K
b10100 d
0)
0E
b101 F
b10100 a
1]
0=
1;
b11 C
b101 B
1!
#3760
0!
#3780
0/
b0 C
1!
#3800
0!
#3820
0]
0;
b1 C
1!
#3840
0!
#3860
b10101 d
b110 F
1K
1)
1/
b10 C
1!
#3880
0!
#3900
0K
0)
0E
b110 F
b10101 a
1]
1;
b11 C
b110 B
1!
#3920
0!
#3940
0/
b0 C
1!
#3960
0!
#3980
0]
0;
b1 C
1!
#4000
0!
#4020
b10110 d
1E
b111 F
1K
1)
1/
b10 C
1!
#4040
0!
#4060
0K
b10110 d
0)
0E
b111 F
b10110 a
1]
0=
1;
b11 C
b111 B
1!
#4080
0!
#4100
0/
b0 C
1!
#4120
0!
#4140
0]
0;
b1 C
1!
#4160
0!
#4180
b10111 d
0E
b0 F
1K
1)
1/
b10 C
1!
#4200
0!
#4220
0K
0)
b0 F
b10111 a
1]
1;
b11 C
b0 B
1!
#4240
0!
#4260
0/
b0 C
1!
#4280
0!
#4300
0]
0;
b1 C
1!
#4320
0!
#4340
b11000 d
b1 F
1K
1)
1/
b10 C
1!
#4360
0!
#4380
0K
0)
0E
b1 F
b11000 a
1]
1;
b11 C
b1 B
1!
#4400
0!
#4420
0/
b0 C
1!
#4440
0!
#4460
0]
0;
b1 C
1!
#4480
0!
#4500
b11001 d
1E
b10 F
1K
1)
1/
b10 C
1!
#4520
0!
#4540
0E
0K
b11001 d
0)
b10 F
b11001 a
1]
0=
1;
b11 C
b10 B
1!
#4560
0!
#4580
0/
b0 C
1!
#4600
0!
#4620
0]
0;
b1 C
1!
#4640
0!
#4660
b11010 d
1E
b11 F
1K
1)
1/
b10 C
1!
#4680
0!
#4700
0E
0K
b11010 d
0)
b11 F
b11010 a
1]
0=
1;
b11 C
b11 B
1!
#4720
0!
#4740
0/
b0 C
1!
#4760
0!
#4780
0]
0;
b1 C
1!
#4800
0!
#4820
b11011 d
1E
b100 F
1K
1)
1/
b10 C
1!
#4840
0!
#4860
0E
0K
b11011 d
0)
b100 F
b11011 a
1]
0=
1;
b11 C
b100 B
1!
#4880
0!
#4900
0/
b0 C
1!
#4920
0!
#4940
0]
0;
b1 C
1!
#4960
0!
#4980
b11100 d
1E
b101 F
1K
1)
1/
b10 C
1!
#5000
0!
#5020
0K
b11100 d
0)
0E
b101 F
b11100 a
1]
0=
1;
b11 C
b101 B
1!
#5040
0!
#5060
0/
b0 C
1!
#5080
0!
#5100
0]
0;
b1 C
1!
#5120
0!
#5140
b11101 d
b110 F
1K
1)
1/
b10 C
1!
#5160
0!
#5180
0K
0)
0E
b110 F
b11101 a
1]
1;
b11 C
b110 B
1!
#5200
0!
#5220
0/
b0 C
1!
#5240
0!
#5260
0]
0;
b1 C
1!
#5280
0!
#5300
b11110 d
1E
b111 F
1K
1)
1/
b10 C
1!
#5320
0!
#5340
0K
b11110 d
0)
0E
b111 F
b11110 a
1]
0=
1;
b11 C
b111 B
1!
#5360
0!
#5380
0/
b0 C
1!
#5400
0!
#5420
0]
0;
b1 C
1!
#5440
0!
#5460
b11111 d
0E
b0 F
1K
1)
1/
b10 C
1!
#5480
0!
#5500
0K
0)
b0 F
b11111 a
1]
1;
b11 C
b0 B
1!
#5520
0!
#5540
0/
b0 C
1!
#5560
0!
#5580
0]
0;
b1 C
1!
#5600
0!
#5620
b0 d
b1 F
1K
1)
1/
b10 C
1!
#5640
0!
#5660
0K
0)
0E
b1 F
b0 a
1]
1;
b11 C
b1 B
1!
#5680
0!
#5700
0/
b0 C
1!
#5720
0!
#5740
0]
0;
b1 C
1!
#5760
0!
#5780
b1 d
1E
b10 F
1K
1)
1/
b10 C
1!
#5800
0!
#5820
0E
0K
b1 d
0)
b10 F
b1 a
1]
0=
1;
b11 C
b10 B
1!
#5840
0!
#5860
0/
b0 C
1!
#5880
0!
#5900
0]
0;
b1 C
1!
#5920
0!
#5940
b10 d
1E
b11 F
1K
1)
1/
b10 C
1!
#5960
0!
#5980
0E
0K
b10 d
0)
b11 F
b10 a
1]
0=
1;
b11 C
b11 B
1!
#6000
0!
#6020
0/
b0 C
1!
#6040
0!
#6060
0]
0;
b1 C
1!
#6080
0!
#6100
b11 d
1E
b100 F
1K
1)
1/
b10 C
1!
#6120
0!
#6140
0E
0K
b11 d
0)
b100 F
b11 a
1]
0=
1;
b11 C
b100 B
1!
#6160
0!
#6180
0/
b0 C
1!
#6200
0!
#6220
0]
0;
b1 C
1!
#6240
0!
#6260
b100 d
1E
b101 F
1K
1)
1/
b10 C
1!
#6280
0!
#6300
0K
b100 d
0)
0E
b101 F
b100 a
1]
0=
1;
b11 C
b101 B
1!
#6320
0!
#6340
0/
b0 C
1!
#6360
0!
#6380
0]
0;
b1 C
1!
#6400
0!
#6420
b101 d
b110 F
1K
1)
1/
b10 C
1!
#6440
0!
#6460
0K
0)
0E
b110 F
b101 a
1]
1;
b11 C
b110 B
1!
#6480
0!
#6500
0/
b0 C
1!
#6520
0!
#6540
0]
0;
b1 C
1!
#6560
0!
#6580
b110 d
1E
b111 F
1K
1)
1/
b10 C
1!
#6600
0!
#6620
0K
b110 d
0)
0E
b111 F
b110 a
1]
0=
1;
b11 C
b111 B
1!
#6640
0!
#6660
0/
b0 C
1!
#6680
0!
#6700
0]
0;
b1 C
1!
#6720
0!
#6740
b111 d
0E
b0 F
1K
1)
1/
b10 C
1!
#6760
0!
#6780
0K
0)
b0 F
b111 a
1]
1;
b11 C
b0 B
1!
#6800
0!
#6820
0/
b0 C
1!
#6840
0!
#6860
0]
0;
b1 C
1!
#6880
0!
#6900
b1000 d
b1 F
1K
1)
1/
b10 C
1!
#6920
0!
#6940
0K
0)
0E
b1 F
b1000 a
1]
1;
b11 C
b1 B
1!
#6960
0!
#6980
0/
b0 C
1!
#7000
0!
#7020
0]
0;
b1 C
1!
#7040
0!
#7060
b1001 d
1E
b10 F
1K
1)
1/
b10 C
1!
#7080
0!
#7100
0E
0K
b1001 d
0)
b10 F
b1001 a
1]
0=
1;
b11 C
b10 B
1!
#7120
0!
#7140
0/
b0 C
1!
#7160
0!
#7180
0]
0;
b1 C
1!
#7200
0!
#7220
b1010 d
1E
b11 F
1K
1)
1/
b10 C
1!
#7240
0!
#7260
0E
0K
b1010 d
0)
b11 F
b1010 a
1]
0=
1;
b11 C
b11 B
1!
#7280
0!
#7300
0/
b0 C
1!
#7320
0!
#7340
0]
0;
b1 C
1!
#7360
0!
#7380
b1011 d
1E
b100 F
1K
1)
1/
b10 C
1!
#7400
0!
#7420
0E
0K
b1011 d
0)
b100 F
b1011 a
1]
0=
1;
b11 C
b100 B
1!
#7440
0!
#7460
0/
b0 C
1!
#7480
0!
#7500
0]
0;
b1 C
1!
#7520
0!
#7540
b1100 d
1E
b101 F
1K
1)
1/
b10 C
1!
#7560
0!
#7580
0K
b1100 d
0)
0E
b101 F
b1100 a
1]
0=
1;
b11 C
b101 B
1!
#7600
0!
#7620
0/
b0 C
1!
#7640
0!
#7660
0]
0;
b1 C
1!
