Homeworks/Homework 4/v2/B63561/B63561/target_spi.v
module target_spi(/*AUTOARG*/
   // Outputs
   MISO, trans_finalizada,
   // Inputs
   SCK, RESET, MOSI, SS, dato_enviado, CKP, CPH, SCK_anterior
   );
  input SCK,RESET,MOSI,SS, CKP, CPH, SCK_anterior;
  input [15:0] dato_enviado;
  output reg MISO, trans_finalizada;

  //ESTADOS
  localparam INICIO = 2'b01;
  localparam ESCRITURA_LECTURA = 2'b10;

  localparam MODE0 = 2'b00;   
  localparam MODE1 = 2'b01; 
  localparam MODE2 = 2'b10;   
  localparam MODE3 = 2'b11;   

  //VARIABLES INTERMEDIAS
  reg [15:0] dato_leido,prox_dato_leido;
  reg [1:0] estado, prox_estado;
  reg [4:0] cuenta_bits, cuenta_bits_d, prox_cuenta_bits;
  reg SS_d, MOSI_d;  
  wire negedge_SS;

  wire posedge_SCK;
  wire negedge_SCK; 
  
  assign posedge_SCK = SCK & ~SCK_anterior;   // MODO 0 y 3
  assign negedge_SCK = ~SCK & SCK_anterior;   // MODO 1 y 2

  //DETECCION DEL FLANCO POSITIVO DE SS
  assign negedge_SS = !SS && SS_d;

  //FLIP FLOPS PARA LAS TRANSACCIONES
  always @(posedge SCK) begin
	  if (RESET==0 || negedge_SS) begin
	  //estado        <= ESCRITURA_LECTURA;
    estado        <= INICIO;
		dato_leido   <= 0;
		cuenta_bits   <= 0;
		cuenta_bits_d <= 0;
	  end else begin      
		estado        <= prox_estado;
		dato_leido   <= prox_dato_leido;
		cuenta_bits_d <= cuenta_bits;
	  end
  end 

  always @(posedge SCK) begin
          if (RESET==0) 
                begin
                  if (MODE0 || MODE3) 
                    begin
                      SS_d    <= 1;
                      MOSI_d  <= 0;
                    end
                end 
          else 
                begin
                  if (MODE0 || MODE3) 
                    begin
                      SS_d   <= SS;
                      MOSI_d  <= MOSI;
                      MISO <= dato_enviado[15-cuenta_bits]; 
                    end
                end
  end

  always @(negedge SCK) begin
          if (RESET==0) 
            begin
                if (MODE1 || MODE2) 
                    begin
                      SS_d    <= 1;
                      MOSI_d  <= 0;
                    end
              end 
          else 
                begin
                if (MODE1 || MODE2) 
                    begin
                      SS_d   <= SS;
                      MOSI_d  <= MOSI;
                      MISO <= dato_enviado[15-cuenta_bits];
                    end
                end
  end

    //Logica combinacional
    always @(*) begin
      prox_estado        = estado;
      prox_dato_leido = dato_leido; 
      prox_cuenta_bits = cuenta_bits;

      case (estado)
        INICIO:
          begin
            prox_cuenta_bits = 0;
            trans_finalizada = 0;
            if (SS==0) begin
              prox_estado = ESCRITURA_LECTURA;
            end
          end
        ESCRITURA_LECTURA: 
          begin
              if (cuenta_bits == 18)
                begin
                  prox_estado = INICIO;
                end
              else 
                  begin
                    case ({CKP, CPH})
                      MODE0:      
                          begin
                            if (posedge_SCK) 
                              begin 
                                if (MOSI == 0 || MOSI ==1)
                                  begin
                                    prox_cuenta_bits = cuenta_bits+1;
                                    prox_dato_leido[15-cuenta_bits] = MOSI;
                                      if (cuenta_bits==30) 
                                        begin
                                          trans_finalizada = 1;
                                          prox_estado = INICIO;
                                        end 
                                  end
                             end
                          end
                      MODE1:  
                           begin
                            if (negedge_SCK) 
                               begin 
                                if (MOSI == 0 || MOSI ==1)
                                  begin
                                    prox_cuenta_bits = cuenta_bits+1;
                                    prox_dato_leido[15-cuenta_bits] = MOSI;
                                      if (cuenta_bits==30) 
                                        begin
                                          trans_finalizada = 1;
                                          prox_estado = INICIO;
                                        end 
                                  end
                              end
                          end
                      MODE2:    
                          begin
                            if (negedge_SCK) 
                              begin 
                                if (MOSI == 0 || MOSI ==1)
                                  begin
                                    prox_cuenta_bits = cuenta_bits+1;
                                    prox_dato_leido[15-cuenta_bits] = MOSI;
                                      if (cuenta_bits==30) 
                                        begin
                                          trans_finalizada = 1;
                                          prox_estado = INICIO;
                                        end 
                                  end
                              end
                          end
                      MODE3:  
                          begin
                            if (posedge_SCK) 
                              begin
                                if (MOSI == 0 || MOSI ==1)
                                  begin
                                    prox_cuenta_bits = cuenta_bits+1;
                                    prox_dato_leido[15-cuenta_bits] = MOSI;
                                      if (cuenta_bits==30) 
                                        begin
                                          trans_finalizada = 1;
                                          prox_estado = INICIO;
                                        end 
                                  end
                             end
                          end
                      default: begin end
                    endcase
                  end
              
          end
        default:  
          begin
            prox_estado = INICIO;
            prox_dato_leido = 0;
          end
      endcase;
    end

  always @(posedge SCK) begin
  if (!RESET) 
    begin
        if (MODE0 || MODE3) begin
          cuenta_bits   <= 0;
          cuenta_bits_d <= 0;
        end
    end 
  else 
  begin
      if (MODE0 || MODE3) begin
          cuenta_bits   <= prox_cuenta_bits;
          cuenta_bits_d <= cuenta_bits;
          dato_leido <= prox_dato_leido;
        end
  end
end

always @(negedge SCK) begin
  if (!RESET) 
    begin
        if (MODE1 || MODE2) begin
          cuenta_bits   <= 0;
          cuenta_bits_d <= 0;
        end
    end 
  else 
  begin
      if (MODE1 || MODE2) begin
          cuenta_bits   <= prox_cuenta_bits;
          cuenta_bits_d <= cuenta_bits;
          dato_leido <= prox_dato_leido;
        end
  end
end

endmodule

Homeworks/Homework 5/CPU_spi.v
module CPU_spi(
   // Outputs
   MOSI, CS, SCK, SCK_anterior,
   CLK, RESET, START_STB, MISO, transaccion, trans_finalizada, CKP, CPH
   );

  // Entradas y salidas
  input CLK,RESET,START_STB,MISO, trans_finalizada, CKP, CPH;
  input [15:0] transaccion;
  output reg MOSI, CS;
  output SCK, SCK_anterior;

  // Variables intermedias
  reg [1:0]  estado, prox_estado;
  reg [15:0] dato_leido, prox_dato_leido;
  reg [4:0]  cuenta_bits_d, cuenta_bits, prox_cuenta_bits;
  reg NXT_CS, MISO_d;
  reg [4:0] aux;
  reg SCK_anterior;  
  reg PROX_MOSI;
  
  localparam INICIO    = 2'b01;
  localparam ESCRITURA_LECTURA = 2'b10;

  localparam MODE0 = 2'b00;   
  localparam MODE1 = 2'b01; 
  localparam MODE2 = 2'b10;   
  localparam MODE3 = 2'b11;    

  wire posedge_SCK;
  wire negedge_SCK;

  //Flip flops
  always @(posedge CLK) begin
    if (RESET==0) begin
      estado        <= INICIO;
      dato_leido <= 0;
      cuenta_bits <= 0;
      aux <= 0;
    end else begin
      estado <= prox_estado;
    end
  end

  // Logica combinacional
  always @(*) begin

  if (START_STB) flag = 1;
  prox_estado        = estado;
  prox_dato_leido    = dato_leido;
  NXT_CS = CS;
  prox_cuenta_bits = cuenta_bits;
  PROX_MOSI = MOSI;
  
    case (estado)
      INICIO:
        begin
          prox_cuenta_bits = 0;
          NXT_CS = !START_STB;
	        if (START_STB) 
              begin
                  prox_estado = ESCRITURA_LECTURA;
              end 
	      end
      ESCRITURA_LECTURA: 
        begin
            if (cuenta_bits == 18)
              begin
                prox_estado = INICIO;
                flag = 0;
              end
            else 
                begin
                  NXT_CS = 0;
                  case ({CKP, CPH})
                    MODE0:      
                        begin
                          if (posedge_SCK) 
                              begin 
                                PROX_MOSI <= transaccion[15-cuenta_bits];
                                if (MISO == 0 || MISO == 1) 
                                  begin
                                    prox_cuenta_bits = cuenta_bits+1;
                                    aux = cuenta_bits_d - 1;
                                    if (aux > 15) aux = 0; 
                                    prox_dato_leido[15-aux] = MISO;
                                  end
                              end
                        end
                    MODE1:  
                        begin
                          if (negedge_SCK) 
                              begin 
                                PROX_MOSI <= transaccion[15-cuenta_bits];
                                if (MISO == 0 || MISO == 1) 
                                  begin
                                    prox_cuenta_bits = cuenta_bits+1;
                                    aux = cuenta_bits_d - 1;
                                    if (aux > 15) aux = 0; 
                                    prox_dato_leido[15-aux] = MISO;
                                  end
                              end
                        end
                    MODE2:    
                        begin
                          if (negedge_SCK) 
                              begin 
                                PROX_MOSI <= transaccion[15-cuenta_bits];
                                if (MISO == 0 || MISO == 1) 
                                  begin
                                    prox_cuenta_bits = cuenta_bits+1;
                                    aux = cuenta_bits_d - 1;
                                    if (aux > 15) aux = 0; 
                                    prox_dato_leido[15-aux] = MISO;
                                  end
                              end
                        end
                    MODE3:  
                        begin
                          if (posedge_SCK) 
                              begin 
                                PROX_MOSI <= transaccion[15-cuenta_bits];
                                if (MISO == 0 || MISO == 1) 
                                  begin
                                    prox_cuenta_bits = cuenta_bits+1;
                                    aux = cuenta_bits_d - 1;
                                    if (aux > 15) aux = 0; 
                                    prox_dato_leido[15-aux] = MISO;
                                  end
                              end
                        end
                    default: begin end
                  endcase
                end
            
	      end
      default:  
        begin
          prox_estado = INICIO;
          prox_dato_leido = 0;
	      end
    endcase;
  end

// Generación del reloj de salida SCK
reg clk_div2;
wire clk_div4;
reg [1:0] count_clock;
reg SCK_reg, flag;

always @(posedge CLK) begin
  if (RESET==0) begin
    clk_div2    <= 0;
    count_clock <= 0;
    SCK_anterior <= 0;
  end 
  else if (flag) begin
    clk_div2    <= ~clk_div2;
    count_clock <= count_clock+1;
    SCK_anterior <= SCK;
  end
  else begin
    clk_div2    <= 0;
    count_clock <= 0;
  end

end

assign clk_div4 = count_clock[1];

always @(*) begin
    case ({CKP, CPH})
      MODE0: SCK_reg = clk_div2;
      MODE1: SCK_reg = ~clk_div2;
      MODE2: SCK_reg = clk_div2;
      MODE3: SCK_reg = ~clk_div2;
      default: SCK_reg = CKP;
    endcase
end

assign SCK = SCK_reg;
assign posedge_SCK = SCK & ~SCK_anterior;   // MODO 0 y 3
assign negedge_SCK = ~SCK & SCK_anterior;     // MODO 1 y 2


always @(posedge SCK) begin
  CS <= 1;
  if (RESET==0 || START_STB) 
    begin
        if (MODE0 || MODE3) begin
          cuenta_bits   <= 0;
          cuenta_bits_d <= 0;
          MISO_d  <= 0;
        end
    end 
  else 
  begin
      CS       <= NXT_CS;
      if (MODE0 || MODE3) begin
          cuenta_bits   <= prox_cuenta_bits;
          cuenta_bits_d <= cuenta_bits;
          dato_leido <= prox_dato_leido;
          MISO_d  <= MISO;
          PROX_MOSI <= transaccion[15-cuenta_bits];
          MOSI <= PROX_MOSI;
        end
  end
end

always @(negedge SCK) begin
  CS <= 1;
  if (RESET==0 || START_STB) 
    begin
        if (MODE1 || MODE2) begin
          cuenta_bits   <= 0;
          cuenta_bits_d <= 0;
        end
    end 
  else 
  begin
      CS <= NXT_CS;
      if (MODE1 || MODE2) begin
          cuenta_bits   <= prox_cuenta_bits;
          cuenta_bits_d <= cuenta_bits;
          dato_leido <= prox_dato_leido;
          MISO_d  <= MISO;
          MOSI <= PROX_MOSI;
        end
  end
end


endmodule

Homeworks/Homework 4/v2/B63561/B63561/testbench_spi.v
`include "CPU_spi.v"
`include "target_spi.v"

// Testbench Code Goes here
module spi_tb;

reg         CLK, RESET, spi_start_stb, CKP, CPH;
reg  [31:0] transaccion;
reg  [15:0] dato_enviado;
wire        SCK, MOSICPU_to_MOSIT1, MISOT1_to_MOSIT2, MISOT2_to_MISOCPU, CS, MISO, SCK_anterior;

initial begin
	$dumpfile("spi.vcd");
	$dumpvars(-1, U0);
	$dumpvars(-1, U1);
	$dumpvars(-1, U2);
end


initial begin
  CLK = 0;
  RESET = 1;

/********************************** Prueba Modo 0 **********************************/
  /*#60 RESET = 0;
  #120 RESET = 1;
	  CKP = 0;
	  CPH = 0; 
      spi_start_stb = 0;
      transaccion = 16'b0000001100000101; // 0305
	  dato_enviado = 16'b0000011000000001; // 0601

  #80 spi_start_stb = 1;
  #45 spi_start_stb = 0;*/
/********************************** Prueba Modo 1 **********************************/
  /*#60 RESET = 0;
  #120 RESET = 1;
	  CKP = 0;
	  CPH = 1; 
      spi_start_stb = 0;
      transaccion = 16'b0000001100000101; // 0305
	  dato_enviado = 16'b0000011000000001; // 0601

  #80 spi_start_stb = 1;
  #45 spi_start_stb = 0;*/
/********************************** Prueba Modo 2 **********************************/
  /*#60 RESET = 0;
  #120 RESET = 1;
	  CKP = 1;
	  CPH = 0; 
      spi_start_stb = 0;
      transaccion = 16'b0000001100000101; // 0305
	  dato_enviado = 16'b0000011000000001; // 0601

  #80 spi_start_stb = 1;
  #45 spi_start_stb = 0;*/

/********************************** Prueba Modo 3 **********************************/

  #60 RESET = 0;
  #120 RESET = 1;
	  CKP = 1;
	  CPH = 1; 
      spi_start_stb = 0;
      transaccion = 16'b0000001100000101; // 0305
	  dato_enviado = 16'b0000011000000001; // 0601

  #80 spi_start_stb = 1;
  #45 spi_start_stb = 0;
  
  #3000 $finish;

end

always begin
 #20 CLK = !CLK;
end


CPU_spi U0 (
/*AUTOINST*/
		   // Outputs
		   .MOSI		 (MOSICPU_to_MOSIT1),
		   .CS			 (CS),
		   .SCK			 (SCK),
		   .SCK_anterior (SCK_anterior),
		   // Inputs
		   .CLK			(CLK),
		   .RESET		(RESET),
		   .START_STB	(spi_start_stb),
		   .MISO		(MISOT2_to_MISOCPU),
		   .transaccion		(transaccion[15:0]),
		   .trans_finalizada (trans_finalizada),
		   .CKP (CKP), 
		   .CPH (CPH)
		   );


target_spi U1 (
/*AUTOINST*/
		  // Outputs
		  .MISO			(MISOT1_to_MOSIT2),
		  .trans_finalizada (trans_finalizada),
		  // Inputs
		  .SCK			(SCK),
		  .SCK_anterior (SCK_anterior),
		  .RESET		(RESET),
		  .MOSI			(MOSICPU_to_MOSIT1),
		  .SS			(CS),
		  .dato_enviado	(dato_enviado[15:0]),
		  .CKP 			(CKP), 
		  .CPH 			(CPH)
		  );

target_spi U2 (
/*AUTOINST*/
		  // Outputs
		  .MISO			(MISOT2_to_MISOCPU),
		  .trans_finalizada (trans_finalizada),
		  // Inputs
		  .SCK			(SCK),
		  .SCK_anterior (SCK_anterior),
		  .RESET		(RESET),
		  .MOSI			(MISOT1_to_MOSIT2),
		  .SS			(CS),
		  .dato_enviado	(dato_enviado[15:0]),
		  .CKP 			(CKP), 
		  .CPH 			(CPH)
		  );

endmodule

Homeworks/Homework 5/spi.vcd
$date
	Tue Jun 11 18:34:31 2024
$end
$version
	Icarus Verilog
$end
$timescale
	1s
$end
$scope module spi_tb $end
$scope module U0 $end
$var wire 1 ! CKP $end
$var wire 1 " CLK $end
$var wire 1 # CPH $end
$var wire 1 $ RESET $end
$var wire 1 % START_STB $end
$var wire 1 & negedge_SCK $end
$var wire 1 ' posedge_SCK $end
$var wire 1 ( trans_finalizada $end
$var wire 16 ) transaccion [15:0] $end
$var wire 1 * clk_div4 $end
$var wire 1 + SCK $end
$var wire 1 , MISO $end
$var parameter 2 - ESCRITURA_LECTURA $end
$var parameter 2 . INICIO $end
$var parameter 2 / MODE0 $end
$var parameter 2 0 MODE1 $end
$var parameter 2 1 MODE2 $end
$var parameter 2 2 MODE3 $end
$var reg 1 3 CS $end
$var reg 1 4 MISO_d $end
$var reg 1 5 MOSI $end
$var reg 1 6 NXT_CS $end
$var reg 1 7 PROX_MOSI $end
$var reg 1 8 SCK_anterior $end
$var reg 1 + SCK_reg $end
$var reg 5 9 aux [4:0] $end
$var reg 1 : clk_div2 $end
$var reg 2 ; count_clock [1:0] $end
$var reg 5 < cuenta_bits [4:0] $end
$var reg 5 = cuenta_bits_d [4:0] $end
$var reg 16 > dato_leido [15:0] $end
$var reg 2 ? estado [1:0] $end
$var reg 1 @ flag $end
$var reg 5 A prox_cuenta_bits [4:0] $end
$var reg 16 B prox_dato_leido [15:0] $end
$var reg 2 C prox_estado [1:0] $end
$upscope $end
$upscope $end
$scope module spi_tb $end
$scope module U1 $end
$var wire 1 ! CKP $end
$var wire 1 # CPH $end
$var wire 1 5 MOSI $end
$var wire 1 $ RESET $end
$var wire 1 + SCK $end
$var wire 1 8 SCK_anterior $end
$var wire 1 3 SS $end
$var wire 16 D dato_enviado [15:0] $end
$var wire 1 E negedge_SCK $end
$var wire 1 F negedge_SS $end
$var wire 1 G posedge_SCK $end
$var parameter 2 H ESCRITURA_LECTURA $end
$var parameter 2 I INICIO $end
$var parameter 2 J MODE0 $end
$var parameter 2 K MODE1 $end
$var parameter 2 L MODE2 $end
$var parameter 2 M MODE3 $end
$var reg 1 N MISO $end
$var reg 1 O MOSI_d $end
$var reg 1 P SS_d $end
$var reg 5 Q cuenta_bits [4:0] $end
$var reg 5 R cuenta_bits_d [4:0] $end
$var reg 16 S dato_leido [15:0] $end
$var reg 2 T estado [1:0] $end
$var reg 5 U prox_cuenta_bits [4:0] $end
$var reg 16 V prox_dato_leido [15:0] $end
$var reg 2 W prox_estado [1:0] $end
$var reg 1 X trans_finalizada $end
$upscope $end
$upscope $end
$scope module spi_tb $end
$scope module U2 $end
$var wire 1 ! CKP $end
$var wire 1 # CPH $end
$var wire 1 N MOSI $end
$var wire 1 $ RESET $end
$var wire 1 + SCK $end
$var wire 1 8 SCK_anterior $end
$var wire 1 3 SS $end
$var wire 16 Y dato_enviado [15:0] $end
$var wire 1 Z negedge_SCK $end
$var wire 1 [ negedge_SS $end
$var wire 1 \ posedge_SCK $end
$var parameter 2 ] ESCRITURA_LECTURA $end
$var parameter 2 ^ INICIO $end
$var parameter 2 _ MODE0 $end
$var parameter 2 ` MODE1 $end
$var parameter 2 a MODE2 $end
$var parameter 2 b MODE3 $end
$var reg 1 , MISO $end
$var reg 1 c MOSI_d $end
$var reg 1 d SS_d $end
$var reg 5 e cuenta_bits [4:0] $end
$var reg 5 f cuenta_bits_d [4:0] $end
$var reg 16 g dato_leido [15:0] $end
$var reg 2 h estado [1:0] $end
$var reg 5 i prox_cuenta_bits [4:0] $end
$var reg 16 j prox_dato_leido [15:0] $end
$var reg 2 k prox_estado [1:0] $end
$var reg 1 l trans_finalizada $end
$upscope $end
$upscope $end
$enddefinitions $end
$comment Show the parameter values. $end
$dumpall
b11 b
b10 a
b1 `
b0 _
b1 ^
b10 ]
b11 M
b10 L
b1 K
b0 J
b1 I
b10 H
b11 2
b10 1
b1 0
b0 /
b1 .
b10 -
$end
#0
$dumpvars
xl
bx k
bx j
bx i
bx h
bx g
bx f
bx e
xd
xc
x\
x[
xZ
bx Y
xX
bx W
bx V
bx U
bx T
bx S
bx R
bx Q
xP
xO
xN
xG
xF
xE
bx D
bx C
bx B
bx A
x@
bx ?
bx >
bx =
bx <
bx ;
x:
bx 9
x8
x7
x6
x5
x4
x3
x,
x+
x*
bx )
x(
x'
x&
x%
1$
x#
0"
x!
$end
#20
0*
b0 ;
0:
1"
#40
0"
#60
b0 V
b1 W
b0 j
b1 k
0E
0Z
0&
b0 A
b0 B
b1 C
08
b0 9
b0 <
b0 >
b1 ?
1"
0$
#80
0"
#100
1"
#120
0"
#140
1"
#160
0"
#180
0F
0[
0(
0X
b0 U
0l
b0 i
x7
b0 =
13
b1 T
b0 S
b1 h
b0 g
1G
1\
1'
b1100000101 )
1+
16
b0 V
b1 W
b0 j
b1 k
1"
b11000000001 D
b11000000001 Y
0%
1#
1!
1$
#200
0"
#220
1"
#240
0"
#260
1P
b0 Q
1d
b0 e
07
b0 U
1E
b0 i
1Z
1&
0G
0\
0'
0+
b10 ?
18
b1 ;
1:
b10 C
06
1@
1"
1%
#280
0"
#300
b0 9
b1 A
0,
b0 f
0N
b0 R
04
07
06
1G
1\
1'
0E
0Z
0&
1*
1+
08
b10 ;
0:
1"
#305
b0 9
07
b1 A
06
0%
#320
0"
#340
b10 W
1F
b10 k
1[
0c
05
b1 <
03
1E
1Z
1&
07
b1 A
06
0G
0\
0'
0+
18
b11 ;
1:
1"
#360
0"
#380
0F
0[
b1 =
03
0O
0P
0d
b10 W
b10 k
b0 9
b10 A
1G
1\
1'
0E
0Z
0&
0*
1+
08
b0 ;
0:
1"
#400
0"
#420
b10 <
03
b10 W
1E
b10 k
1Z
1&
b10 A
0G
0\
0'
0+
18
b1 ;
1:
1"
#440
0"
#460
b1 9
b1 U
b1 i
b10 h
b10 T
b10 =
03
b10 W
b10 k
b11 A
1G
1\
1'
0E
0Z
0&
1*
1+
08
b10 ;
0:
1"
#480
0"
#500
b1 e
b1 Q
b11 <
03
b1 U
1E
b1 i
1Z
1&
b11 A
0G
0\
0'
0+
18
b11 ;
1:
1"
#520
0"
#540
b10 9
b11 =
03
b1 R
b1 f
b10 U
b10 i
b100 A
1G
1\
1'
0E
0Z
0&
0*
1+
08
b0 ;
0:
1"
#560
0"
#580
b100 <
03
b10 Q
b10 e
b10 U
1E
b10 i
1Z
1&
b100 A
0G
0\
0'
0+
18
b1 ;
1:
1"
#600
0"
#620
b11 9
b10 f
b10 R
b100 =
03
b11 U
b11 i
b101 A
1G
1\
1'
0E
0Z
0&
1*
1+
08
b10 ;
0:
1"
#640
0"
#660
b11 e
b11 Q
b101 <
03
b11 U
1E
b11 i
1Z
1&
b101 A
0G
0\
0'
0+
18
b11 ;
1:
1"
#680
0"
#700
b100 9
b101 =
03
b11 R
b11 f
b100 U
b100 i
b110 A
1G
1\
1'
0E
0Z
0&
0*
1+
08
b0 ;
0:
1"
#720
0"
#740
b110 <
03
b100 Q
b100 e
b100 U
1E
b100 i
1Z
1&
b110 A
0G
0\
0'
0+
18
b1 ;
1:
1"
#760
0"
#780
b101 9
b100 f
b100 R
17
b110 =
03
b101 U
b101 i
b111 A
1G
1\
1'
0E
0Z
0&
1*
1+
08
b10 ;
0:
1"
#800
0"
#820
b101 e
b101 Q
15
b111 <
03
b101 U
1E
b101 i
1Z
1&
17
b111 A
0G
0\
0'
0+
18
b11 ;
1:
1"
#840
0"
#860
b10000000000 j
b1000000000 B
b110 9
b111 =
03
1N
1O
b101 R
1,
b101 f
b10000000000 V
b110 U
b110 i
b1000 A
1G
1\
1'
0E
0Z
0&
0*
1+
08
b0 ;
0:
1"
#880
0"
#900
14
b1000000000 >
b1000 <
03
b10000000000 S
b110 Q
1c
b10000000000 g
b110 e
b110 U
b10000000000 V
1E
b110 i
b10000000000 j
1Z
1&
b1000 A
b1000000000 B
0G
0\
0'
0+
18
b1 ;
1:
1"
#920
0"
#940
b1100000000 B
b111 9
b110 f
b110 R
07
b1000 =
03
b11000000000 V
b111 U
b11000000000 j
b111 i
b1001 A
1G
1\
1'
0E
0Z
0&
1*
1+
08
b10 ;
0:
1"
#960
0"
#980
b11000000000 g
b111 e
b11000000000 S
b111 Q
05
b1100000000 >
b1001 <
03
b111 U
b11000000000 V
1E
b111 i
b11000000000 j
1Z
1&
07
b1001 A
b1100000000 B
0G
0\
0'
0+
18
b11 ;
1:
1"
#1000
0"
#1020
b1000 9
b1001 =
03
0N
0O
b111 R
0,
b111 f
b1000 U
b11000000000 j
b1000 i
b1010 A
1G
1\
1'
0E
0Z
0&
0*
1+
08
b0 ;
0:
1"
#1040
0"
#1060
04
b1010 <
03
b1000 Q
0c
b1000 e
b1000 U
1E
b1000 i
1Z
1&
b1010 A
0G
0\
0'
0+
18
b1 ;
1:
1"
#1080
0"
#1100
b1001 9
b1000 f
b1000 R
b1010 =
03
b1001 U
b1001 i
b1011 A
1G
1\
1'
0E
0Z
0&
1*
1+
08
b10 ;
0:
1"
#1120
0"
#1140
b1001 e
b1001 Q
b1011 <
03
b1001 U
1E
b1001 i
1Z
1&
b1011 A
0G
0\
0'
0+
18
b11 ;
1:
1"
#1160
0"
#1180
b1010 9
b1011 =
03
b1001 R
b1001 f
b1010 U
b1010 i
b1100 A
1G
1\
1'
0E
0Z
0&
0*
1+
08
b0 ;
0:
1"
#1200
0"
#1220
b1100 <
03
b1010 Q
b1010 e
b1010 U
1E
b1010 i
1Z
1&
b1100 A
0G
0\
0'
0+
18
b1 ;
1:
1"
#1240
0"
#1260
b1011 9
b1010 f
b1010 R
b1100 =
03
b1011 U
b1011 i
b1101 A
1G
1\
1'
0E
0Z
0&
1*
1+
08
b10 ;
0:
1"
#1280
0"
#1300
b1011 e
b1011 Q
b1101 <
03
b1011 U
1E
b1011 i
1Z
1&
b1101 A
0G
0\
0'
0+
18
b11 ;
1:
1"
#1320
0"
#1340
b1100 9
17
b1101 =
03
b1011 R
b1011 f
b1100 U
b1100 i
b1110 A
1G
1\
1'
0E
0Z
0&
0*
1+
08
b0 ;
0:
1"
#1360
0"
#1380
15
b1110 <
03
b1100 Q
b1100 e
b1100 U
1E
b1100 i
1Z
1&
17
b1110 A
0G
0\
0'
0+
18
b1 ;
1:
1"
#1400
0"
#1420
b1101 9
b1100 f
1O
b1100 R
07
b1110 =
03
b11000001000 V
b1101 U
b1101 i
b1111 A
1G
1\
1'
0E
0Z
0&
1*
1+
08
b10 ;
0:
1"
#1440
0"
#1460
b1101 e
b11000001000 S
b1101 Q
05
b1111 <
03
b1101 U
b11000001000 V
1E
b1101 i
1Z
1&
07
b1111 A
0G
0\
0'
0+
18
b11 ;
1:
1"
#1480
0"
#1500
b1110 9
17
b1111 =
03
0O
b1101 R
b1101 f
b1110 U
b1110 i
b10000 A
1G
1\
1'
0E
0Z
0&
0*
1+
08
b0 ;
0:
1"
#1520
0"
#1540
15
b10000 <
03
b1110 Q
b1110 e
b1110 U
1E
b1110 i
1Z
1&
17
b10000 A
0G
0\
0'
0+
18
b1 ;
1:
1"
#1560
0"
#1580
b1111 9
b1110 f
1O
b1110 R
x7
b10000 =
03
b11000001010 V
b1111 U
b1111 i
b10001 A
1G
1\
1'
0E
0Z
0&
1*
1+
08
b10 ;
0:
1"
#1600
0"
#1620
b1111 e
b11000001010 S
b1111 Q
x5
b10001 <
03
b1111 U
b11000001010 V
1E
b1111 i
1Z
1&
x7
b10001 A
0G
0\
0'
0+
18
b11 ;
1:
1"
#1640
0"
#1660
b11000000001 j
b1000001100000000 B
b0 9
b10001 =
03
1N
xO
b1111 R
1,
b1111 f
b10000 i
b10010 A
1G
1\
1'
0E
0Z
0&
0*
1+
08
b0 ;
0:
1"
#1680
0"
#1700
0@
b1 C
14
b1000001100000000 >
b10010 <
03
1c
b11000000001 g
b10000 e
1E
b10000 i
b11000000001 j
1Z
1&
b10010 A
b1000001100000000 B
0G
0\
0'
0+
18
b1 ;
1:
1"
#1720
0"
#1740
x,
b10000 f
b10010 =
b0 <
13
0E
0Z
0&
1+
16
b0 A
b0 ;
0:
b1 ?
1"
