Homeworks/Homework 4/MDIO 2-2023/receptor_mdio.v
module receptor_mdio(/*AUTOARG*/
   // Outputs
   mdio_data_write, reg_addr, mdio_in,
   // Inputs
   mdc, reset, mdio_out, mdio_oe, mdio_data_read
   );
  input mdc,reset,mdio_out,mdio_oe;
  input [15:0] mdio_data_read;
  output [15:0] mdio_data_write;
  output [5:0]  reg_addr;
  output reg mdio_in;

  //ESTADOS
  localparam REC_BITS = 2'b01;
  localparam ENV_BITS = 2'b10;

  //VARIABLES INTERMEDIAS
  reg [31:0] transaccion,prox_transaccion;
  reg [1:0] estado, prox_estado;
  reg [4:0] cuenta_bits, cuenta_bits_d;
  reg mdio_oe_d, mdio_out_d;
  wire posedge_mdio_oe, trans_finalizada, mitad_transaccion, start, write;

  // CONSTRUCCION DE VARIABLES INTERMEDIAS
  assign trans_finalizada  = (cuenta_bits_d == 31);
  assign mitad_transaccion = (cuenta_bits == 14);
  assign start             = ~transaccion[31] & transaccion[30]; // START = 01
  assign lectura           = transaccion[29]  & ~transaccion[28]; // READ = 10
  assign mdio_data_write   = transaccion[15:0];
  assign reg_addr          = transaccion[22:18];

  //DETECCION DEL FLANCO POSITIVO DE MDIO_OE
  assign posedge_mdio_oe = mdio_oe && !mdio_oe_d;

  //FLIP FLOPS PARA LAS TRANSACCIONES
  always @(posedge mdc) begin
	  if (reset || posedge_mdio_oe) begin
		estado        <= REC_BITS;
//		mdio_oe_d     <= 0;
		transaccion   <= 0;
		cuenta_bits   <= 0;
		cuenta_bits_d <= 0;
	  end else begin      
		estado        <= prox_estado;
//		mdio_oe_d     <= mdio_oe;
		transaccion   <= prox_transaccion;
		cuenta_bits   <= cuenta_bits+1;
		cuenta_bits_d <= cuenta_bits;
	  end
  end 

//FLIP FLOP PARA DETECTAR EL FLANCO DE MDIO
//NO PUEDE DEPENDER DE POSEDGE DE MDIO PORQUE
//HACE REFERENCIA CIRCULAR

  always @(posedge mdc) begin
          if (reset) begin
                mdio_oe_d   <= 0;
                mdio_out_d  <= 0;
          end else begin
                mdio_oe_d   <= mdio_oe;
                mdio_out_d  <= mdio_out;
          end
  end



  //LOGICA COMBINACIONAL
  always @(*) begin
    //RETROALIMENTACION PARA SOSTENER EL ESTADO Y LA TRANSACCION HASTA QUE SE
    //RECIBE UN CAMBIO
    prox_estado = estado;
    prox_transaccion = transaccion;
    if (reset || posedge_mdio_oe) prox_estado = REC_BITS;

    case (estado)
      REC_BITS:
          begin
            if (mdio_oe || mdio_oe_d) prox_transaccion[31-cuenta_bits] = mdio_out_d;
            if (lectura && mitad_transaccion) prox_estado = ENV_BITS;
	        end
      ENV_BITS:
	        begin
	            mdio_in = mdio_data_read[30-cuenta_bits];
              if (trans_finalizada) prox_estado = REC_BITS;
          end
    endcase
  end

endmodule

Homeworks/Homework 4/MDIO 2-2023/generador_mdio.v
module generador_mdio(/*AUTOARG*/
   // Outputs
   mdio_out, mdio_oe, mdc,
   // Inputs
   clk, reset, start_stb, mdio_in, transaccion
   );

  //Entradas y salidas
  input clk,reset,start_stb,mdio_in;
  input [31:0] transaccion;
  output reg mdio_out, mdio_oe;
  output     mdc;

  //Variables intermedias
  reg [2:0]  estado, prox_estado;
  reg [15:0] dato_recibido, prox_dato_recibido;
  reg [4:0]  cuenta_bits_d, cuenta_bits, prox_cuenta_bits; //Cuenta bits de la transacción
  wire write,trans_finalizada;
  reg nxt_mdio_oe;
  
  assign write = ~transaccion[29] && transaccion[28];
  assign trans_finalizada = (cuenta_bits_d == 31);
  //assign trans_finalizada = &cuenta_bits;

  localparam INICIO    = 3'b001;
  localparam ESCRITURA = 3'b010;
  localparam LECTURA   = 3'b100;

  //Fip flops
  always @(posedge clk) begin
    if (reset) begin
      estado        <= INICIO;
      dato_recibido <= 0;
    end else begin
      estado        <= prox_estado;
      dato_recibido <= prox_dato_recibido;
    end
  end

  //Logica combinacional
  always @(*) begin

  prox_estado        = estado;
  prox_dato_recibido = dato_recibido;
  nxt_mdio_oe = mdio_oe;
  prox_cuenta_bits = cuenta_bits;
  
    case (estado)
      INICIO:
        begin
          prox_cuenta_bits = 0;
          nxt_mdio_oe = start_stb;
	        if (start_stb && write)
            begin
                prox_estado = ESCRITURA;
            end else if (start_stb && ~write)
            begin
                prox_estado = LECTURA;
	          end
	      end
      ESCRITURA: 
        begin
        if (trans_finalizada) prox_estado = INICIO;
        nxt_mdio_oe = 1;
        prox_cuenta_bits = cuenta_bits+1;
        end
      LECTURA:
	      begin
           if (trans_finalizada) prox_estado = INICIO;
	         nxt_mdio_oe = (cuenta_bits < 16) ? 1 : 0;
	         prox_cuenta_bits = cuenta_bits+1;
           if (cuenta_bits < 15) prox_dato_recibido = 0;
	         else prox_dato_recibido[31-cuenta_bits_d] = mdio_in; 
        end
      default:  
        begin
	          prox_estado = INICIO;
	          prox_dato_recibido = 0;
	      end
    endcase;
  end

//Generación del reloj de salida MDC  
reg clk_div2; 
wire clk_div4;
reg [1:0] count_clock;

always @(posedge clk) begin
  if (reset) begin
    clk_div2    <= 0;
    count_clock <= 0;
  end else begin
    clk_div2    <= ~clk_div2;
    count_clock <= count_clock+1;
  end
end

assign clk_div4 = count_clock[1];
assign mdc = clk_div2;

// Incremento de cuenta_bits
always @(posedge mdc) begin
   if (reset || start_stb) begin
     cuenta_bits   <= 0;
     cuenta_bits_d <= 0;
     mdio_oe       <= 0;
   end else begin
     cuenta_bits   <= prox_cuenta_bits;
     cuenta_bits_d <= cuenta_bits;
     mdio_out      <= transaccion[31-cuenta_bits];
     mdio_oe       <= nxt_mdio_oe;
   end
 end

endmodule

Homeworks/Homework 4/MDIO 2-2023/testbench_mdio.v
`include "generador_mdio.v"
`include "receptor_mdio.v"
  

// Testbench Code Goes here
module mdio_tb;

reg         clock, reset, mdio_start_stb;
reg  [31:0] transaccion;
reg  [15:0] mdio_data_read;
wire [15:0] mdio_data_write;
wire [15:0] reg_addr;
wire        mdc, mdio_out, mdio_oe, mdio_in;

initial begin
	$dumpfile("mdio.vcd");
	$dumpvars(-1, U0);
	$dumpvars(-1, U1);
end


initial begin
  clock = 0;
  reset = 0;

  #20 reset = 1;
  #120 reset = 0;
      mdio_start_stb = 0;
      transaccion = 32'h55555555;
  #80 mdio_start_stb = 1;
  #40 mdio_start_stb = 0;
  #7800 transaccion = 32'h65557777;
        mdio_data_read = 16'h2468;
  #160  mdio_start_stb = 1;
  #40   mdio_start_stb = 0;
  #8000 $finish;
end

always begin
 #20 clock = !clock;
end


generador_mdio U0 (
/*AUTOINST*/
		   // Outputs
		   .mdio_out		(mdio_out),
		   .mdio_oe		(mdio_oe),
		   .mdc			(mdc),
		   // Inputs
		   .clk			(clock),
		   .reset		(reset),
		   .start_stb		(mdio_start_stb),
		   .mdio_in		(mdio_in),
		   .transaccion		(transaccion[31:0]));


receptor_mdio U1 (
/*AUTOINST*/
		  // Outputs
		  .mdio_data_write	(mdio_data_write[15:0]),
		  .reg_addr		(reg_addr[5:0]),
		  .mdio_in		(mdio_in),
		  // Inputs
		  .mdc			(mdc),
		  .reset		(reset),
		  .mdio_out		(mdio_out),
		  .mdio_oe		(mdio_oe),
		  .mdio_data_read	(mdio_data_read[15:0]));


endmodule

Homeworks/Homework 5/MDIO 2-2023/mdio.vcd
$date
	Mon Jun  3 13:04:57 2024
$end
$version
	Icarus Verilog
$end
$timescale
	1s
$end
$scope module mdio_tb $end
$scope module U0 $end
$var wire 1 ! clk $end
$var wire 1 " mdc $end
$var wire 1 # reset $end
$var wire 1 $ start_stb $end
$var wire 32 % transaccion [31:0] $end
$var wire 1 & write $end
$var wire 1 ' trans_finalizada $end
$var wire 1 ( mdio_in $end
$var wire 1 ) clk_div4 $end
$var parameter 3 * ESCRITURA $end
$var parameter 3 + INICIO $end
$var parameter 3 , LECTURA $end
$var reg 1 - clk_div2 $end
$var reg 2 . count_clock [1:0] $end
$var reg 5 / cuenta_bits [4:0] $end
$var reg 5 0 cuenta_bits_d [4:0] $end
$var reg 16 1 dato_recibido [15:0] $end
$var reg 3 2 estado [2:0] $end
$var reg 1 3 mdio_oe $end
$var reg 1 4 mdio_out $end
$var reg 1 5 nxt_mdio_oe $end
$var reg 5 6 prox_cuenta_bits [4:0] $end
$var reg 16 7 prox_dato_recibido [15:0] $end
$var reg 3 8 prox_estado [2:0] $end
$upscope $end
$upscope $end
$scope module mdio_tb $end
$scope module U1 $end
$var wire 1 9 lectura $end
$var wire 1 " mdc $end
$var wire 16 : mdio_data_read [15:0] $end
$var wire 1 3 mdio_oe $end
$var wire 1 4 mdio_out $end
$var wire 1 ; posedge_mdio_oe $end
$var wire 1 # reset $end
$var wire 1 < start $end
$var wire 1 = trans_finalizada $end
$var wire 6 > reg_addr [5:0] $end
$var wire 1 ? mitad_transaccion $end
$var wire 16 @ mdio_data_write [15:0] $end
$var parameter 2 A ENV_BITS $end
$var parameter 2 B REC_BITS $end
$var reg 5 C cuenta_bits [4:0] $end
$var reg 5 D cuenta_bits_d [4:0] $end
$var reg 2 E estado [1:0] $end
$var reg 1 ( mdio_in $end
$var reg 1 F mdio_oe_d $end
$var reg 1 G mdio_out_d $end
$var reg 2 H prox_estado [1:0] $end
$var reg 32 I prox_transaccion [31:0] $end
$var reg 32 J transaccion [31:0] $end
$upscope $end
$upscope $end
$enddefinitions $end
$comment Show the parameter values. $end
$dumpall
b1 B
b10 A
b100 ,
b1 +
b10 *
$end
#0
$dumpvars
bx J
bx I
bx H
xG
xF
bx E
bx D
bx C
bx @
x?
b0xxxxx >
x=
x<
x;
bx :
x9
bx 8
bx 7
bx 6
x5
x4
x3
bx 2
bx 1
bx 0
bx /
bx .
x-
x)
x(
x'
x&
bx %
x$
0#
x"
0!
$end
#20
b0 6
b0 7
b1 8
0)
b0 1
b1 2
b0 .
0"
0-
b1 H
1!
1#
#40
0!
#60
1!
#80
0!
#100
1!
#120
0!
#140
0;
03
b0 /
b1 .
1"
1-
1&
05
b0 6
bx H
1!
b1010101010101010101010101010101 %
0$
0#
#160
0!
#180
1)
b10 .
0"
0-
1!
#200
0!
#220
0'
0F
b0 0
b1 6
b11 .
1"
1-
b10 2
b10 8
15
1!
1$
#240
0!
#260
0)
b0 .
0"
0-
b1 6
15
1!
0$
#280
0!
#300
b1 H
1;
b10 6
13
04
b1 /
b1 .
1"
1-
1!
#320
0!
#340
1)
b10 .
0"
0-
1!
#360
0!
#380
0<
09
b0 >
0;
0=
0?
b0 @
b0 I
b11 6
0G
1F
b0 D
b0 C
b0 J
b1 E
14
b1 0
b10 /
b11 .
1"
1-
1!
#400
0!
#420
0)
b0 .
0"
0-
1!
#440
0!
#460
b100 6
b1000000000000000000000000000000 I
04
b10 0
b11 /
b1 C
1G
b1 .
1"
1-
1!
#480
0!
#500
1)
b10 .
0"
0-
1!
#520
0!
#540
1<
b101 6
0G
b1 D
b10 C
b1000000000000000000000000000000 J
14
b11 0
b100 /
b11 .
1"
1-
1!
#560
0!
#580
0)
b0 .
0"
0-
1!
#600
0!
#620
b110 6
b1010000000000000000000000000000 I
04
b100 0
b101 /
b10 D
b11 C
1G
b1 .
1"
1-
1!
#640
0!
#660
1)
b10 .
0"
0-
1!
#680
0!
#700
b111 6
0G
b11 D
b100 C
b1010000000000000000000000000000 J
14
b101 0
b110 /
b11 .
1"
1-
1!
#720
0!
#740
0)
b0 .
0"
0-
1!
#760
0!
#780
b1000 6
b1010100000000000000000000000000 I
04
b110 0
b111 /
b100 D
b101 C
1G
b1 .
1"
1-
1!
#800
0!
#820
1)
b10 .
0"
0-
1!
#840
0!
#860
b1001 6
0G
b101 D
b110 C
b1010100000000000000000000000000 J
14
b111 0
b1000 /
b11 .
1"
1-
1!
#880
0!
#900
0)
b0 .
0"
0-
1!
#920
0!
#940
b1010 6
b1010101000000000000000000000000 I
04
b1000 0
b1001 /
b110 D
b111 C
1G
b1 .
1"
1-
1!
#960
0!
#980
1)
b10 .
0"
0-
1!
#1000
0!
#1020
b1011 6
0G
b111 D
b1000 C
b1010101000000000000000000000000 J
14
b1001 0
b1010 /
b11 .
1"
1-
1!
#1040
0!
#1060
0)
b0 .
0"
0-
1!
#1080
0!
#1100
b1100 6
b1010101010000000000000000000000 I
04
b1010 0
b1011 /
b1000 D
b1001 C
1G
b1 .
1"
1-
1!
#1120
0!
#1140
1)
b10 .
0"
0-
1!
#1160
0!
#1180
b10000 >
b1101 6
0G
b1001 D
b1010 C
b1010101010000000000000000000000 J
14
b1011 0
b1100 /
b11 .
1"
1-
1!
#1200
0!
#1220
0)
b0 .
0"
0-
1!
#1240
0!
#1260
b1110 6
b1010101010100000000000000000000 I
04
b1100 0
b1101 /
b1010 D
b1011 C
1G
b1 .
1"
1-
1!
#1280
0!
#1300
1)
b10 .
0"
0-
1!
#1320
0!
#1340
b10100 >
b1111 6
0G
b1011 D
b1100 C
b1010101010100000000000000000000 J
14
b1101 0
b1110 /
b11 .
1"
1-
1!
#1360
0!
#1380
0)
b0 .
0"
0-
1!
#1400
0!
#1420
b10000 6
b1010101010101000000000000000000 I
04
b1110 0
b1111 /
b1100 D
b1101 C
1G
b1 .
1"
1-
1!
#1440
0!
#1460
1)
b10 .
0"
0-
1!
#1480
0!
#1500
b10101 >
1?
b10001 6
0G
b1101 D
b1110 C
b1010101010101000000000000000000 J
14
b1111 0
b10000 /
b11 .
1"
1-
1!
#1520
0!
#1540
0)
b0 .
0"
0-
1!
#1560
0!
#1580
b10010 6
0?
b1010101010101010000000000000000 I
04
b10000 0
b10001 /
b1110 D
b1111 C
1G
b1 .
1"
1-
1!
#1600
0!
#1620
1)
b10 .
0"
0-
1!
#1640
0!
#1660
b10011 6
0G
b1111 D
b10000 C
b1010101010101010000000000000000 J
14
b10001 0
b10010 /
b11 .
1"
1-
1!
#1680
0!
#1700
0)
b0 .
0"
0-
1!
#1720
0!
#1740
b10100 6
b1010101010101010100000000000000 I
04
b10010 0
b10011 /
b10000 D
b10001 C
1G
b1 .
1"
1-
1!
#1760
0!
#1780
1)
b10 .
0"
0-
1!
#1800
0!
#1820
b100000000000000 @
b10101 6
0G
b10001 D
b10010 C
b1010101010101010100000000000000 J
14
b10011 0
b10100 /
b11 .
1"
1-
1!
#1840
0!
#1860
0)
b0 .
0"
0-
1!
#1880
0!
#1900
b10110 6
b1010101010101010101000000000000 I
04
b10100 0
b10101 /
b10010 D
b10011 C
1G
b1 .
1"
1-
1!
#1920
0!
#1940
1)
b10 .
0"
0-
1!
#1960
0!
#1980
b101000000000000 @
b10111 6
0G
b10011 D
b10100 C
b1010101010101010101000000000000 J
14
b10101 0
b10110 /
b11 .
1"
1-
1!
#2000
0!
#2020
0)
b0 .
0"
0-
1!
#2040
0!
#2060
b11000 6
b1010101010101010101010000000000 I
04
b10110 0
b10111 /
b10100 D
b10101 C
1G
b1 .
1"
1-
1!
#2080
0!
#2100
1)
b10 .
0"
0-
1!
#2120
0!
#2140
b101010000000000 @
b11001 6
0G
b10101 D
b10110 C
b1010101010101010101010000000000 J
14
b10111 0
b11000 /
b11 .
1"
1-
1!
#2160
0!
#2180
0)
b0 .
0"
0-
1!
#2200
0!
#2220
b11010 6
b1010101010101010101010100000000 I
04
b11000 0
b11001 /
b10110 D
b10111 C
1G
b1 .
1"
1-
1!
#2240
0!
#2260
1)
b10 .
0"
0-
1!
#2280
0!
#2300
b101010100000000 @
b11011 6
0G
b10111 D
b11000 C
b1010101010101010101010100000000 J
14
b11001 0
b11010 /
b11 .
1"
1-
1!
#2320
0!
#2340
0)
b0 .
0"
0-
1!
#2360
0!
#2380
b11100 6
b1010101010101010101010101000000 I
04
b11010 0
b11011 /
b11000 D
b11001 C
1G
b1 .
1"
1-
1!
#2400
0!
#2420
1)
b10 .
0"
0-
1!
#2440
0!
#2460
b101010101000000 @
b11101 6
0G
b11001 D
b11010 C
b1010101010101010101010101000000 J
14
b11011 0
b11100 /
b11 .
1"
1-
1!
#2480
0!
#2500
0)
b0 .
0"
0-
1!
#2520
0!
#2540
b11110 6
b1010101010101010101010101010000 I
04
b11100 0
b11101 /
b11010 D
b11011 C
1G
b1 .
1"
1-
1!
#2560
0!
#2580
1)
b10 .
0"
0-
1!
#2600
0!
#2620
b101010101010000 @
b11111 6
0G
b11011 D
b11100 C
b1010101010101010101010101010000 J
14
b11101 0
b11110 /
b11 .
1"
1-
1!
#2640
0!
#2660
0)
b0 .
0"
0-
1!
#2680
0!
#2700
b0 6
b1010101010101010101010101010100 I
04
b11110 0
b11111 /
b11100 D
b11101 C
1G
b1 .
1"
1-
1!
#2720
0!
#2740
1)
b10 .
0"
0-
1!
#2760
0!
#2780
b1 8
b101010101010100 @
1'
b1 6
0G
b11101 D
b11110 C
b1010101010101010101010101010100 J
14
b11111 0
b0 /
b11 .
1"
1-
1!
#2800
0!
#2820
05
b0 6
0)
b1 2
b0 .
0"
0-
1!
#2840
0!
#2860
0'
b1010101010101010101010101010101 I
03
04
b0 0
b11110 D
b11111 C
1G
b1 .
1"
1-
1!
#2880
0!
#2900
1)
b10 .
0"
0-
1!
#2920
0!
#2940
1=
b101010101010101 @
0G
0F
b11111 D
b0 C
b1010101010101010101010101010101 J
b11 .
1"
1-
1!
#2960
0!
#2980
0)
b0 .
0"
0-
1!
#3000
0!
#3020
0=
b0 D
b1 C
b1 .
1"
1-
1!
#3040
0!
#3060
1)
b10 .
0"
0-
1!
#3080
0!
#3100
b1 D
b10 C
b11 .
1"
1-
1!
#3120
0!
#3140
0)
b0 .
0"
0-
1!
#3160
0!
#3180
b10 D
b11 C
b1 .
1"
1-
1!
#3200
0!
#3220
1)
b10 .
0"
0-
1!
#3240
0!
#3260
b11 D
b100 C
b11 .
1"
1-
1!
#3280
0!
#3300
0)
b0 .
0"
0-
1!
#3320
0!
#3340
b100 D
b101 C
b1 .
1"
1-
1!
#3360
0!
#3380
1)
b10 .
0"
0-
1!
#3400
0!
#3420
b101 D
b110 C
b11 .
1"
1-
1!
#3440
0!
#3460
0)
b0 .
0"
0-
1!
#3480
0!
#3500
b110 D
b111 C
b1 .
1"
1-
1!
#3520
0!
#3540
1)
b10 .
0"
0-
1!
#3560
0!
#3580
b111 D
b1000 C
b11 .
1"
1-
1!
#3600
0!
#3620
0)
b0 .
0"
0-
1!
#3640
0!
#3660
b1000 D
b1001 C
b1 .
1"
1-
1!
#3680
0!
#3700
1)
b10 .
0"
0-
1!
#3720
0!
#3740
b1001 D
b1010 C
b11 .
1"
1-
1!
#3760
0!
#3780
0)
b0 .
0"
0-
1!
#3800
0!
#3820
b1010 D
b1011 C
b1 .
1"
1-
1!
#3840
0!
#3860
1)
b10 .
0"
0-
1!
#3880
0!
#3900
b1011 D
b1100 C
b11 .
1"
1-
1!
#3920
0!
#3940
0)
b0 .
0"
0-
1!
#3960
0!
#3980
b1100 D
b1101 C
b1 .
1"
1-
1!
#4000
0!
#4020
1)
b10 .
0"
0-
1!
#4040
0!
#4060
1?
b1101 D
b1110 C
b11 .
1"
1-
1!
#4080
0!
#4100
0)
b0 .
0"
0-
1!
#4120
0!
#4140
0?
b1110 D
b1111 C
b1 .
1"
1-
1!
#4160
0!
#4180
1)
b10 .
0"
0-
1!
#4200
0!
#4220
b1111 D
b10000 C
b11 .
1"
1-
1!
#4240
0!
#4260
0)
b0 .
0"
0-
1!
#4280
0!
#4300
b10000 D
b10001 C
b1 .
1"
1-
1!
#4320
0!
#4340
1)
b10 .
0"
0-
1!
#4360
0!
#4380
b10001 D
b10010 C
b11 .
1"
1-
1!
#4400
0!
#4420
0)
b0 .
0"
0-
1!
#4440
0!
#4460
b10010 D
b10011 C
b1 .
1"
1-
1!
#4480
0!
#4500
1)
b10 .
0"
0-
1!
#4520
0!
#4540
b10011 D
b10100 C
b11 .
1"
1-
1!
#4560
0!
#4580
0)
b0 .
0"
0-
1!
#4600
0!
#4620
b10100 D
b10101 C
b1 .
1"
1-
1!
#4640
0!
#4660
1)
b10 .
0"
0-
1!
#4680
0!
#4700
b10101 D
b10110 C
b11 .
1"
1-
1!
#4720
0!
#4740
0)
b0 .
0"
0-
1!
#4760
0!
#4780
b10110 D
b10111 C
b1 .
1"
1-
1!
#4800
0!
#4820
1)
b10 .
0"
0-
1!
#4840
0!
#4860
b10111 D
b11000 C
b11 .
1"
1-
1!
#4880
0!
#4900
0)
b0 .
0"
0-
1!
#4920
0!
#4940
b11000 D
b11001 C
b1 .
1"
1-
1!
#4960
0!
#4980
1)
b10 .
0"
0-
1!
#5000
0!
#5020
b11001 D
b11010 C
b11 .
1"
1-
1!
#5040
0!
#5060
0)
b0 .
0"
0-
1!
#5080
0!
#5100
b11010 D
b11011 C
b1 .
1"
1-
1!
#5120
0!
#5140
1)
b10 .
0"
0-
1!
#5160
0!
#5180
b11011 D
b11100 C
b11 .
1"
1-
1!
#5200
0!
#5220
0)
b0 .
0"
0-
1!
#5240
0!
#5260
b11100 D
b11101 C
b1 .
1"
1-
1!
#5280
0!
#5300
1)
b10 .
0"
0-
1!
#5320
0!
#5340
b11101 D
b11110 C
b11 .
1"
1-
1!
#5360
0!
#5380
0)
b0 .
0"
0-
1!
#5400
0!
#5420
b11110 D
b11111 C
b1 .
1"
1-
1!
#5440
0!
#5460
1)
b10 .
0"
0-
1!
#5480
0!
#5500
1=
b11111 D
b0 C
b11 .
1"
1-
1!
#5520
0!
#5540
0)
b0 .
0"
0-
1!
#5560
0!
#5580
0=
b0 D
b1 C
b1 .
1"
1-
1!
#5600
0!
#5620
1)
b10 .
0"
0-
1!
#5640
0!
#5660
b1 D
b10 C
b11 .
1"
1-
1!
#5680
0!
#5700
0)
b0 .
0"
0-
1!
#5720
0!
#5740
b10 D
b11 C
b1 .
1"
1-
1!
#5760
0!
#5780
1)
b10 .
0"
0-
1!
#5800
0!
#5820
b11 D
b100 C
b11 .
1"
1-
1!
#5840
0!
#5860
0)
b0 .
0"
0-
1!
#5880
0!
#5900
b100 D
b101 C
b1 .
1"
1-
1!
#5920
0!
#5940
1)
b10 .
0"
0-
1!
#5960
0!
#5980
b101 D
b110 C
b11 .
1"
1-
1!
#6000
0!
#6020
0)
b0 .
0"
0-
1!
#6040
0!
#6060
b110 D
b111 C
b1 .
1"
1-
1!
#6080
0!
#6100
1)
b10 .
0"
0-
1!
#6120
0!
#6140
b111 D
b1000 C
b11 .
1"
1-
1!
#6160
0!
#6180
0)
b0 .
0"
0-
1!
#6200
0!
#6220
b1000 D
b1001 C
b1 .
1"
1-
1!
#6240
0!
#6260
1)
b10 .
0"
0-
1!
#6280
0!
#6300
b1001 D
b1010 C
b11 .
1"
1-
1!
#6320
0!
#6340
0)
b0 .
0"
0-
1!
#6360
0!
#6380
b1010 D
b1011 C
b1 .
1"
1-
1!
#6400
0!
#6420
1)
b10 .
0"
0-
1!
#6440
0!
#6460
b1011 D
b1100 C
b11 .
1"
1-
1!
#6480
0!
#6500
0)
b0 .
0"
0-
1!
#6520
0!
#6540
b1100 D
b1101 C
b1 .
1"
1-
1!
#6560
0!
#6580
1)
b10 .
0"
0-
1!
#6600
0!
#6620
1?
b1101 D
b1110 C
b11 .
1"
1-
1!
#6640
0!
#6660
0)
b0 .
0"
0-
1!
#6680
0!
#6700
0?
b1110 D
b1111 C
b1 .
1"
1-
1!
#6720
0!
#6740
1)
b10 .
0"
0-
1!
#6760
0!
#6780
b1111 D
b10000 C
b11 .
1"
1-
1!
#6800
0!
#6820
0)
b0 .
0"
0-
1!
#6840
0!
#6860
b10000 D
b10001 C
b1 .
1"
1-
1!
#6880
0!
#6900
1)
b10 .
0"
0-
1!
#6920
0!
#6940
b10001 D
b10010 C
b11 .
1"
1-
1!
#6960
0!
#6980
0)
b0 .
0"
0-
1!
#7000
0!
#7020
b10010 D
b10011 C
b1 .
1"
1-
1!
#7040
0!
#7060
1)
b10 .
0"
0-
1!
#7080
0!
#7100
b10011 D
b10100 C
b11 .
1"
1-
1!
#7120
0!
#7140
0)
b0 .
0"
0-
1!
#7160
0!
#7180
b10100 D
b10101 C
b1 .
1"
1-
1!
#7200
0!
#7220
1)
b10 .
0"
0-
1!
#7240
0!
#7260
b10101 D
b10110 C
b11 .
1"
1-
1!
#7280
0!
#7300
0)
b0 .
0"
0-
1!
#7320
0!
#7340
b10110 D
b10111 C
b1 .
1"
1-
1!
#7360
0!
#7380
1)
b10 .
0"
0-
1!
#7400
0!
#7420
b10111 D
b11000 C
b11 .
1"
1-
1!
#7440
0!
#7460
0)
b0 .
0"
0-
1!
#7480
0!
#7500
b11000 D
b11001 C
b1 .
1"
1-
1!
#7520
0!
#7540
1)
b10 .
0"
0-
1!
#7560
0!
#7580
b11001 D
b11010 C
b11 .
1"
1-
1!
#7600
0!
#7620
0)
b0 .
0"
0-
1!
#7640
0!
#7660
b11010 D
b11011 C
b1 .
1"
1-
1!
#7680
0!
#7700
1)
b10 .
0"
0-
1!
#7720
0!
#7740
b11011 D
b11100 C
b11 .
1"
1-
1!
#7760
0!
#7780
0)
b0 .
0"
0-
1!
#7800
0!
#7820
b11100 D
b11101 C
b1 .
1"
1-
1!
#7840
0!
#7860
1)
b10 .
0"
0-
1!
#7880
0!
#7900
b11101 D
b11110 C
b11 .
1"
1-
1!
#7920
0!
#7940
0)
b0 .
0"
0-
1!
#7960
0!
#7980
b11110 D
b11111 C
b1 .
1"
1-
1!
#8000
0!
#8020
1)
b10 .
0"
0-
1!
#8040
0!
#8060
1=
b11111 D
b0 C
b11 .
1"
1-
0&
1!
b10010001101000 :
b1100101010101010111011101110111 %
#8080
0!
#8100
0)
b0 .
0"
0-
1!
#8120
0!
#8140
0=
b0 D
b1 C
b1 .
1"
1-
1!
#8160
0!
#8180
1)
b10 .
0"
0-
1!
#8200
0!
#8220
b1 D
b10 C
b1 6
b11 .
1"
1-
b100 2
b100 8
15
1!
1$
#8240
0!
#8260
0)
b0 .
0"
0-
b1 6
15
1!
0$
#8280
0!
#8300
1;
b10 6
b1000101010101010101010101010101 I
13
b1 /
b10 D
b11 C
b1 .
1"
1-
1!
#8320
0!
#8340
1)
b10 .
0"
0-
1!
#8360
0!
#8380
0<
b0 >
0;
b0 I
b0 @
b11 6
1F
b0 D
b0 C
b0 J
14
b1 0
b10 /
b11 .
1"
1-
1!
#8400
0!
#8420
0)
b0 .
0"
0-
1!
#8440
0!
#8460
b100 6
b1000000000000000000000000000000 I
b10 0
b11 /
b1 C
1G
b1 .
1"
1-
1!
#8480
0!
#8500
1)
b10 .
0"
0-
1!
#8520
0!
#8540
1<
b1100000000000000000000000000000 I
b101 6
b1 D
b10 C
b1000000000000000000000000000000 J
04
b11 0
b100 /
b11 .
1"
1-
1!
#8560
0!
#8580
0)
b0 .
0"
0-
1!
#8600
0!
#8620
19
b110 6
b100 0
b101 /
b10 D
b11 C
b1100000000000000000000000000000 J
0G
b1 .
1"
1-
1!
#8640
0!
#8660
1)
b10 .
0"
0-
1!
#8680
0!
#8700
b111 6
b11 D
b100 C
14
b101 0
b110 /
b11 .
1"
1-
1!
#8720
0!
#8740
0)
b0 .
0"
0-
1!
#8760
0!
#8780
b1000 6
b1100100000000000000000000000000 I
04
b110 0
b111 /
b100 D
b101 C
1G
b1 .
1"
1-
1!
#8800
0!
#8820
1)
b10 .
0"
0-
1!
#8840
0!
#8860
b1001 6
0G
b101 D
b110 C
b1100100000000000000000000000000 J
14
b111 0
b1000 /
b11 .
1"
1-
1!
#8880
0!
#8900
0)
b0 .
0"
0-
1!
#8920
0!
#8940
b1010 6
b1100101000000000000000000000000 I
04
b1000 0
b1001 /
b110 D
b111 C
1G
b1 .
1"
1-
1!
#8960
0!
#8980
1)
b10 .
0"
0-
1!
#9000
0!
#9020
b1011 6
0G
b111 D
b1000 C
b1100101000000000000000000000000 J
14
b1001 0
b1010 /
b11 .
1"
1-
1!
#9040
0!
#9060
0)
b0 .
0"
0-
1!
#9080
0!
#9100
b1100 6
b1100101010000000000000000000000 I
04
b1010 0
b1011 /
b1000 D
b1001 C
1G
b1 .
1"
1-
1!
#9120
0!
#9140
1)
b10 .
0"
0-
1!
#9160
0!
#9180
b10000 >
b1101 6
0G
b1001 D
b1010 C
b1100101010000000000000000000000 J
14
b1011 0
b1100 /
b11 .
1"
1-
1!
#9200
0!
#9220
0)
b0 .
0"
0-
1!
#9240
0!
#9260
b1110 6
b1100101010100000000000000000000 I
04
b1100 0
b1101 /
b1010 D
b1011 C
1G
b1 .
1"
1-
1!
#9280
0!
#9300
1)
b10 .
0"
0-
1!
#9320
0!
#9340
b10100 >
b1111 6
0G
b1011 D
b1100 C
b1100101010100000000000000000000 J
14
b1101 0
b1110 /
b11 .
1"
1-
1!
#9360
0!
#9380
0)
b0 .
0"
0-
1!
#9400
0!
#9420
b10000 6
b1100101010101000000000000000000 I
04
b1110 0
b1111 /
b1100 D
b1101 C
1G
b1 .
1"
1-
1!
#9440
0!
#9460
1)
b10 .
0"
0-
1!
#9480
0!
#9500
b10 H
b10101 >
1?
b10001 6
05
0G
b1101 D
b1110 C
b1100101010101000000000000000000 J
14
b1111 0
b10000 /
b11 .
1"
1-
1!
#9520
0!
#9540
0)
b0 .
0"
0-
1!
#9560
0!
#9580
b10010 6
0?
0(
03
04
b10000 0
b10001 /
b1110 D
b1111 C
b10 E
1G
b1 .
1"
1-
1!
#9600
0!
#9620
1)
b10 .
0"
0-
1!
#9640
0!
#9660
b10011 6
0G
0F
b1111 D
b10000 C
14
b10001 0
b10010 /
b11 .
1"
1-
1!
#9680
0!
#9700
0)
b0 .
0"
0-
1!
#9720
0!
#9740
b10000000000000 7
b10100 6
1(
b10010 0
b10011 /
b10000 D
b10001 C
1G
b1 .
1"
1-
1!
#9760
0!
#9780
b10100 6
1)
b10000000000000 1
b10 .
0"
0-
1!
#9800
0!
