Homeworks/Homework 5/MDIO_HECHO_EN_CLASE_ESTE_SEMESTRE/objetivo_mdio.v
module objetivo_mdio(
   // Inputs
   mdio_out, mdio_oe, mdc, dato_leido,
   // Outputs
   reset, mdio_in, reg_addr
   );

  //Entradas y salidas
  output reg mdio_in;
  output     [4:0] reg_addr;
  input reset, mdio_out, mdio_oe, mdc;
  input [15:0] dato_leido;

  localparam INICIO       = 3'b001;
  localparam RECIBIR_BITS = 3'b010;
  localparam ENVIAR_BITS  = 3'b100;

  //Variables intermedias
  reg [2:0] estado, prox_estado;
  reg [4:0] cuenta_bits, prox_cuenta_bits;
  wire escritura, lectura;
  wire [1:0] start, op;
  wire [4:0] phy_addr;
  reg [31:0] transaccion;

  assign escritura = (op[1:0] == 2'b01);
  assign lectura   =   (op == 2'b10);
  assign start     = transaccion[31:30];
  assign op        = transaccion[29:28];
  assign phy_addr  = transaccion[27:24];
  assign reg_addr  = transaccion[24:20];

  //Fip flops
  always @(posedge mdc) begin
    if (reset) begin
      estado       <= INICIO;
      cuenta_bits  <= 0;
    end else begin
      estado       <= prox_estado;
      cuenta_bits  <= prox_cuenta_bits;
    end
  end

  //Logica combinacional

  always @(*) begin
    prox_estado = estado;
    prox_cuenta_bits = cuenta_bits;

    case (estado)
	    INICIO: begin
		    prox_cuenta_bits = 0;
		    if (mdio_oe) begin
		        prox_estado = RECIBIR_BITS;
//			transaccion[31-cuenta_bits] = mdio_out;
//			prox_cuenta_bits = cuenta_bits+1;
		    end
	    end
	    RECIBIR_BITS: 
        begin
	        prox_cuenta_bits = cuenta_bits+1;
		      transaccion[31-cuenta_bits] = mdio_out;
	    	  if (lectura && (cuenta_bits == 15)) prox_estado = ENVIAR_BITS;
		      if (cuenta_bits == 31) prox_estado = INICIO;
        end

	    ENVIAR_BITS: 
        begin
          prox_cuenta_bits = cuenta_bits+1;
          mdio_in = dato_leido[31-cuenta_bits];
          if (cuenta_bits == 31) prox_estado = INICIO;
        end
            default: begin
	    end
    endcase;
  end
endmodule

Homeworks/Homework 5/MDIO_HECHO_EN_CLASE_ESTE_SEMESTRE/generador_mdio.v
module generador_mdio(
   // Outputs
   mdio_out, mdio_oe, mdc, dato_leido,
   // Inputs
   clk, reset, start_stb, mdio_in, transaccion
   );

  //Entradas y salidas
  input clk,reset,start_stb,mdio_in;
  input [31:0] transaccion;
  output reg mdio_out, mdio_oe;
  output     mdc;
  output reg [15:0] dato_leido;

  localparam INICIO    = 3'b001;
  localparam ESCRITURA = 3'b010;
  localparam LECTURA   = 3'b100;
  localparam DIV_FREQ  = 2;

  //Variables intermedias
  reg [2:0] estado, prox_estado;
  reg [4:0] cuenta_bits, prox_cuenta_bits;
  reg [DIV_FREQ-1:0] div_freq;
  reg start_stb_d, start_stb_reg;
  wire iniciar, escritura, lectura;
  wire posedge_mdc;
  reg mdc_anterior, prox_mdio_out;

  assign iniciar   = (transaccion[31:30] == 2'b01);
  assign escritura = (transaccion[29:28] == 2'b01);
  assign lectura = (transaccion[29:28] == 2'b10);
  //MDC a fraccion del clk
  assign mdc = div_freq[DIV_FREQ-1];
  assign posedge_mdc = !mdc_anterior && mdc;

  //Fip flops
  always @(posedge clk) begin
    if (reset) begin
      estado       <= INICIO;
      cuenta_bits  <= 0;
      div_freq     <= 0;
      mdc_anterior <= 0;
      mdio_out     <= 0;
      start_stb_reg <= 0;
      start_stb_d  <= 0;
    end else begin
      estado        <= prox_estado;
      cuenta_bits   <= prox_cuenta_bits;
      div_freq      <= div_freq+1;
      mdc_anterior  <= mdc;
      mdio_out      <= prox_mdio_out;
      start_stb_reg <= start_stb;
      start_stb_d   <= start_stb_reg;
    end
  end

  //Logica combinacional

/*  always @(posedge mdc) begin
     if (estado == ESCRITURA) prox_cuenta_bits = cuenta_bits+1;
  end */

  always @(*) begin
    prox_estado = estado;
    prox_cuenta_bits = cuenta_bits;
    prox_mdio_out = mdio_out;

    case (estado)
	    INICIO:
        begin
		      mdio_oe = 1'b0;
		      prox_cuenta_bits = 0;
		      if (iniciar && lectura && (start_stb || start_stb_d) && posedge_mdc)   prox_estado = LECTURA;
		      if (iniciar && escritura && (start_stb || start_stb_d) && posedge_mdc) prox_estado = ESCRITURA;
	      end

	    ESCRITURA: 
        begin
		      mdio_oe = 1'b1;
          //prox_mdio_out = transaccion[31-cuenta_bits];
		      if (posedge_mdc) begin 
		        prox_cuenta_bits = cuenta_bits+1;
		        prox_mdio_out = transaccion[31-cuenta_bits];
		      if (cuenta_bits == 31) prox_estado = INICIO;
                end
        end

	    LECTURA:
      begin
		    mdio_oe = (cuenta_bits < 16);
        if (posedge_mdc) prox_mdio_out = transaccion[31-cuenta_bits];
        if (!mdio_oe) dato_leido[31-cuenta_bits] = mdio_in;
	      if (posedge_mdc) prox_cuenta_bits = cuenta_bits+1;
		    if (cuenta_bits == 31) prox_estado = INICIO;
	    end
            default: begin end
    endcase;
  end
endmodule

Homeworks/Homework 5/MDIO_HECHO_EN_CLASE_ESTE_SEMESTRE/testbench_mdio.v
`include "generador_mdio.v"
`include "objetivo_mdio.v"
  

// Testbench Code Goes here
module mdio_tb;

reg         clock, reset_generador, reset_objetivo, mdio_start_stb;
wire        mdio_in;
reg  [31:0] transaccion;
reg  [15:0] mdio_data_read;
wire [15:0] mdio_data_write;
wire [15:0] reg_addr;
wire        mdc, mdio_out, mdio_oe;

initial begin
	$dumpfile("mdio.vcd");
	$dumpvars(-1, U0);
	$dumpvars(-1, U1);
end


initial begin
  clock = 0;
  reset_generador = 0;
  reset_objetivo  =0;

  #20  reset_generador = 1;
       reset_objetivo  = 1;
  #120 reset_generador = 0;
  #160 reset_objetivo  =0; 
      mdio_start_stb = 0;
      transaccion = 32'h5BA73549;
  #320 mdio_start_stb = 1;
  #40  mdio_start_stb = 0;
  #7800 transaccion = 32'h65557777;
        mdio_data_read = 16'h2468;
  #160  mdio_start_stb = 1;
  #40   mdio_start_stb = 0;
  #8000 $finish;
end

always begin
 #20 clock = !clock;
end


generador_mdio U0 (
/*AUTOINST*/
		   // Outputs
		   .mdio_out		(mdio_out),
		   .mdio_oe		(mdio_oe),
		   .mdc			(mdc),
		   // Inputs
		   .clk			(clock),
		   .reset		(reset_generador),
		   .start_stb		(mdio_start_stb),
		   .mdio_in		(mdio_in),
		   .transaccion		(transaccion[31:0]));


objetivo_mdio U1 (
/*AUTOINST*/
		  // Outputs
		  .reg_addr		(reg_addr[4:0]),
		  .mdio_in		(mdio_in),
		  // Inputs
		  .mdc			(mdc),
		  .reset		(reset_objetivo),
		  .mdio_out		(mdio_out),
		  .mdio_oe		(mdio_oe),
		  .dato_leido    	(mdio_data_read[15:0]));


endmodule

Homeworks/Homework 5/MDIO_HECHO_EN_CLASE_ESTE_SEMESTRE/mdio.vcd
$date
	Sun Jun 16 14:38:36 2024
$end
$version
	Icarus Verilog
$end
$timescale
	1s
$end
$scope module mdio_tb $end
$scope module U0 $end
$var wire 1 ! clk $end
$var wire 1 " posedge_mdc $end
$var wire 1 # reset $end
$var wire 1 $ start_stb $end
$var wire 32 % transaccion [31:0] $end
$var wire 1 & mdio_in $end
$var wire 1 ' mdc $end
$var wire 1 ( lectura $end
$var wire 1 ) iniciar $end
$var wire 1 * escritura $end
$var parameter 32 + DIV_FREQ $end
$var parameter 3 , ESCRITURA $end
$var parameter 3 - INICIO $end
$var parameter 3 . LECTURA $end
$var reg 5 / cuenta_bits [4:0] $end
$var reg 16 0 dato_leido [15:0] $end
$var reg 2 1 div_freq [1:0] $end
$var reg 3 2 estado [2:0] $end
$var reg 1 3 mdc_anterior $end
$var reg 1 4 mdio_oe $end
$var reg 1 5 mdio_out $end
$var reg 5 6 prox_cuenta_bits [4:0] $end
$var reg 3 7 prox_estado [2:0] $end
$var reg 1 8 prox_mdio_out $end
$var reg 1 9 start_stb_d $end
$var reg 1 : start_stb_reg $end
$upscope $end
$upscope $end
$scope module mdio_tb $end
$scope module U1 $end
$var wire 16 ; dato_leido [15:0] $end
$var wire 1 ' mdc $end
$var wire 1 4 mdio_oe $end
$var wire 1 5 mdio_out $end
$var wire 1 < reset $end
$var wire 2 = start [1:0] $end
$var wire 5 > reg_addr [4:0] $end
$var wire 5 ? phy_addr [4:0] $end
$var wire 2 @ op [1:0] $end
$var wire 1 A lectura $end
$var wire 1 B escritura $end
$var parameter 3 C ENVIAR_BITS $end
$var parameter 3 D INICIO $end
$var parameter 3 E RECIBIR_BITS $end
$var reg 5 F cuenta_bits [4:0] $end
$var reg 3 G estado [2:0] $end
$var reg 1 & mdio_in $end
$var reg 5 H prox_cuenta_bits [4:0] $end
$var reg 3 I prox_estado [2:0] $end
$var reg 32 J transaccion [31:0] $end
$upscope $end
$upscope $end
$enddefinitions $end
$comment Show the parameter values. $end
$dumpall
b10 E
b1 D
b100 C
b100 .
b1 -
b10 ,
b10 +
$end
#0
$dumpvars
bx J
bx I
bx H
bx G
bx F
xB
xA
bx @
b0xxxx ?
bx >
bx =
0<
bx ;
x:
x9
x8
bx 7
bx 6
x5
x4
x3
bx 2
bx 1
bx 0
bx /
x*
x)
x(
x'
x&
bx %
x$
0#
x"
0!
$end
#20
0"
0'
04
08
b0 6
b1 7
09
0:
05
03
b0 1
b0 /
b1 2
1!
1<
1#
#40
0!
#60
1!
#80
0!
#100
1!
#120
0!
#140
x:
b1 1
1!
0#
#160
0!
#180
b0 H
b1 I
b0 F
b1 G
1"
1'
x9
b10 1
1!
#200
0!
#220
0"
13
b11 1
1!
#240
0!
#260
0'
b0 1
1!
#280
0!
#300
0:
03
b1 1
1)
1*
0(
1!
b1011011101001110011010101001001 %
0$
0<
#320
0!
#340
1"
1'
09
b10 1
1!
#360
0!
#380
0"
13
b11 1
1!
#400
0!
#420
0'
b0 1
1!
#440
0!
#460
03
b1 1
1!
#480
0!
#500
1"
1'
b10 1
1!
#520
0!
#540
0"
13
b11 1
1!
#560
0!
#580
0'
b0 1
1!
#600
0!
#620
1:
03
b1 1
1!
1$
#640
0!
#660
b10 7
1"
1'
19
0:
b10 1
1!
0$
#680
0!
#700
b10 I
0"
b0 6
14
09
13
b11 1
b10 2
1!
#720
0!
#740
0'
b0 1
1!
#760
0!
#780
03
b1 1
1!
#800
0!
#820
b0x =
b0xxxxxxxxxxxxxxxxxxxxxxxxxxxxxxx J
b1 H
b10 G
b1 6
1"
1'
b10 1
1!
#840
0!
#860
0"
08
b1 6
13
b11 1
b1 /
1!
#880
0!
#900
0'
b0 1
1!
#920
0!
#940
03
b1 1
1!
#960
0!
#980
b0 =
b0xxxxxxxxxxxxxxxxxxxxxxxxxxxxxx J
b10 H
b1 F
18
b10 6
1"
1'
b10 1
1!
#1000
0!
#1020
b1 =
b1xxxxxxxxxxxxxxxxxxxxxxxxxxxxxx J
b10 H
0"
18
b10 6
15
13
b11 1
b10 /
1!
#1040
0!
#1060
0'
b0 1
1!
#1080
0!
#1100
03
b1 1
1!
#1120
0!
#1140
0B
b1x @
b11xxxxxxxxxxxxxxxxxxxxxxxxxxxxx J
b11 H
b10 F
08
b11 6
1"
1'
b10 1
1!
#1160
0!
#1180
0A
xB
b0x @
b10xxxxxxxxxxxxxxxxxxxxxxxxxxxxx J
b11 H
0"
08
b11 6
05
13
b11 1
b11 /
1!
#1200
0!
#1220
0'
b0 1
1!
#1240
0!
#1260
03
b1 1
1!
#1280
0!
#1300
0B
b0 @
b100xxxxxxxxxxxxxxxxxxxxxxxxxxxx J
b100 H
b11 F
18
b100 6
1"
1'
b10 1
1!
#1320
0!
#1340
1B
b1 @
b101xxxxxxxxxxxxxxxxxxxxxxxxxxxx J
b100 H
0"
b100 6
15
13
b11 1
b100 /
1!
#1360
0!
#1380
0'
b0 1
1!
#1400
0!
#1420
03
b1 1
1!
#1440
0!
#1460
b1xxx ?
b1011xxxxxxxxxxxxxxxxxxxxxxxxxxx J
b101 H
b100 F
b101 6
1"
1'
b10 1
1!
#1480
0!
#1500
0"
18
b101 6
13
b11 1
b101 /
1!
#1520
0!
#1540
0'
b0 1
1!
#1560
0!
#1580
03
b1 1
1!
#1600
0!
#1620
b11xx ?
b10111xxxxxxxxxxxxxxxxxxxxxxxxxx J
b110 H
b101 F
08
b110 6
1"
1'
b10 1
1!
#1640
0!
#1660
b10xx ?
b10110xxxxxxxxxxxxxxxxxxxxxxxxxx J
b110 H
0"
08
b110 6
05
13
b11 1
b110 /
1!
#1680
0!
#1700
0'
b0 1
1!
#1720
0!
#1740
03
b1 1
1!
#1760
0!
#1780
b100x ?
b101100xxxxxxxxxxxxxxxxxxxxxxxxx J
b111 H
b110 F
18
b111 6
1"
1'
b10 1
1!
#1800
0!
#1820
b101x ?
b101101xxxxxxxxxxxxxxxxxxxxxxxxx J
b111 H
0"
b111 6
15
13
b11 1
b111 /
1!
#1840
0!
#1860
0'
b0 1
1!
#1880
0!
#1900
03
b1 1
1!
#1920
0!
#1940
b1011 ?
b1xxxx >
b1011011xxxxxxxxxxxxxxxxxxxxxxxx J
b1000 H
b111 F
b1000 6
1"
1'
b10 1
1!
#1960
0!
#1980
0"
b1000 6
13
b11 1
b1000 /
1!
#2000
0!
#2020
0'
b0 1
1!
#2040
0!
#2060
03
b1 1
1!
#2080
0!
#2100
b11xxx >
b10110111xxxxxxxxxxxxxxxxxxxxxxx J
b1001 H
b1000 F
b1001 6
1"
1'
b10 1
1!
#2120
0!
#2140
0"
18
b1001 6
13
b11 1
b1001 /
1!
#2160
0!
#2180
0'
b0 1
1!
#2200
0!
#2220
03
b1 1
1!
#2240
0!
#2260
b111xx >
b101101111xxxxxxxxxxxxxxxxxxxxxx J
b1010 H
b1001 F
08
b1010 6
1"
1'
b10 1
1!
#2280
0!
#2300
b110xx >
b101101110xxxxxxxxxxxxxxxxxxxxxx J
b1010 H
0"
08
b1010 6
05
13
b11 1
b1010 /
1!
#2320
0!
#2340
0'
b0 1
1!
#2360
0!
#2380
03
b1 1
1!
#2400
0!
#2420
b1100x >
b1011011100xxxxxxxxxxxxxxxxxxxxx J
b1011 H
b1010 F
18
b1011 6
1"
1'
b10 1
1!
#2440
0!
#2460
b1101x >
b1011011101xxxxxxxxxxxxxxxxxxxxx J
b1011 H
0"
18
b1011 6
15
13
b11 1
b1011 /
1!
#2480
0!
#2500
0'
b0 1
1!
#2520
0!
#2540
03
b1 1
1!
#2560
0!
#2580
b11011 >
b10110111011xxxxxxxxxxxxxxxxxxxx J
b1100 H
b1011 F
08
b1100 6
1"
1'
b10 1
1!
#2600
0!
#2620
b11010 >
b10110111010xxxxxxxxxxxxxxxxxxxx J
b1100 H
0"
b1100 6
05
13
b11 1
b1100 /
1!
#2640
0!
#2660
0'
b0 1
1!
#2680
0!
#2700
03
b1 1
1!
#2720
0!
#2740
b101101110100xxxxxxxxxxxxxxxxxxx J
b1101 H
b1100 F
b1101 6
1"
1'
b10 1
1!
#2760
0!
#2780
0"
08
b1101 6
13
b11 1
b1101 /
1!
#2800
0!
#2820
0'
b0 1
1!
#2840
0!
#2860
03
b1 1
1!
#2880
0!
#2900
b1011011101000xxxxxxxxxxxxxxxxxx J
b1110 H
b1101 F
18
b1110 6
1"
1'
b10 1
1!
#2920
0!
#2940
b1011011101001xxxxxxxxxxxxxxxxxx J
b1110 H
0"
b1110 6
15
13
b11 1
b1110 /
1!
#2960
0!
#2980
0'
b0 1
1!
#3000
0!
#3020
03
b1 1
1!
#3040
0!
#3060
b10110111010011xxxxxxxxxxxxxxxxx J
b1111 H
b1110 F
b1111 6
1"
1'
b10 1
1!
#3080
0!
#3100
0"
b1111 6
13
b11 1
b1111 /
1!
#3120
0!
#3140
0'
b0 1
1!
#3160
0!
#3180
03
b1 1
1!
#3200
0!
#3220
b101101110100111xxxxxxxxxxxxxxxx J
b10000 H
b1111 F
b10000 6
1"
1'
b10 1
1!
#3240
0!
#3260
0"
18
b10000 6
13
b11 1
b10000 /
1!
#3280
0!
#3300
0'
b0 1
1!
#3320
0!
#3340
03
b1 1
1!
#3360
0!
#3380
b1011011101001111xxxxxxxxxxxxxxx J
b10001 H
b10000 F
08
b10001 6
1"
1'
b10 1
1!
#3400
0!
#3420
b1011011101001110xxxxxxxxxxxxxxx J
b10001 H
0"
b10001 6
05
13
b11 1
b10001 /
1!
#3440
0!
#3460
0'
b0 1
1!
#3480
0!
#3500
03
b1 1
1!
#3520
0!
#3540
b10110111010011100xxxxxxxxxxxxxx J
b10010 H
b10001 F
b10010 6
1"
1'
b10 1
1!
#3560
0!
#3580
0"
08
b10010 6
13
b11 1
b10010 /
1!
#3600
0!
#3620
0'
b0 1
1!
#3640
0!
#3660
03
b1 1
1!
#3680
0!
#3700
b101101110100111000xxxxxxxxxxxxx J
b10011 H
b10010 F
18
b10011 6
1"
1'
b10 1
1!
#3720
0!
#3740
b101101110100111001xxxxxxxxxxxxx J
b10011 H
0"
b10011 6
15
13
b11 1
b10011 /
1!
#3760
0!
#3780
0'
b0 1
1!
#3800
0!
#3820
03
b1 1
1!
#3840
0!
#3860
b1011011101001110011xxxxxxxxxxxx J
b10100 H
b10011 F
b10100 6
1"
1'
b10 1
1!
#3880
0!
#3900
0"
18
b10100 6
13
b11 1
b10100 /
1!
#3920
0!
#3940
0'
b0 1
1!
#3960
0!
#3980
03
b1 1
1!
#4000
0!
#4020
b10110111010011100111xxxxxxxxxxx J
b10101 H
b10100 F
08
b10101 6
1"
1'
b10 1
1!
#4040
0!
#4060
b10110111010011100110xxxxxxxxxxx J
b10101 H
0"
08
b10101 6
05
13
b11 1
b10101 /
1!
#4080
0!
#4100
0'
b0 1
1!
#4120
0!
#4140
03
b1 1
1!
#4160
0!
#4180
b101101110100111001100xxxxxxxxxx J
b10110 H
b10101 F
18
b10110 6
1"
1'
b10 1
1!
#4200
0!
#4220
b101101110100111001101xxxxxxxxxx J
b10110 H
0"
18
b10110 6
15
13
b11 1
b10110 /
1!
#4240
0!
#4260
0'
b0 1
1!
#4280
0!
#4300
03
b1 1
1!
#4320
0!
#4340
b1011011101001110011011xxxxxxxxx J
b10111 H
b10110 F
08
b10111 6
1"
1'
b10 1
1!
#4360
0!
#4380
b1011011101001110011010xxxxxxxxx J
b10111 H
0"
08
b10111 6
05
13
b11 1
b10111 /
1!
#4400
0!
#4420
0'
b0 1
1!
#4440
0!
#4460
03
b1 1
1!
#4480
0!
#4500
b10110111010011100110100xxxxxxxx J
b11000 H
b10111 F
18
b11000 6
1"
1'
b10 1
1!
#4520
0!
#4540
b10110111010011100110101xxxxxxxx J
b11000 H
0"
18
b11000 6
15
13
b11 1
b11000 /
1!
#4560
0!
#4580
0'
b0 1
1!
#4600
0!
#4620
03
b1 1
1!
#4640
0!
#4660
b101101110100111001101011xxxxxxx J
b11001 H
b11000 F
08
b11001 6
1"
1'
b10 1
1!
#4680
0!
#4700
b101101110100111001101010xxxxxxx J
b11001 H
0"
08
b11001 6
05
13
b11 1
b11001 /
1!
#4720
0!
#4740
0'
b0 1
1!
#4760
0!
#4780
03
b1 1
1!
#4800
0!
#4820
b1011011101001110011010100xxxxxx J
b11010 H
b11001 F
18
b11010 6
1"
1'
b10 1
1!
#4840
0!
#4860
b1011011101001110011010101xxxxxx J
b11010 H
0"
18
b11010 6
15
13
b11 1
b11010 /
1!
#4880
0!
#4900
0'
b0 1
1!
#4920
0!
#4940
03
b1 1
1!
#4960
0!
#4980
b10110111010011100110101011xxxxx J
b11011 H
b11010 F
08
b11011 6
1"
1'
b10 1
1!
#5000
0!
#5020
b10110111010011100110101010xxxxx J
b11011 H
0"
b11011 6
05
13
b11 1
b11011 /
1!
#5040
0!
#5060
0'
b0 1
1!
#5080
0!
#5100
03
b1 1
1!
#5120
0!
#5140
b101101110100111001101010100xxxx J
b11100 H
b11011 F
b11100 6
1"
1'
b10 1
1!
#5160
0!
#5180
0"
08
b11100 6
13
b11 1
b11100 /
1!
#5200
0!
#5220
0'
b0 1
1!
#5240
0!
#5260
03
b1 1
1!
#5280
0!
#5300
b1011011101001110011010101000xxx J
b11101 H
b11100 F
18
b11101 6
1"
1'
b10 1
1!
#5320
0!
#5340
b1011011101001110011010101001xxx J
b11101 H
0"
18
b11101 6
15
13
b11 1
b11101 /
1!
#5360
0!
#5380
0'
b0 1
1!
#5400
0!
#5420
03
b1 1
1!
#5440
0!
#5460
b10110111010011100110101010011xx J
b11110 H
b11101 F
08
b11110 6
1"
1'
b10 1
1!
#5480
0!
#5500
b10110111010011100110101010010xx J
b11110 H
0"
b11110 6
05
13
b11 1
b11110 /
1!
#5520
0!
#5540
0'
b0 1
1!
#5560
0!
#5580
03
b1 1
1!
#5600
0!
#5620
b101101110100111001101010100100x J
b11111 H
b11110 F
b11111 6
1"
1'
b10 1
1!
#5640
0!
#5660
0"
b10 7
08
b11111 6
13
b11 1
b11111 /
1!
#5680
0!
#5700
0'
b0 1
1!
#5720
0!
#5740
03
b1 1
1!
#5760
0!
#5780
b1 I
b1011011101001110011010101001000 J
b0 H
b11111 F
b1 7
18
b0 6
1"
1'
b10 1
1!
#5800
0!
#5820
b1011011101001110011010101001001 J
b0 H
b1 I
0"
04
15
13
b11 1
b0 /
b1 2
1!
#5840
0!
#5860
0'
b0 1
1!
#5880
0!
#5900
03
b1 1
1!
#5920
0!
#5940
b0 F
b1 G
1"
1'
b10 1
1!
#5960
0!
#5980
0"
13
b11 1
1!
#6000
0!
#6020
0'
b0 1
1!
#6040
0!
#6060
03
b1 1
1!
#6080
0!
#6100
1"
1'
b10 1
1!
#6120
0!
#6140
0"
13
b11 1
1!
#6160
0!
#6180
0'
b0 1
1!
#6200
0!
#6220
03
b1 1
1!
#6240
0!
#6260
1"
1'
b10 1
1!
#6280
0!
#6300
0"
13
b11 1
1!
#6320
0!
#6340
0'
b0 1
1!
#6360
0!
#6380
03
b1 1
1!
#6400
0!
#6420
1"
1'
b10 1
1!
#6440
0!
#6460
0"
13
b11 1
1!
#6480
0!
#6500
0'
b0 1
1!
#6520
0!
#6540
03
b1 1
1!
#6560
0!
#6580
1"
1'
b10 1
1!
#6600
0!
#6620
0"
13
b11 1
1!
#6640
0!
#6660
0'
b0 1
1!
#6680
0!
#6700
03
b1 1
1!
#6720
0!
#6740
1"
1'
b10 1
1!
#6760
0!
#6780
0"
13
b11 1
1!
#6800
0!
#6820
0'
b0 1
1!
#6840
0!
#6860
03
b1 1
1!
#6880
0!
#6900
1"
1'
b10 1
1!
#6920
0!
#6940
0"
13
b11 1
1!
#6960
0!
#6980
0'
b0 1
1!
#7000
0!
#7020
03
b1 1
1!
#7040
0!
#7060
1"
1'
b10 1
1!
#7080
0!
#7100
0"
13
b11 1
1!
#7120
0!
#7140
0'
b0 1
1!
#7160
0!
#7180
03
b1 1
1!
#7200
0!
#7220
1"
1'
b10 1
1!
#7240
0!
#7260
0"
13
b11 1
1!
#7280
0!
#7300
0'
b0 1
1!
#7320
0!
#7340
03
b1 1
1!
#7360
0!
#7380
1"
1'
b10 1
1!
#7400
0!
#7420
0"
13
b11 1
1!
#7440
0!
#7460
0'
b0 1
1!
#7480
0!
#7500
03
b1 1
1!
#7520
0!
#7540
1"
1'
b10 1
1!
#7560
0!
#7580
0"
13
b11 1
1!
#7600
0!
#7620
0'
b0 1
1!
#7640
0!
#7660
03
b1 1
1!
#7680
0!
#7700
1"
1'
b10 1
1!
#7720
0!
#7740
0"
13
b11 1
1!
#7760
0!
#7780
0'
b0 1
1!
#7800
0!
#7820
03
b1 1
1!
#7840
0!
#7860
1"
1'
b10 1
1!
#7880
0!
#7900
0"
13
b11 1
1!
#7920
0!
#7940
0'
b0 1
1!
#7960
0!
#7980
03
b1 1
1!
#8000
0!
#8020
1"
1'
b10 1
1!
#8040
0!
#8060
0"
13
b11 1
1!
#8080
0!
#8100
0'
b0 1
1!
#8120
0!
#8140
03
b1 1
1!
#8160
0!
#8180
1"
1'
b10 1
1!
#8200
0!
#8220
0"
13
b11 1
1!
#8240
0!
#8260
0'
b0 1
1!
#8280
0!
#8300
03
b1 1
1!
#8320
0!
#8340
1"
1'
b10 1
1!
#8360
0!
#8380
0"
13
b11 1
1!
#8400
0!
#8420
0'
b0 1
1!
#8440
0!
#8460
03
b1 1
0*
1(
1!
b10010001101000 ;
b1100101010101010111011101110111 %
#8480
0!
#8500
1"
1'
b10 1
1!
#8520
0!
#8540
0"
13
b11 1
1!
#8560
0!
#8580
0'
b0 1
1!
#8600
0!
#8620
1:
03
b1 1
1!
1$
#8640
0!
#8660
b100 7
1"
1'
19
0:
b10 1
1!
0$
#8680
0!
#8700
b10 I
0"
b0 6
18
14
09
13
b11 1
b100 2
1!
#8720
0!
#8740
0'
b0 1
1!
#8760
0!
#8780
03
b1 1
1!
#8800
0!
#8820
b11 =
b11011011101001110011010101001001 J
b1 H
b10 G
b1 6
08
1"
1'
b10 1
1!
#8840
0!
#8860
b1 =
b1011011101001110011010101001001 J
b1 H
0"
b1 6
08
05
13
b11 1
b1 /
1!
#8880
0!
#8900
0'
b0 1
1!
#8920
0!
#8940
03
b1 1
1!
#8960
0!
#8980
b0 =
b11011101001110011010101001001 J
b10 H
b1 F
b10 6
18
1"
1'
b10 1
1!
#9000
0!
#9020
b1 =
b1011011101001110011010101001001 J
b10 H
0"
b10 6
15
13
b11 1
b10 /
1!
#9040
0!
#9060
0'
b0 1
1!
#9080
0!
#9100
03
b1 1
1!
#9120
0!
#9140
0B
b11 @
b1111011101001110011010101001001 J
b11 H
b10 F
b11 6
1"
1'
b10 1
1!
#9160
0!
#9180
0"
b11 6
18
13
b11 1
b11 /
1!
#9200
0!
#9220
0'
b0 1
1!
#9240
0!
#9260
03
b1 1
1!
#9280
0!
#9300
b100 H
b11 F
b100 6
08
1"
1'
b10 1
1!
#9320
0!
#9340
1A
b10 @
b1101011101001110011010101001001 J
b100 H
0"
b100 6
05
13
b11 1
b100 /
1!
#9360
0!
#9380
0'
b0 1
1!
#9400
0!
#9420
03
b1 1
1!
#9440
0!
#9460
b11 ?
b1100011101001110011010101001001 J
b101 H
b100 F
b101 6
1"
1'
b10 1
1!
#9480
0!
#9500
0"
b101 6
08
13
b11 1
b101 /
1!
#9520
0!
#9540
0'
b0 1
1!
#9560
0!
#9580
03
b1 1
1!
#9600
0!
#9620
b110 H
b101 F
b110 6
18
1"
1'
b10 1
1!
#9640
0!
#9660
b111 ?
b1100111101001110011010101001001 J
b110 H
0"
b110 6
18
15
13
b11 1
b110 /
1!
#9680
0!
#9700
0'
b0 1
1!
#9720
0!
#9740
03
b1 1
1!
#9760
0!
#9780
b111 H
b110 F
b111 6
08
1"
1'
b10 1
1!
#9800
0!
#9820
b101 ?
b1100101101001110011010101001001 J
b111 H
0"
b111 6
08
05
13
b11 1
b111 /
1!
#9840
0!
#9860
0'
b0 1
1!
#9880
0!
#9900
03
b1 1
1!
#9920
0!
#9940
b100 ?
b1010 >
b1100100101001110011010101001001 J
b1000 H
b111 F
b1000 6
18
1"
1'
b10 1
1!
#9960
0!
#9980
b101 ?
b11010 >
b1100101101001110011010101001001 J
b1000 H
0"
b1000 6
18
15
13
b11 1
b1000 /
1!
#10000
0!
#10020
0'
b0 1
1!
#10040
0!
#10060
03
b1 1
1!
#10080
0!
#10100
b1001 H
b1000 F
b1001 6
08
1"
1'
b10 1
1!
#10120
0!
#10140
b10010 >
b1100101001001110011010101001001 J
b1001 H
0"
b1001 6
08
05
13
b11 1
b1001 /
1!
#10160
0!
#10180
0'
b0 1
1!
#10200
0!
#10220
03
b1 1
1!
#10240
0!
#10260
b1010 H
b1001 F
b1010 6
18
1"
1'
b10 1
1!
#10280
0!
#10300
b10110 >
b1100101011001110011010101001001 J
b1010 H
0"
b1010 6
18
15
13
b11 1
b1010 /
1!
#10320
0!
#10340
0'
b0 1
1!
#10360
0!
#10380
03
b1 1
1!
#10400
0!
#10420
b1011 H
b1010 F
b1011 6
08
1"
1'
b10 1
1!
#10440
0!
#10460
b10100 >
b1100101010001110011010101001001 J
b1011 H
0"
b1011 6
08
05
13
b11 1
b1011 /
1!
#10480
0!
#10500
0'
b0 1
1!
#10520
0!
#10540
03
b1 1
1!
#10560
0!
#10580
b1100 H
b1011 F
b1100 6
18
1"
1'
b10 1
1!
#10600
0!
#10620
b10101 >
b1100101010101110011010101001001 J
b1100 H
0"
b1100 6
18
15
13
b11 1
b1100 /
1!
#10640
0!
#10660
0'
b0 1
1!
#10680
0!
#10700
03
b1 1
1!
#10720
0!
#10740
b1100101010111110011010101001001 J
b1101 H
b1100 F
b1101 6
08
1"
1'
b10 1
1!
#10760
0!
#10780
b1100101010101110011010101001001 J
b1101 H
0"
b1101 6
08
05
13
b11 1
b1101 /
1!
#10800
0!
#10820
0'
b0 1
1!
#10840
0!
#10860
03
b1 1
1!
#10880
0!
#10900
b1100101010100110011010101001001 J
b1110 H
b1101 F
b1110 6
18
1"
1'
b10 1
1!
#10920
0!
#10940
b1100101010101110011010101001001 J
b1110 H
0"
b1110 6
18
15
13
b11 1
b1110 /
1!
#10960
0!
#10980
0'
b0 1
1!
#11000
0!
#11020
03
b1 1
1!
#11040
0!
#11060
b1111 H
b1110 F
b1111 6
08
1"
1'
b10 1
1!
#11080
0!
#11100
b1100101010101010011010101001001 J
b1111 H
0"
b1111 6
08
05
13
b11 1
b1111 /
1!
#11120
0!
#11140
0'
b0 1
1!
#11160
0!
#11180
03
b1 1
1!
#11200
0!
#11220
b100 I
b1100101010101000011010101001001 J
b10000 H
b1111 F
b10000 6
18
1"
1'
b10 1
1!
#11240
0!
#11260
b1100101010101010011010101001001 J
b10000 H
b100 I
0"
b10000 6
18
04
15
13
b11 1
b10000 /
1!
#11280
0!
#11300
0'
b0 1
1!
#11320
0!
#11340
03
b1 1
1!
#11360
0!
